Workbook

Sheet FBCJ Jul-Des 2025
A1: PT SMART Tbk. (Downstream | E1: CASH JOURNAL
A2: Jakarta | E2: R124:KAS BESAR | H2: Rupiah
A3: 3300 | E3: 3301 | F3: 10000001
A4: 01.07.2025 | C4: - | D4: 31.12.2025
J6: 45000000 | M6: IDR
B8: Pstng Date | E8: Reference | F8: Business Trans. | H8: Expenses | I8: Receipt recipient | K8: Rev.Doc.No
B9: G/L acct | C9: G/L acct | D9: Cost Ctr | G9: Text for item | N9: G/L acct | O9: Cost Ctr
B10: 07.07.2025 | C10: 70107300 | D10: R124D1HRDV | E10: 510/PPC/VI/2025 | F10: OLAHRAGA DAN PERMAINAN | G10: BY OLAHRAGA 20/06/2025 | H10: 400000 | I10: DEWI PRIYANTI | N10: =+C10 -> 70107300 | O10: =+D10 -> R124D1HRDV
B11: 07.07.2025 | C11: 70009110 | D11: P206D1SLSS | E11: 498/PPC/VI/2025 | F11: SURVEY DAN ANALISA | G11: BY COO KADIN ASSUDAMAL EBP 2411775352 | H11: 100000 | I11: ORIENTASI | N11: =+C11 -> 70009110 | O11: =+D11 -> P206D1SLSS
B12: 07.07.2025 | C12: 70009110 | D12: P206D1SLSS | E12: 498/PPC/VI/2025 | F12: SURVEY DAN ANALISA | G12: BY COO KADIN ASSUDAMAL EBP 2411775353 | H12: 100000 | I12: ORIENTASI | N12: =+C12 -> 70009110 | O12: =+D12 -> P206D1SLSS
B13: 07.07.2025 | C13: 70009110 | D13: P206D1SLSS | E13: 498/PPC/VI/2025 | F13: SURVEY DAN ANALISA | G13: BY COO KADIN ASSUDAMAL EBP 2411775354 | H13: 150000 | I13: ORIENTASI | N13: =+C13 -> 70009110 | O13: =+D13 -> P206D1SLSS
B14: 07.07.2025 | C14: 70009110 | D14: C206D1SLSS | E14: 498/PPC/VI/2025 | F14: SURVEY DAN ANALISA | G14: BY COO KADIN ASSUDAMAL EBP 2411775666 | H14: 100000 | I14: ORIENTASI | N14: =+C14 -> 70009110 | O14: =+D14 -> C206D1SLSS
B15: 07.07.2025 | C15: 70009110 | D15: P206D1SLSS | E15: 498/PPC/VI/2025 | F15: SURVEY DAN ANALISA | G15: BY COO KADIN ASSUDAMAL EBP 2411775667 | H15: 100000 | I15: ORIENTASI | N15: =+C15 -> 70009110 | O15: =+D15 -> P206D1SLSS
B16: 07.07.2025 | C16: 70009110 | D16: P206D1SLSS | E16: 498/PPC/VI/2025 | F16: SURVEY DAN ANALISA | G16: BY COO KADIN ASSUDAMAL EBP 2411775668 | H16: 100000 | I16: ORIENTASI | N16: =+C16 -> 70009110 | O16: =+D16 -> P206D1SLSS
B17: 07.07.2025 | C17: 70009110 | D17: C206D1SLSS | E17: 498/PPC/VI/2025 | F17: SURVEY DAN ANALISA | G17: BY COO KADIN ASSUDAMAL EBP 2411775669 | H17: 100000 | I17: ORIENTASI | N17: =+C17 -> 70009110 | O17: =+D17 -> C206D1SLSS
B18: 07.07.2025 | C18: 70009110 | D18: P206D1SLSS | E18: 498/PPC/VI/2025 | F18: SURVEY DAN ANALISA | G18: BY COO KADIN ASSUDAMAL EBP 2411775670 | H18: 100000 | I18: ORIENTASI | N18: =+C18 -> 70009110 | O18: =+D18 -> P206D1SLSS
B19: 07.07.2025 | C19: 70009110 | D19: P206D1SLSS | E19: 498/PPC/VI/2025 | F19: SURVEY DAN ANALISA | G19: BY COO KADIN ASSUDAMAL EBP 2411775671 | H19: 100000 | I19: ORIENTASI | N19: =+C19 -> 70009110 | O19: =+D19 -> P206D1SLSS
B20: 07.07.2025 | C20: 70009110 | D20: P206D1SLSS | E20: 498/PPC/VI/2025 | F20: SURVEY DAN ANALISA | G20: BY HC BPOM AL JAZIRA EBP 2411775754 | H20: 50000 | I20: ORIENTASI | N20: =+C20 -> 70009110 | O20: =+D20 -> P206D1SLSS
B21: 07.07.2025 | C21: 70101202 | D21: R124NSS | E21: 504/PPC/VI/2025 | F21: PEMEL.KEND&A.BERAT MATRL | G21: BY PEMBELIAN CAIRAN PENETRANT DAN CLEANER | H21: 940000 | I21: HADI SUPENO | N21: =+C21 -> 70101202 | O21: =+D21 -> R124NSS
... B148: 11.07.2025 | C148: 70009110 | D148: P206D1SLSS | E148: 558/PPC/VII/2025 | F148: SURVEY DAN ANALISA | G148: BY HC HOME CHAIN EBP 2411775613 | H148: 50000 | I148: SANTI | N148: =+C148 -> 70009110 | O148: =+D148 -> P206D1SLSS
B149: 11.07.2025 | C149: 16.07.2025 | D149: R124TCP | F149: BANK IN TRANSIT | H149: 0 | I149: PT. SMART Tbk | N149: =+C149 -> 16.07.2025 | O149: =+D149 -> R124TCP
B150: 16.07.2025 | C150: 70101114 | D150: R124TCP | F150: PBAIKN&PRAWATN PRABT MATR | G150: BY PEMB EXHAUST FAN, TIMP FLOOR MARKING | H150: 629000 | I150: ARDHIAN Y | N150: =+C150 -> 70101114 | O150: =+D150 -> R124TCP
B151: 16.07.2025 | C151: 70101202 | D151: R124REF3 | F151: PEMEL.KEND&A.BERAT MATRL | G151: BY PEMB WIPER SPRING U/ MOTOR POMPA F204 | H151: 303100 | I151: M. NUR HUDA | N151: =+C151 -> 70101202 | O151: =+D151 -> R124REF3
B152: 16.07.2025 | C152: 70107100 | D152: R124D1HRGA | F152: BIAYA MESS | G152: BY PDAM MESS PKTJAND JULI 2025 | H152: 290500 | I152: IFAN SAFRIANTO | N152: =+C152 -> 70107100 | O152: =+D152 -> R124D1HRGA
B153: 16.07.2025 | C153: 70108110 | D153: R124QMR | F153: PERLENGKAPAN FOTOCOPY | G153: BY CETAK POSTER, BANNER, TAGGING PRP | H153: 304800 | I153: LILA | N153: =+C153 -> 70108110 | O153: =+D153 -> R124QMR
B154: 16.07.2025 | C154: 70107300 | D154: R124D1HRDV | F154: OLAHRAGA DAN PERMAINAN | G154: BY OLAHRAGA 11/07/2025 | H154: 500000 | I154: DEWI PRIYANTI | N154: =+C154 -> 70107300 | O154: =+D154 -> R124D1HRDV
B155: 16.07.2025 | C155: 70107600 | D155: R124D1HRGA | F155: MAKANAN DAN MINUMAN | G155: BY SNACK KUNJUNGAN SLF | H155: 331500 | I155: IFAN SAFRIANTO | N155: =+C155 -> 70107600 | O155: =+D155 -> R124D1HRGA
B156: 16.07.2025 | C156: 70119300 | D156: R124D1PRCN | F156: UMUM & ADMIN LAIN | G156: BY PEMB MATERAI | H156: 1000000 | I156: ANTONIUS L | N156: =+C156 -> 70119300 | O156: =+D156 -> R124D1PRCN
B157: 16.07.2025 | C157: 70101102 | D157: R124REF | F157: PEMEL.BNGAN&PSARANA MATRL | G157: BY PEMB KUAS U/ CAT | H157: 153000 | I157: TRI SUMARNO | N157: =+C157 -> 70101102 | O157: =+D157 -> R124REF
B158: 16.07.2025 | C158: 70009110 | D158: P206D1SLSS | F158: SURVEY DAN ANALISA | G158: BY HC SG OILSEED EBP 2411776092 | H158: 50000 | I158: FELISIA | N158: =+C158 -> 70009110 | O158: =+D158 -> P206D1SLSS
B159: 16.07.2025 | C159: 70009110 | D159: P206D1SLSS | F159: SURVEY DAN ANALISA | G159: BY HC SG OILSEED EBP 2411776096 | H159: 50000 | I159: FELISIA | N159: =+C159 -> 70009110 | O159: =+D159 -> P206D1SLSS
B160: 16.07.2025 | C160: 70009110 | D160: P206D1SLSS | F160: SURVEY DAN ANALISA | G160: BY HC MONDELEZ EBP 2411776205 | H160: 50000 | I160: FELISIA | N160: =+C160 -> 70009110 | O160: =+D160 -> P206D1SLSS
B161: 16.07.2025 | C161: 70009110 | D161: P206D1SLSS | F161: SURVEY DAN ANALISA | G161: BY HC THAI GLICO EBP 2411776134 | H161: 50000 | I161: CHRISTIE ADRIAN | N161: =+C161 -> 70009110 | O161: =+D161 -> P206D1SLSS
... B178: 17.07.2025 | C178: 70107600 | D178: R124D1MGMT | F178: MAKANAN DAN MINUMAN | G178: BY KONSUMSI SC MEETING 17/07/2025 | H178: 500000 | I178: DEWI PRIYANTI | N178: =+C178 -> 70107600 | O178: =+D178 -> R124D1MGMT
B179: 25.07.2025 | C179: 70101202 | D179: R124WTT | E179: 571/PPC/VII/2025 | F179: PEMEL.KEND&A.BERAT MATRL | G179: BY PEMB NIPPLE SELANG PVC, ELBOW SS, DLL | H179: 991000 | I179: SUGIANTORO | N179: =+C179 -> 70101202 | O179: =+D179 -> R124WTT
B180: 25.07.2025 | C180: 70101114 | D180: R124NSS | E180: 577/PPC/VII/2025 | F180: PBAIKN&PRAWATN PRABT MATR | G180: BY PEMB TANGGA LIPAT TELESKOPIK | H180: 904127 | I180: HADI SUPENO | N180: =+C180 -> 70101114 | O180: =+D180 -> R124NSS
B181: 25.07.2025 | C181: 70009110 | D181: P206D1SLSS | E181: 587/PPC/VII/2025 | F181: SURVEY DAN ANALISA | G181: BY HC AST PVT EBP 2411776266 | H181: 50000 | I181: RIZKY R | N181: =+C181 -> 70009110 | O181: =+D181 -> P206D1SLSS
B182: 25.07.2025 | C182: 70009110 | D182: P206D1SLSS | E182: 587/PPC/VII/2025 | F182: SURVEY DAN ANALISA | G182: BY HC SG OILSEED EBP 2411775747 | H182: 50000 | I182: RIZKY R | N182: =+C182 -> 70009110 | O182: =+D182 -> P206D1SLSS
B183: 25.07.2025 | C183: 70009110 | D183: P206D1SLSS | E183: 587/PPC/VII/2025 | F183: SURVEY DAN ANALISA | G183: BY HC SG OILSEED EBP 2411776233 | H183: 50000 | I183: RIZKY R | N183: =+C183 -> 70009110 | O183: =+D183 -> P206D1SLSS
B184: 25.07.2025 | C184: 70009110 | D184: P206D1SLSS | E184: 587/PPC/VII/2025 | F184: SURVEY DAN ANALISA | G184: BY COO KADIN AST PVT EBP 2411776266 | H184: 200000 | I184: RIZKY R | N184: =+C184 -> 70009110 | O184: =+D184 -> P206D1SLSS
B185: 25.07.2025 | C185: 70115100 | D185: R124QCA | E185: 592/PPC/VII/2025 | F185: RISET/PENGEMBANGAN PRODUK | G185: BY SENSORY KFC, McD | H185: 301000 | I185: MEGAWATI | N185: =+C185 -> 70115100 | O185: =+D185 -> R124QCA
B186: 25.07.2025 | C186: 70101114 | D186: R124QCA | E186: 592/PPC/VII/2025 | F186: PBAIKN&PRAWATN PRABT MATR | G186: BY PEMB SLING | H186: 264000 | I186: MEGAWATI | N186: =+C186 -> 70101114 | O186: =+D186 -> R124QCA
B187: 25.07.2025 | C187: 70119300 | D187: R124QCA | E187: 592/PPC/VII/2025 | F187: UMUM & ADMIN LAIN | G187: BY ONGKIR SAMPLE KE QUALIS | H187: 44000 | I187: MEGAWATI | N187: =+C187 -> 70119300 | O187: =+D187 -> R124QCA
B188: 25.07.2025 | C188: 70009110 | D188: P206D1SLSS | E188: 593/PPC/VII/2025 | F188: SURVEY DAN ANALISA | G188: BY HC SG OILSEED EBP 2411775745 | H188: 50000 | I188: FELISIA | N188: =+C188 -> 70009110 | O188: =+D188 -> P206D1SLSS
B189: 25.07.2025 | C189: 70009110 | D189: P206D1SLSS | E189: 593/PPC/VII/2025 | F189: SURVEY DAN ANALISA | G189: BY HC SG OILSEED EBP 2411776321 | H189: 50000 | I189: FELISIA | N189: =+C189 -> 70009110 | O189: =+D189 -> P206D1SLSS
B190: 25.07.2025 | C190: 70009110 | D190: P206D1SLSS | E190: 593/PPC/VII/2025 | F190: SURVEY DAN ANALISA | G190: BY HC SG OILSEED EBP 2411776320 | H190: 50000 | I190: FELISIA | N190: =+C190 -> 70009110 | O190: =+D190 -> P206D1SLSS
... B238: 29.07.2025 | C238: 70101202 | D238: R124REF3 | E238: 528/PPV/VII/2025 | F238: PEMEL.KEND&A.BERAT MATRL | G238: BY PEMBELIAN B/M TWP SS | H238: 345000 | I238: MOH. HADI | N238: =+C238 -> 70101202 | O238: =+D238 -> R124REF3
B239: 29.07.2025 | C239: 29.07.2025 | D239: R124D1HRGA | E239: 528/PPV/VII/2025 | F239: UANG MUKA BIAYA | G239: BY FLANGE BADJA KARYA T FP 04002500197911271 | H239: 131000 | I239: MOH. HADI | N239: =+C239 -> 29.07.2025 | O239: =+D239 -> R124D1HRGA
B240: 29.07.2025 | C240: 04.08.2025 | D240: R124D1HRGA | F240: BANK IN TRANSIT | G240: PETTY CASH RUNGKUT SURABAYA PERIODE 15-29 JULI 25 | H240: 0 | I240: PT. SMART Tbk | N240: =+C240 -> 04.08.2025 | O240: =+D240 -> R124D1HRGA
B241: 04.08.2025 | C241: 70107100 | D241: R124D1HRGA | E241: 620/PPC/VII/2025 | F241: BIAYA MESS | G241: BY IURAN RT BULANAN 8 UNIT, PDK TJANDRA INDAH JUL | H241: 800000 | I241: IFAN SAFRIANTO | N241: =+C241 -> 70107100 | O241: =+D241 -> R124D1HRGA
B242: 04.08.2025 | C242: 70009110 | D242: P206D1SLSS | E242: 613/PPC/VII/2025 | F242: SURVEY DAN ANALISA | G242: BY HC SHENGRONG EBP/0725/0486-2411776274 | H242: 50000 | I242: SANTI | N242: =+C242 -> 70009110 | O242: =+D242 -> P206D1SLSS
B243: 04.08.2025 | C243: 70009110 | D243: P206D1SLSS | E243: 613/PPC/VII/2025 | F243: SURVEY DAN ANALISA | G243: BY HC HOME CHAIN EBP/0725/0488-2411776293 | H243: 50000 | I243: SANTI | N243: =+C243 -> 70009110 | O243: =+D243 -> P206D1SLSS
B244: 04.08.2025 | C244: 70009110 | D244: M204D1COMM | E244: 613/PPC/VII/2025 | F244: SURVEY DAN ANALISA | G244: BY HC NESTLE SENEGAL ETP/0725/0140/2411776136 | H244: 50000 | I244: SANTI | N244: =+C244 -> 70009110 | O244: =+D244 -> M204D1COMM
B245: 04.08.2025 | C245: 70009110 | D245: M204D1COMM | E245: 613/PPC/VII/2025 | F245: SURVEY DAN ANALISA | G245: BY HC NESTLE SENEGAL ETP/0725/0140/2411776137 | H245: 50000 | I245: SANTI | N245: =+C245 -> 70009110 | O245: =+D245 -> M204D1COMM
B246: 04.08.2025 | C246: 70009110 | D246: P206D1SLSS | E246: 613/PPC/VII/2025 | F246: SURVEY DAN ANALISA | G246: BY HC HOME CHAIN EBP/0625/0459-2411776133 | H246: 50000 | I246: SANTI | N246: =+C246 -> 70009110 | O246: =+D246 -> P206D1SLSS
B247: 04.08.2025 | C247: 70009110 | D247: P206D1SLSS | E247: 613/PPC/VII/2025 | F247: SURVEY DAN ANALISA | G247: BY HC HOCHEE EBP/0625/0462-2411776138 | H247: 50000 | I247: SANTI | N247: =+C247 -> 70009110 | O247: =+D247 -> P206D1SLSS
B248: 04.08.2025 | C248: 70009110 | D248: C206D1SLSS | E248: 613/PPC/VII/2025 | F248: SURVEY DAN ANALISA | G248: BY HC RAMFOOD EBP/0625/0453-2411776116 | H248: 50000 | I248: SANTI | N248: =+C248 -> 70009110 | O248: =+D248 -> C206D1SLSS
B249: 04.08.2025 | C249: 70009110 | D249: C206D1SLSS | E249: 613/PPC/VII/2025 | F249: SURVEY DAN ANALISA | G249: BY HC RAMFOOD EBP/0625/0454-2411776117 | H249: 50000 | I249: SANTI | N249: =+C249 -> 70009110 | O249: =+D249 -> C206D1SLSS
B250: 04.08.2025 | C250: 70009110 | D250: P206D1SLSS | E250: 613/PPC/VII/2025 | F250: SURVEY DAN ANALISA | G250: BY REPROSES HC HOME CHAIN EBP/0625/0454-2411776133 | H250: 50000 | I250: SANTI | N250: =+C250 -> 70009110 | O250: =+D250 -> P206D1SLSS
B251: 04.08.2025 | C251: 70009110 | D251: P206D1SLSS | E251: 613/PPC/VII/2025 | F251: SURVEY DAN ANALISA | G251: BY HC SUNNY EBP/0725/0485-2411776270 | H251: 50000 | I251: SANTI | N251: =+C251 -> 70009110 | O251: =+D251 -> P206D1SLSS
B252: 04.08.2025 | C252: 70106100 | D252: R124D1HRGA | E252: 622/PPC/VII/2025 | F252: TRANSPORTASI LOKAL | G252: BY TRANSPORTASI LOKAL 300725 | H252: 369000 | I252: MOH.ALAMSYAH | N252: =+C252 -> 70106100 | O252: =+D252 -> R124D1HRGA
... B394: 20.08.2025 | C394: 70101202 | D394: R124REF | E394: 645/PPC/VIII/25 | F394: PEMEL.KEND&A.BERAT MATRL | G394: BY PEMB SKUN, CONNECTOR LIGHT, NIPLE DRAT,DLL | H394: 604000 | I394: TRI SUMARNO | N394: =+C394 -> 70101202 | O394: =+D394 -> R124REF
B395: 20.08.2025 | C395: 20.08.2025 | D395: R124D1HRDV | E395: 645/PPC/VIII/25 | F395: UANG MUKA BIAYA | G395: BY STRAINER VALVE AMARTA T FP:04002500243246107 | H395: 280000 | I395: TRI SUMARNO | N395: =+C395 -> 20.08.2025 | O395: =+D395 -> R124D1HRDV
B396: 20.08.2025 | C396: 20.08.2025 | D396: R124D1HRDV | E396: 667/PPC/VIII/25 | F396: UANG MUKA BIAYA | G396: BY CHECK VALVE AMARTA T FP:04002500243246108 | H396: 650000 | I396: TRI SUMARNO | N396: =+C396 -> 20.08.2025 | O396: =+D396 -> R124D1HRDV
B397: 20.08.2025 | C397: 02.09.2025 | D397: R124D1HRDV | F397: BANK IN TRANSIT | G397: PETTY CASH RUNGKUT SURABAYA PERIODE 01-20 AGUST 25 | H397: 0 | I397: PT. SMART Tbk | N397: =+C397 -> 02.09.2025 | O397: =+D397 -> R124D1HRDV
B398: 02.09.2025 | C398: 70107300 | D398: R124D1HRDV | E398: 678/PPC/VIII/25 | F398: OLAHRAGA DAN PERMAINAN | G398: BY Olahraga cardio boxing 15 Agustus'25 | H398: 500000 | I398: DEWI PRIYANTI | N398: =+C398 -> 70107300 | O398: =+D398 -> R124D1HRDV
B399: 02.09.2025 | C399: 70009110 | D399: P206D1SLSC | E399: 690/PPC/VIII/25 | F399: SURVEY DAN ANALISA | G399: BY HC SG OILSEED EBP/0825/0596-241177690 | H399: 50000 | I399: FELLY | N399: =+C399 -> 70009110 | O399: =+D399 -> P206D1SLSC
B400: 02.09.2025 | C400: 70009110 | D400: P206D1SLSC | E400: 690/PPC/VIII/25 | F400: SURVEY DAN ANALISA | G400: BY HC XIAMEN AOZHI EBP/0825/0436-2411776918 | H400: 50000 | I400: FELLY | N400: =+C400 -> 70009110 | O400: =+D400 -> P206D1SLSC
B401: 02.09.2025 | C401: 70009110 | D401: P206D1SLSC | E401: 690/PPC/VIII/25 | F401: SURVEY DAN ANALISA | G401: BY HC HORGOS EBP/0825/0588-2411776862 | H401: 50000 | I401: FELLY | N401: =+C401 -> 70009110 | O401: =+D401 -> P206D1SLSC
B402: 02.09.2025 | C402: 70009110 | D402: P206D1SLSC | E402: 690/PPC/VIII/25 | F402: SURVEY DAN ANALISA | G402: BY HC FUJIAN NANAN EBP/0825/0580-2411776818 | H402: 50000 | I402: FELLY | N402: =+C402 -> 70009110 | O402: =+D402 -> P206D1SLSC
B403: 02.09.2025 | C403: 70009110 | D403: P206D1SLSC | E403: 690/PPC/VIII/25 | F403: SURVEY DAN ANALISA | G403: BY HC HORGOS EBP/0825/0620-2411776989 | H403: 50000 | I403: FELLY | N403: =+C403 -> 70009110 | O403: =+D403 -> P206D1SLSC
B404: 02.09.2025 | C404: 70009110 | D404: P206D1SLSS | E404: 692/PPC/VIII/25 | F404: SURVEY DAN ANALISA | G404: BY HC HORGOS BAIPENG 2411776885 | H404: 50000 | I404: FEBRINA RIZKIKA | N404: =+C404 -> 70009110 | O404: =+D404 -> P206D1SLSS
B405: 02.09.2025 | C405: 70009110 | D405: P206D1SLSS | E405: 692/PPC/VIII/25 | F405: SURVEY DAN ANALISA | G405: BY HC HORGOS BAIPENG 2411776884 | H405: 50000 | I405: FEBRINA RIZKIKA | N405: =+C405 -> 70009110 | O405: =+D405 -> P206D1SLSS
B406: 02.09.2025 | C406: 70009110 | D406: P206D1SLSS | E406: 692/PPC/VIII/25 | F406: SURVEY DAN ANALISA | G406: BY HC SG OIL SEED 2411776891 | H406: 50000 | I406: FEBRINA RIZKIKA | N406: =+C406 -> 70009110 | O406: =+D406 -> P206D1SLSS
B407: 02.09.2025 | C407: 70009110 | D407: P206D1SLSS | E407: 692/PPC/VIII/25 | F407: SURVEY DAN ANALISA | G407: BY HC HORGOS BAIPENG 2411776863 | H407: 50000 | I407: FEBRINA RIZKIKA | N407: =+C407 -> 70009110 | O407: =+D407 -> P206D1SLSS
B408: 02.09.2025 | C408: 70009110 | D408: P206D1SLSS | E408: 692/PPC/VIII/25 | F408: SURVEY DAN ANALISA | G408: BY HC GUANGDONG SHENGRONG 2411776775 | H408: 50000 | I408: FEBRINA RIZKIKA | N408: =+C408 -> 70009110 | O408: =+D408 -> P206D1SLSS
B409: 02.09.2025 | C409: 70009110 | D409: P206D1SLSS | E409: 692/PPC/VIII/25 | F409: SURVEY DAN ANALISA | G409: BY HC SG OILSEED 2411776838 | H409: 50000 | I409: FEBRINA RIZKIKA | N409: =+C409 -> 70009110 | O409: =+D409 -> P206D1SLSS
... B548: 15.09.2025 | C548: 70101202 | D548: R124REF | E548: 738/PPC/IX/25 | F548: PEMEL.KEND&A.BERAT MATRL | G548: BY PEMB. Bearing Fan BAC | H548: 800000 | I548: TRI SUMARNO | N548: =+C548 -> 70101202 | O548: =+D548 -> R124REF
B549: 15.09.2025 | C549: 15.09.2025 | D549: R124FRA | E549: 694/PPC/VIII/25 | F549: UANG MUKA BIAYA | G549: BY PEMB.PRESSR SWITCH HYDRANT FP04002500244949528 | H549: 690000 | I549: MOCH. TEKAD | N549: =+C549 -> 15.09.2025 | O549: =+D549 -> R124FRA
B550: 15.09.2025 | C550: 15.09.2025 | D550: R124FRA | E550: 699/PPC/VIII/25 | F550: UANG MUKA BIAYA | G550: BY PEMBELIAN DOUBLE NIPLE FP 04002500260289183 | H550: 40770 | I550: AKHMAD NIZAR | N550: =+C550 -> 15.09.2025 | O550: =+D550 -> R124FRA
B551: 15.09.2025 | C551: 15.09.2025 | D551: R124FRA | E551: 726/PPC/IX/25 | F551: UANG MUKA BIAYA | G551: BY PEMB. DUNLOP P.430& 5/16 NB FP04002500262634254 | H551: 321404 | I551: ANJAS A | N551: =+C551 -> 15.09.2025 | O551: =+D551 -> R124FRA
B552: 15.09.2025 | C552: 15.09.2025 | D552: R124FRA | E552: 697/PPC/VIII/25 | F552: UANG MUKA BIAYA | G552: BY PEMB. STRAIGHT MALE FP04002500259735097 | H552: 151679 | I552: MOH. BAIDOWI | N552: =+C552 -> 15.09.2025 | O552: =+D552 -> R124FRA
B553: 15.09.2025 | C553: 70101114 | D553: R124FRA | E553: 697/PPC/VIII/25 | F553: PBAIKN&PRAWATN PRABT MATR | G553: BY PEMB. SUNLIGHT 5PCS | H553: 61000 | I553: MOH. BAIDOWI | N553: =+C553 -> 70101114 | O553: =+D553 -> R124FRA
B554: 15.09.2025 | C554: 70101202 | D554: R124STTRK | E554: 741/PPC/IX/25 | F554: PEMEL.KEND&A.BERAT MATRL | G554: BY PERBAIKAN MOTOR POMPA KMSC & TANKI P10 | H554: 133500 | I554: MIFTAKHUL HUDA | N554: =+C554 -> 70101202 | O554: =+D554 -> R124STTRK
B555: 15.09.2025 | C555: 70107100 | D555: R124D1HRGA | E555: 737/PPC/IX/25 | F555: BIAYA MESS | G555: BY PDAM BULANAN MESS PT SMART PTI SEPT 25 | H555: 290500 | I555: IFAN SAFRIANTO | N555: =+C555 -> 70107100 | O555: =+D555 -> R124D1HRGA
B556: 15.09.2025 | C556: 70101202 | D556: C206D1SLSS | E556: 723/PPC/IX/25 | F556: PEMEL.KEND&A.BERAT MATRL | G556: BY PERAWATAN BERKALA KENDARAAN NOPOL L2167FT | H556: 430000 | I556: ALDI JAYA | N556: =+C556 -> 70101202 | O556: =+D556 -> C206D1SLSS
B557: 15.09.2025 | C557: 70101202 | D557: P206D1SLSS | E557: 720/PPC/IX/25 | F557: PEMEL.KEND&A.BERAT MATRL | G557: BY PERAWATAN BERKALA KENDARAAN NOPOL L2057EK | H557: 298000 | I557: ACH. ALFIAN | N557: =+C557 -> 70101202 | O557: =+D557 -> P206D1SLSS
B558: 15.09.2025 | C558: 01.10.2025 | D558: R124D1HRGA | F558: BANK IN TRANSIT | G558: PETTY CASH RUNGKUT SURABAYA PERIODE 01-15 SEPT 25 | H558: 0 | I558: PT. SMART Tbk | N558: =+C558 -> 01.10.2025 | O558: =+D558 -> R124D1HRGA
B559: 01.10.2025 | C559: 70101102 | D559: R124D1HRGA | E559: 746/PPC/IX/2025 | F559: PEMEL.BNGAN&PSARANA MATRL | G559: BY PEMB SIKA GROUT U/ PERBAIKAN JALAN PARKIR SPD M | H559: 990000 | I559: IFAN SAFRIANTO | N559: =+C559 -> 70101102 | O559: =+D559 -> R124D1HRGA
B560: 02.10.2025 | C560: 70119300 | D560: P206D1SLSS | E560: 747/PPC/IX/2025 | F560: UMUM & ADMIN LAIN | G560: BY PEMB MATERAI U/ ADM EXPORT | H560: 1000000 | I560: SANTI | N560: =+C560 -> 70119300 | O560: =+D560 -> P206D1SLSS
B561: 02.10.2025 | C561: 70107300 | D561: R124D1HRDV | E561: 757/PPC/IX/2025 | F561: OLAHRAGA DAN PERMAINAN | G561: BY OLAHRAGA 12/09/2025 | H561: 480000 | I561: DEWI PRIYANTI | N561: =+C561 -> 70107300 | O561: =+D561 -> R124D1HRDV
B562: 02.10.2025 | C562: 70101202 | D562: R124TCP | E562: 758/PPC/IX/2025 | F562: PEMEL.KEND&A.BERAT MATRL | G562: BY PEMB RODA SELING IBC | H562: 80000 | I562: ARDHIAN YANUAR | N562: =+C562 -> 70101202 | O562: =+D562 -> R124TCP
B563: 02.10.2025 | C563: 70101102 | D563: R124D1HRGA | E563: 759/PPC/IX/2025 | F563: PEMEL.BNGAN&PSARANA MATRL | G563: BY PEMB SIKA GROUT U/ PERBAIKAN JALAN UMUM | H563: 990000 | I563: IFAN SAFRIANTO | N563: =+C563 -> 70101102 | O563: =+D563 -> R124D1HRGA
B564: 02.10.2025 | C564: 70101114 | D564: R124D1HRGA | E564: 760/PPC/IX/2025 | F564: PBAIKN&PRAWATN PRABT MATR | G564: BY PEMB DUCTING PSD U/ PENGRAPIAN KABEL KANTOR LOG | H564: 225000 | I564: IFAN SAFRIANTO | N564: =+C564 -> 70101114 | O564: =+D564 -> R124D1HRGA
B565: 02.10.2025 | C565: 70009110 | D565: M204D1COMM | E565: 754/PPC/IX/2025 | F565: SURVEY DAN ANALISA | G565: BY HC DINKES POLIVA ETP 2411777074 | H565: 100000 | I565: ORIENTASI | N565: =+C565 -> 70009110 | O565: =+D565 -> M204D1COMM
B566: 02.10.2025 | C566: 70009110 | D566: C206D1SLSS | E566: 754/PPC/IX/2025 | F566: SURVEY DAN ANALISA | G566: BY COO KADIN ASSUDAMAL EBP 2411777285 | H566: 350000 | I566: ORIENTASI | N566: =+C566 -> 70009110 | O566: =+D566 -> C206D1SLSS
B567: 02.10.2025 | C567: 70009110 | D567: P206D1SLSS | E567: 754/PPC/IX/2025 | F567: SURVEY DAN ANALISA | G567: BY COO KADIN AL JAZIRA EBP 2411777288 | H567: 200000 | I567: ORIENTASI | N567: =+C567 -> 70009110 | O567: =+D567 -> P206D1SLSS
B568: 02.10.2025 | C568: 70009110 | D568: P206D1SLSS | E568: 762/PPC/IX/2025 | F568: SURVEY DAN ANALISA | G568: BY HC SG OILSEED EBP 2411777314 | H568: 50000 | I568: FEBRINA R | N568: =+C568 -> 70009110 | O568: =+D568 -> P206D1SLSS
B569: 02.10.2025 | C569: 70009110 | D569: P206D1SLSS | E569: 762/PPC/IX/2025 | F569: SURVEY DAN ANALISA | G569: BY HC FUJIAN NANAN EBP 2411777254 | H569: 50000 | I569: FEBRINA R | N569: =+C569 -> 70009110 | O569: =+D569 -> P206D1SLSS
B570: 02.10.2025 | C570: 70009110 | D570: P206D1SLSS | E570: 762/PPC/IX/2025 | F570: SURVEY DAN ANALISA | G570: BY HC FUJIAN NANAN EBP 2411777221 | H570: 50000 | I570: FEBRINA R | N570: =+C570 -> 70009110 | O570: =+D570 -> P206D1SLSS
...

Sheet FBL3N
A2: G/L Account | E2: 10000001 | G2: Kas Kecil Unit 01
A3: Company Code | E3: 3300
C6: Account | D6: Doc. Date | F6: DocumentNo | H6: Pstng Date | I6: PK | J6: Amount in doc. curr. | K6: Curr. | L6: Amount in local cur. | M6: LCurr | N6: Quantity | O6: BUn | P6: Cost Ctr | Q6: Profit Ctr | R6: Reference | S6: Document Header Text | T6: Text | U6: Tr.Prt | V6: Ref.key (header) 1 | W6: Ref.key (header) 2 | X6: Type | Y6: Clrng doc. | Z6: Assignment
C8: 10000001 | D8: 31.12.2025 | F8: 1888429 | H8: 31.12.2025 | I8: 50 | J8: 0 | K8: IDR | L8: 0 | M8: IDR | Q8: R124 | S8: FC Valuation | T8: 10000001 - Valuation on 20251231 | X8: SA | Y8: 1003022 | Z8: 20251231
C9: 10000001 | D9: 30.06.2025 | F9: 1413583 | H9: 01.07.2025 | I9: 40 | J9: 0 | K9: IDR | L9: 0 | M9: IDR | Q9: R124 | S9: Reverse posting | T9: 10000001 - Valuation on 20250630 Reversal | X9: SA | Y9: 1415341 | Z9: 20250701
C10: 10000001 | D10: 03.07.2025 | F10: 1415341 | H10: 03.07.2025 | I10: 40 | J10: 0 | K10: IDR | L10: 0 | M10: IDR | Q10: R124 | S10: Autom.clearing SAPF124 | T10: 10000001 - Valuation on 20250630 | X10: AB | Y10: 1415341 | Z10: 20250703
C11: 10000001 | D11: 03.07.2025 | F11: 1415341 | H11: 03.07.2025 | I11: 50 | J11: 0 | K11: IDR | L11: 0 | M11: IDR | Q11: R124 | S11: Autom.clearing SAPF124 | T11: 10000001 - Valuation on 20250630 Reversal | X11: AB | Y11: 1415341 | Z11: 20250703
C12: 10000001 | D12: 07.07.2025 | F12: 12005321 | H12: 07.07.2025 | I12: 50 | J12: -400000 | K12: IDR | L12: -400000 | M12: IDR | Q12: R124 | R12: 510/PPC/VI/2025 | S12: OLAHRAGA DAN PERMAINAN | T12: BY OLAHRAGA 20/06/2025 | X12: SP | Y12: 1495275 | Z12: 20250707
C13: 10000001 | D13: 07.07.2025 | F13: 12005322 | H13: 07.07.2025 | I13: 50 | J13: -100000 | K13: IDR | L13: -100000 | M13: IDR | Q13: R124 | R13: 498/PPC/VI/2025 | S13: SURVEY DAN ANALISA | T13: BY COO KADIN ASSUDAMAL EBP 2411775352 | X13: SP | Y13: 1495275 | Z13: 20250707
C14: 10000001 | D14: 07.07.2025 | F14: 12005323 | H14: 07.07.2025 | I14: 50 | J14: -100000 | K14: IDR | L14: -100000 | M14: IDR | Q14: R124 | R14: 498/PPC/VI/2025 | S14: SURVEY DAN ANALISA | T14: BY COO KADIN ASSUDAMAL EBP 2411775353 | X14: SP | Y14: 1495275 | Z14: 20250707
C15: 10000001 | D15: 07.07.2025 | F15: 12005324 | H15: 07.07.2025 | I15: 50 | J15: -150000 | K15: IDR | L15: -150000 | M15: IDR | Q15: R124 | R15: 498/PPC/VI/2025 | S15: SURVEY DAN ANALISA | T15: BY COO KADIN ASSUDAMAL EBP 2411775354 | X15: SP | Y15: 1495275 | Z15: 20250707
C16: 10000001 | D16: 07.07.2025 | F16: 12005325 | H16: 07.07.2025 | I16: 50 | J16: -100000 | K16: IDR | L16: -100000 | M16: IDR | Q16: R124 | R16: 498/PPC/VI/2025 | S16: SURVEY DAN ANALISA | T16: BY COO KADIN ASSUDAMAL EBP 2411775666 | X16: SP | Y16: 1495275 | Z16: 20250707
C17: 10000001 | D17: 07.07.2025 | F17: 12005326 | H17: 07.07.2025 | I17: 50 | J17: -100000 | K17: IDR | L17: -100000 | M17: IDR | Q17: R124 | R17: 498/PPC/VI/2025 | S17: SURVEY DAN ANALISA | T17: BY COO KADIN ASSUDAMAL EBP 2411775667 | X17: SP | Y17: 1495275 | Z17: 20250707
C18: 10000001 | D18: 07.07.2025 | F18: 12005327 | H18: 07.07.2025 | I18: 50 | J18: -100000 | K18: IDR | L18: -100000 | M18: IDR | Q18: R124 | R18: 498/PPC/VI/2025 | S18: SURVEY DAN ANALISA | T18: BY COO KADIN ASSUDAMAL EBP 2411775668 | X18: SP | Y18: 1495275 | Z18: 20250707
C19: 10000001 | D19: 07.07.2025 | F19: 12005328 | H19: 07.07.2025 | I19: 50 | J19: -100000 | K19: IDR | L19: -100000 | M19: IDR | Q19: R124 | R19: 498/PPC/VI/2025 | S19: SURVEY DAN ANALISA | T19: BY COO KADIN ASSUDAMAL EBP 2411775669 | X19: SP | Y19: 1495275 | Z19: 20250707
C20: 10000001 | D20: 07.07.2025 | F20: 12005329 | H20: 07.07.2025 | I20: 50 | J20: -100000 | K20: IDR | L20: -100000 | M20: IDR | Q20: R124 | R20: 498/PPC/VI/2025 | S20: SURVEY DAN ANALISA | T20: BY COO KADIN ASSUDAMAL EBP 2411775670 | X20: SP | Y20: 1495275 | Z20: 20250707
C21: 10000001 | D21: 07.07.2025 | F21: 12005330 | H21: 07.07.2025 | I21: 50 | J21: -100000 | K21: IDR | L21: -100000 | M21: IDR | Q21: R124 | R21: 498/PPC/VI/2025 | S21: SURVEY DAN ANALISA | T21: BY COO KADIN ASSUDAMAL EBP 2411775671 | X21: SP | Y21: 1495275 | Z21: 20250707
C22: 10000001 | D22: 07.07.2025 | F22: 12005331 | H22: 07.07.2025 | I22: 50 | J22: -50000 | K22: IDR | L22: -50000 | M22: IDR | Q22: R124 | R22: 498/PPC/VI/2025 | S22: SURVEY DAN ANALISA | T22: BY HC BPOM AL JAZIRA EBP 2411775754 | X22: SP | Y22: 1495275 | Z22: 20250707
C23: 10000001 | D23: 07.07.2025 | F23: 12005332 | H23: 07.07.2025 | I23: 50 | J23: -940000 | K23: IDR | L23: -940000 | M23: IDR | Q23: R124 | R23: 504/PPC/VI/2025 | S23: PEMEL.KEND&A.BERAT MATRL | T23: BY PEMBELIAN CAIRAN PENETRANT DAN CLEANER | X23: SP | Y23: 1495275 | Z23: 20250707
... C150: 10000001 | D150: 11.07.2025 | F150: 12005459 | H150: 11.07.2025 | I150: 50 | J150: -50000 | K150: IDR | L150: -50000 | M150: IDR | Q150: R124 | R150: 558/PPC/VII/2025 | S150: SURVEY DAN ANALISA | T150: BY HC HOME CHAIN EBP 2411775613 | X150: SP | Y150: 1495275 | Z150: 20250711
C151: 10000001 | D151: 11.07.2025 | F151: 12005460 | H151: 11.07.2025 | I151: 40 | J151: 32056775 | K151: IDR | L151: 32056775 | M151: IDR | Q151: R124 | S151: BANK IN TRANSIT | T151: PETTY CASH RUNGKUT SURABAYA PERIODE 01-11 JULI 25 | X151: SP | Y151: 1495275 | Z151: 20250711
C152: 10000001 | D152: 16.07.2025 | F152: 12005952 | H152: 16.07.2025 | I152: 50 | J152: -629000 | K152: IDR | L152: -629000 | M152: IDR | Q152: R124 | S152: PBAIKN&PRAWATN PRABT MATR | T152: BY PEMB EXHAUST FAN, TIMP FLOOR MARKING | X152: SP | Y152: 1495275 | Z152: 20250716
C153: 10000001 | D153: 16.07.2025 | F153: 12005953 | H153: 16.07.2025 | I153: 50 | J153: -303100 | K153: IDR | L153: -303100 | M153: IDR | Q153: R124 | S153: PEMEL.KEND&A.BERAT MATRL | T153: BY PEMB WIPER SPRING U/ MOTOR POMPA F204 | X153: SP | Y153: 1495275 | Z153: 20250716
C154: 10000001 | D154: 16.07.2025 | F154: 12005954 | H154: 16.07.2025 | I154: 50 | J154: -290500 | K154: IDR | L154: -290500 | M154: IDR | Q154: R124 | S154: BIAYA MESS | T154: BY PDAM MESS PKTJAND JULI 2025 | X154: SP | Y154: 1495275 | Z154: 20250716
C155: 10000001 | D155: 16.07.2025 | F155: 12005955 | H155: 16.07.2025 | I155: 50 | J155: -304800 | K155: IDR | L155: -304800 | M155: IDR | Q155: R124 | S155: PERLENGKAPAN FOTOCOPY | T155: BY CETAK POSTER, BANNER, TAGGING PRP | X155: SP | Y155: 1495275 | Z155: 20250716
C156: 10000001 | D156: 16.07.2025 | F156: 12005956 | H156: 16.07.2025 | I156: 50 | J156: -500000 | K156: IDR | L156: -500000 | M156: IDR | Q156: R124 | S156: OLAHRAGA DAN PERMAINAN | T156: BY OLAHRAGA 11/07/2025 | X156: SP | Y156: 1495275 | Z156: 20250716
C157: 10000001 | D157: 16.07.2025 | F157: 12005957 | H157: 16.07.2025 | I157: 50 | J157: -331500 | K157: IDR | L157: -331500 | M157: IDR | Q157: R124 | S157: MAKANAN DAN MINUMAN | T157: BY SNACK KUNJUNGAN SLF | X157: SP | Y157: 1495275 | Z157: 20250716
C158: 10000001 | D158: 16.07.2025 | F158: 12005958 | H158: 16.07.2025 | I158: 50 | J158: -1000000 | K158: IDR | L158: -1000000 | M158: IDR | Q158: R124 | S158: UMUM & ADMIN LAIN | T158: BY PEMB MATERAI | X158: SP | Y158: 1495275 | Z158: 20250716
C159: 10000001 | D159: 16.07.2025 | F159: 12005959 | H159: 16.07.2025 | I159: 50 | J159: -153000 | K159: IDR | L159: -153000 | M159: IDR | Q159: R124 | S159: PEMEL.BNGAN&PSARANA MATRL | T159: BY PEMB KUAS U/ CAT | X159: SP | Y159: 1495275 | Z159: 20250716
C160: 10000001 | D160: 16.07.2025 | F160: 12005960 | H160: 16.07.2025 | I160: 50 | J160: -50000 | K160: IDR | L160: -50000 | M160: IDR | Q160: R124 | S160: SURVEY DAN ANALISA | T160: BY HC SG OILSEED EBP 2411776092 | X160: SP | Y160: 1495275 | Z160: 20250716
C161: 10000001 | D161: 16.07.2025 | F161: 12005961 | H161: 16.07.2025 | I161: 50 | J161: -50000 | K161: IDR | L161: -50000 | M161: IDR | Q161: R124 | S161: SURVEY DAN ANALISA | T161: BY HC SG OILSEED EBP 2411776096 | X161: SP | Y161: 1495275 | Z161: 20250716
C162: 10000001 | D162: 16.07.2025 | F162: 12005962 | H162: 16.07.2025 | I162: 50 | J162: -50000 | K162: IDR | L162: -50000 | M162: IDR | Q162: R124 | S162: SURVEY DAN ANALISA | T162: BY HC MONDELEZ EBP 2411776205 | X162: SP | Y162: 1495275 | Z162: 20250716
... C180: 10000001 | D180: 17.07.2025 | F180: 12005980 | H180: 17.07.2025 | I180: 50 | J180: -500000 | K180: IDR | L180: -500000 | M180: IDR | Q180: R124 | S180: MAKANAN DAN MINUMAN | T180: BY KONSUMSI SC MEETING 17/07/2025 | X180: SP | Y180: 1495275 | Z180: 20250717
C181: 10000001 | D181: 25.07.2025 | F181: 12005981 | H181: 25.07.2025 | I181: 50 | J181: -991000 | K181: IDR | L181: -991000 | M181: IDR | Q181: R124 | R181: 571/PPC/VII/2025 | S181: PEMEL.KEND&A.BERAT MATRL | T181: BY PEMB NIPPLE SELANG PVC, ELBOW SS, DLL | X181: SP | Y181: 1495275 | Z181: 20250725
C182: 10000001 | D182: 25.07.2025 | F182: 12005982 | H182: 25.07.2025 | I182: 50 | J182: -904127 | K182: IDR | L182: -904127 | M182: IDR | Q182: R124 | R182: 577/PPC/VII/2025 | S182: PBAIKN&PRAWATN PRABT MATR | T182: BY PEMB TANGGA LIPAT TELESKOPIK | X182: SP | Y182: 1495275 | Z182: 20250725
C183: 10000001 | D183: 25.07.2025 | F183: 12005983 | H183: 25.07.2025 | I183: 50 | J183: -50000 | K183: IDR | L183: -50000 | M183: IDR | Q183: R124 | R183: 587/PPC/VII/2025 | S183: SURVEY DAN ANALISA | T183: BY HC AST PVT EBP 2411776266 | X183: SP | Y183: 1495275 | Z183: 20250725
C184: 10000001 | D184: 25.07.2025 | F184: 12005984 | H184: 25.07.2025 | I184: 50 | J184: -50000 | K184: IDR | L184: -50000 | M184: IDR | Q184: R124 | R184: 587/PPC/VII/2025 | S184: SURVEY DAN ANALISA | T184: BY HC SG OILSEED EBP 2411775747 | X184: SP | Y184: 1495275 | Z184: 20250725
C185: 10000001 | D185: 25.07.2025 | F185: 12005985 | H185: 25.07.2025 | I185: 50 | J185: -50000 | K185: IDR | L185: -50000 | M185: IDR | Q185: R124 | R185: 587/PPC/VII/2025 | S185: SURVEY DAN ANALISA | T185: BY HC SG OILSEED EBP 2411776233 | X185: SP | Y185: 1495275 | Z185: 20250725
C186: 10000001 | D186: 25.07.2025 | F186: 12005986 | H186: 25.07.2025 | I186: 50 | J186: -200000 | K186: IDR | L186: -200000 | M186: IDR | Q186: R124 | R186: 587/PPC/VII/2025 | S186: SURVEY DAN ANALISA | T186: BY COO KADIN AST PVT EBP 2411776266 | X186: SP | Y186: 1495275 | Z186: 20250725
C187: 10000001 | D187: 25.07.2025 | F187: 12005987 | H187: 25.07.2025 | I187: 50 | J187: -301000 | K187: IDR | L187: -301000 | M187: IDR | Q187: R124 | R187: 592/PPC/VII/2025 | S187: RISET/PENGEMBANGAN PRODUK | T187: BY SENSORY KFC, McD | X187: SP | Y187: 1495275 | Z187: 20250725
C188: 10000001 | D188: 25.07.2025 | F188: 12005988 | H188: 25.07.2025 | I188: 50 | J188: -264000 | K188: IDR | L188: -264000 | M188: IDR | Q188: R124 | R188: 592/PPC/VII/2025 | S188: PBAIKN&PRAWATN PRABT MATR | T188: BY PEMB SLING | X188: SP | Y188: 1495275 | Z188: 20250725
C189: 10000001 | D189: 25.07.2025 | F189: 12005989 | H189: 25.07.2025 | I189: 50 | J189: -44000 | K189: IDR | L189: -44000 | M189: IDR | Q189: R124 | R189: 592/PPC/VII/2025 | S189: UMUM & ADMIN LAIN | T189: BY ONGKIR SAMPLE KE QUALIS | X189: SP | Y189: 1495275 | Z189: 20250725
C190: 10000001 | D190: 25.07.2025 | F190: 12005990 | H190: 25.07.2025 | I190: 50 | J190: -50000 | K190: IDR | L190: -50000 | M190: IDR | Q190: R124 | R190: 593/PPC/VII/2025 | S190: SURVEY DAN ANALISA | T190: BY HC SG OILSEED EBP 2411775745 | X190: SP | Y190: 1495275 | Z190: 20250725
C191: 10000001 | D191: 25.07.2025 | F191: 12005991 | H191: 25.07.2025 | I191: 50 | J191: -50000 | K191: IDR | L191: -50000 | M191: IDR | Q191: R124 | R191: 593/PPC/VII/2025 | S191: SURVEY DAN ANALISA | T191: BY HC SG OILSEED EBP 2411776321 | X191: SP | Y191: 1495275 | Z191: 20250725
C192: 10000001 | D192: 25.07.2025 | F192: 12005992 | H192: 25.07.2025 | I192: 50 | J192: -50000 | K192: IDR | L192: -50000 | M192: IDR | Q192: R124 | R192: 593/PPC/VII/2025 | S192: SURVEY DAN ANALISA | T192: BY HC SG OILSEED EBP 2411776320 | X192: SP | Y192: 1495275 | Z192: 20250725
... C241: 10000001 | D241: 29.07.2025 | F241: 12006041 | H241: 29.07.2025 | I241: 50 | J241: -131000 | K241: IDR | L241: -131000 | M241: IDR | Q241: R124 | R241: 528/PPV/VII/2025 | S241: UANG MUKA BIAYA | T241: BY FLANGE BADJA KARYA T FP 04002500197911271 | X241: SP | Y241: 1495275 | Z241: 20250729
C242: 10000001 | D242: 29.07.2025 | F242: 12006042 | H242: 29.07.2025 | I242: 40 | J242: 26532388 | K242: IDR | L242: 26532388 | M242: IDR | Q242: R124 | S242: BANK IN TRANSIT | T242: PETTY CASH RUNGKUT SURABAYA PERIODE 15-29 JULI 25 | X242: SP | Y242: 1495275 | Z242: 20250729
C243: 10000001 | D243: 31.07.2025 | F243: 1495275 | H243: 31.07.2025 | I243: 40 | J243: 727500 | K243: IDR | L243: 727500 | M243: IDR | Q243: R124 | T243: BY ATCQ McD, SENSORY KFC | X243: SA | Y243: 1495275 | Z243: 20250731
C244: 10000001 | D244: 31.07.2025 | F244: 1495275 | H244: 31.07.2025 | I244: 40 | J244: 1360000 | K244: IDR | L244: 1360000 | M244: IDR | Q244: R124 | T244: BY BOTOL JAR+TUTUP SAMPLE RETAIN MOSH MOAH NESTLE | X244: SA | Y244: 1495275 | Z244: 20250731
C245: 10000001 | D245: 31.07.2025 | F245: 1495275 | H245: 31.07.2025 | I245: 40 | J245: 304800 | K245: IDR | L245: 304800 | M245: IDR | Q245: R124 | T245: BY CETAK POSTER, BANNER, TAGGING PRP | X245: SA | Y245: 1495275 | Z245: 20250731
C246: 10000001 | D246: 31.07.2025 | F246: 1495275 | H246: 31.07.2025 | I246: 40 | J246: 200000 | K246: IDR | L246: 200000 | M246: IDR | Q246: R124 | T246: BY COO KADIN AL JAZIRA EBP 2411775754 | X246: SA | Y246: 1495275 | Z246: 20250731
C247: 10000001 | D247: 31.07.2025 | F247: 1495275 | H247: 31.07.2025 | I247: 40 | J247: 100000 | K247: IDR | L247: 100000 | M247: IDR | Q247: R124 | T247: BY COO KADIN ASSUDAMAL EBP 2411775352 | X247: SA | Y247: 1495275 | Z247: 20250731
C248: 10000001 | D248: 31.07.2025 | F248: 1495275 | H248: 31.07.2025 | I248: 40 | J248: 100000 | K248: IDR | L248: 100000 | M248: IDR | Q248: R124 | T248: BY COO KADIN ASSUDAMAL EBP 2411775353 | X248: SA | Y248: 1495275 | Z248: 20250731
C249: 10000001 | D249: 31.07.2025 | F249: 1495275 | H249: 31.07.2025 | I249: 40 | J249: 150000 | K249: IDR | L249: 150000 | M249: IDR | Q249: R124 | T249: BY COO KADIN ASSUDAMAL EBP 2411775354 | X249: SA | Y249: 1495275 | Z249: 20250731
C250: 10000001 | D250: 31.07.2025 | F250: 1495275 | H250: 31.07.2025 | I250: 40 | J250: 100000 | K250: IDR | L250: 100000 | M250: IDR | Q250: R124 | T250: BY COO KADIN ASSUDAMAL EBP 2411775666 | X250: SA | Y250: 1495275 | Z250: 20250731
C251: 10000001 | D251: 31.07.2025 | F251: 1495275 | H251: 31.07.2025 | I251: 40 | J251: 100000 | K251: IDR | L251: 100000 | M251: IDR | Q251: R124 | T251: BY COO KADIN ASSUDAMAL EBP 2411775667 | X251: SA | Y251: 1495275 | Z251: 20250731
C252: 10000001 | D252: 31.07.2025 | F252: 1495275 | H252: 31.07.2025 | I252: 40 | J252: 100000 | K252: IDR | L252: 100000 | M252: IDR | Q252: R124 | T252: BY COO KADIN ASSUDAMAL EBP 2411775668 | X252: SA | Y252: 1495275 | Z252: 20250731
C253: 10000001 | D253: 31.07.2025 | F253: 1495275 | H253: 31.07.2025 | I253: 40 | J253: 100000 | K253: IDR | L253: 100000 | M253: IDR | Q253: R124 | T253: BY COO KADIN ASSUDAMAL EBP 2411775669 | X253: SA | Y253: 1495275 | Z253: 20250731
C254: 10000001 | D254: 31.07.2025 | F254: 1495275 | H254: 31.07.2025 | I254: 40 | J254: 100000 | K254: IDR | L254: 100000 | M254: IDR | Q254: R124 | T254: BY COO KADIN ASSUDAMAL EBP 2411775670 | X254: SA | Y254: 1495275 | Z254: 20250731
... C460: 10000001 | D460: 31.07.2025 | F460: 1495275 | H460: 31.07.2025 | I460: 50 | J460: -26532388 | K460: IDR | L460: -26532388 | M460: IDR | Q460: R124 | T460: PETTY CASH RUNGKUT SURABAYA PERIODE 15-29 JULI 25 | X460: SA | Y460: 1495275 | Z460: 20250731
C461: 10000001 | D461: 31.07.2025 | F461: 1502258 | H461: 31.07.2025 | I461: 50 | J461: 0 | K461: IDR | L461: 0 | M461: IDR | Q461: R124 | S461: FC Valuation | T461: 10000001 - Valuation on 20250731 | X461: SA | Y461: 1505626 | Z461: 20250731
C462: 10000001 | D462: 31.07.2025 | F462: 1502259 | H462: 01.08.2025 | I462: 40 | J462: 0 | K462: IDR | L462: 0 | M462: IDR | Q462: R124 | S462: Reverse posting | T462: 10000001 - Valuation on 20250731 Reversal | X462: SA | Y462: 1505626 | Z462: 20250801
C463: 10000001 | D463: 05.08.2025 | F463: 1505626 | H463: 05.08.2025 | I463: 40 | J463: 0 | K463: IDR | L463: 0 | M463: IDR | Q463: R124 | S463: Autom.clearing SAPF124 | T463: 10000001 - Valuation on 20250731 | X463: AB | Y463: 1505626 | Z463: 20250805
C464: 10000001 | D464: 05.08.2025 | F464: 1505626 | H464: 05.08.2025 | I464: 50 | J464: 0 | K464: IDR | L464: 0 | M464: IDR | Q464: R124 | S464: Autom.clearing SAPF124 | T464: 10000001 - Valuation on 20250731 Reversal | X464: AB | Y464: 1505626 | Z464: 20250805
C465: 10000001 | D465: 04.08.2025 | F465: 12006510 | H465: 04.08.2025 | I465: 50 | J465: -800000 | K465: IDR | L465: -800000 | M465: IDR | Q465: R124 | R465: 620/PPC/VII/2025 | S465: BIAYA MESS | T465: BY IURAN RT BULANAN 8 UNIT, PDK TJANDRA INDAH JUL | X465: SP | Y465: 1557224 | Z465: 20250804
C466: 10000001 | D466: 04.08.2025 | F466: 12006511 | H466: 04.08.2025 | I466: 50 | J466: -50000 | K466: IDR | L466: -50000 | M466: IDR | Q466: R124 | R466: 613/PPC/VII/2025 | S466: SURVEY DAN ANALISA | T466: BY HC SHENGRONG EBP/0725/0486-2411776274 | X466: SP | Y466: 1557224 | Z466: 20250804
C467: 10000001 | D467: 04.08.2025 | F467: 12006512 | H467: 04.08.2025 | I467: 50 | J467: -50000 | K467: IDR | L467: -50000 | M467: IDR | Q467: R124 | R467: 613/PPC/VII/2025 | S467: SURVEY DAN ANALISA | T467: BY HC HOME CHAIN EBP/0725/0488-2411776293 | X467: SP | Y467: 1557224 | Z467: 20250804
C468: 10000001 | D468: 04.08.2025 | F468: 12006513 | H468: 04.08.2025 | I468: 50 | J468: -50000 | K468: IDR | L468: -50000 | M468: IDR | Q468: R124 | R468: 613/PPC/VII/2025 | S468: SURVEY DAN ANALISA | T468: BY HC NESTLE SENEGAL ETP/0725/0140/2411776136 | X468: SP | Y468: 1557224 | Z468: 20250804
C469: 10000001 | D469: 04.08.2025 | F469: 12006514 | H469: 04.08.2025 | I469: 50 | J469: -50000 | K469: IDR | L469: -50000 | M469: IDR | Q469: R124 | R469: 613/PPC/VII/2025 | S469: SURVEY DAN ANALISA | T469: BY HC NESTLE SENEGAL ETP/0725/0140/2411776137 | X469: SP | Y469: 1557224 | Z469: 20250804
C470: 10000001 | D470: 04.08.2025 | F470: 12006515 | H470: 04.08.2025 | I470: 50 | J470: -50000 | K470: IDR | L470: -50000 | M470: IDR | Q470: R124 | R470: 613/PPC/VII/2025 | S470: SURVEY DAN ANALISA | T470: BY HC HOME CHAIN EBP/0625/0459-2411776133 | X470: SP | Y470: 1557224 | Z470: 20250804
C471: 10000001 | D471: 04.08.2025 | F471: 12006516 | H471: 04.08.2025 | I471: 50 | J471: -50000 | K471: IDR | L471: -50000 | M471: IDR | Q471: R124 | R471: 613/PPC/VII/2025 | S471: SURVEY DAN ANALISA | T471: BY HC HOCHEE EBP/0625/0462-2411776138 | X471: SP | Y471: 1557224 | Z471: 20250804
C472: 10000001 | D472: 04.08.2025 | F472: 12006517 | H472: 04.08.2025 | I472: 50 | J472: -50000 | K472: IDR | L472: -50000 | M472: IDR | Q472: R124 | R472: 613/PPC/VII/2025 | S472: SURVEY DAN ANALISA | T472: BY HC RAMFOOD EBP/0625/0453-2411776116 | X472: SP | Y472: 1557224 | Z472: 20250804
C473: 10000001 | D473: 04.08.2025 | F473: 12006518 | H473: 04.08.2025 | I473: 50 | J473: -50000 | K473: IDR | L473: -50000 | M473: IDR | Q473: R124 | R473: 613/PPC/VII/2025 | S473: SURVEY DAN ANALISA | T473: BY HC RAMFOOD EBP/0625/0454-2411776117 | X473: SP | Y473: 1557224 | Z473: 20250804
C474: 10000001 | D474: 04.08.2025 | F474: 12006519 | H474: 04.08.2025 | I474: 50 | J474: -50000 | K474: IDR | L474: -50000 | M474: IDR | Q474: R124 | R474: 613/PPC/VII/2025 | S474: SURVEY DAN ANALISA | T474: BY REPROSES HC HOME CHAIN EBP/0625/0454-2411776133 | X474: SP | Y474: 1557224 | Z474: 20250804
C475: 10000001 | D475: 04.08.2025 | F475: 12006520 | H475: 04.08.2025 | I475: 50 | J475: -50000 | K475: IDR | L475: -50000 | M475: IDR | Q475: R124 | R475: 613/PPC/VII/2025 | S475: SURVEY DAN ANALISA | T475: BY HC SUNNY EBP/0725/0485-2411776270 | X475: SP | Y475: 1557224 | Z475: 20250804
C476: 10000001 | D476: 04.08.2025 | F476: 12006521 | H476: 04.08.2025 | I476: 50 | J476: -369000 | K476: IDR | L476: -369000 | M476: IDR | Q476: R124 | R476: 622/PPC/VII/2025 | S476: TRANSPORTASI LOKAL | T476: BY TRANSPORTASI LOKAL 300725 | X476: SP | Y476: 1557224 | Z476: 20250804
... C620: 10000001 | D620: 20.08.2025 | F620: 12006665 | H620: 20.08.2025 | I620: 50 | J620: -650000 | K620: IDR | L620: -650000 | M620: IDR | Q620: R124 | R620: 667/PPC/VIII/25 | S620: UANG MUKA BIAYA | T620: BY CHECK VALVE AMARTA T FP:04002500243246108 | X620: SP | Y620: 1557224 | Z620: 20250820
C621: 10000001 | D621: 20.08.2025 | F621: 12006666 | H621: 20.08.2025 | I621: 40 | J621: 34438078 | K621: IDR | L621: 34438078 | M621: IDR | Q621: R124 | S621: BANK IN TRANSIT | T621: PETTY CASH RUNGKUT SURABAYA PERIODE 01-20 AGUST 25 | X621: SP | Y621: 1557224 | Z621: 20250820
C622: 10000001 | D622: 31.08.2025 | F622: 1557224 | H622: 31.08.2025 | I622: 40 | J622: 868100 | K622: IDR | L622: 868100 | M622: IDR | Q622: R124 | T622: BY ADM, DOC ART CHEMICALS EBP 2411776577 | X622: SA | Y622: 1557224 | Z622: 20250831
C623: 10000001 | D623: 31.08.2025 | F623: 1557224 | H623: 31.08.2025 | I623: 40 | J623: 600000 | K623: IDR | L623: 600000 | M623: IDR | Q623: R124 | T623: BY BAHAN BAKAR 010825 | X623: SA | Y623: 1557224 | Z623: 20250831
C624: 10000001 | D624: 31.08.2025 | F624: 1557224 | H624: 31.08.2025 | I624: 40 | J624: 580000 | K624: IDR | L624: 580000 | M624: IDR | Q624: R124 | T624: BY BAHAN BAKAR 050825 | X624: SA | Y624: 1557224 | Z624: 20250831
C625: 10000001 | D625: 31.08.2025 | F625: 1557224 | H625: 31.08.2025 | I625: 40 | J625: 630000 | K625: IDR | L625: 630000 | M625: IDR | Q625: R124 | T625: BY BAHAN BAKAR 300725 | X625: SA | Y625: 1557224 | Z625: 20250831
C626: 10000001 | D626: 31.08.2025 | F626: 1557224 | H626: 31.08.2025 | I626: 40 | J626: 3000 | K626: IDR | L626: 3000 | M626: IDR | Q626: R124 | T626: BY BEA DAN LEVY 640250702477056;994025072477060 | X626: SA | Y626: 1557224 | Z626: 20250831
C627: 10000001 | D627: 31.08.2025 | F627: 1557224 | H627: 31.08.2025 | I627: 40 | J627: 2000 | K627: IDR | L627: 2000 | M627: IDR | Q627: R124 | T627: BY BEA SAPLE US 35/QA-QM/0725;640250702476508 levy | X627: SA | Y627: 1557224 | Z627: 20250831
C628: 10000001 | D628: 31.08.2025 | F628: 1557224 | H628: 31.08.2025 | I628: 40 | J628: 220000 | K628: IDR | L628: 220000 | M628: IDR | Q628: R124 | T628: BY BRACKET TV VIPER 32-75 310725 | X628: SA | Y628: 1557224 | Z628: 20250831
C629: 10000001 | D629: 31.08.2025 | F629: 1557224 | H629: 31.08.2025 | I629: 40 | J629: 71400 | K629: IDR | L629: 71400 | M629: IDR | Q629: R124 | T629: BY CETAK TAGGING PRP | X629: SA | Y629: 1557224 | Z629: 20250831
C630: 10000001 | D630: 31.08.2025 | F630: 1557224 | H630: 31.08.2025 | I630: 40 | J630: 650000 | K630: IDR | L630: 650000 | M630: IDR | Q630: R124 | T630: BY CHECK VALVE AMARTA T FP:04002500243246108 | X630: SA | Y630: 1557224 | Z630: 20250831
C631: 10000001 | D631: 31.08.2025 | F631: 1557224 | H631: 31.08.2025 | I631: 40 | J631: 250000 | K631: IDR | L631: 250000 | M631: IDR | Q631: R124 | T631: BY COO KADIN & HC AL JAZIRA EBP 2411776576 | X631: SA | Y631: 1557224 | Z631: 20250831
C632: 10000001 | D632: 31.08.2025 | F632: 1557224 | H632: 31.08.2025 | I632: 40 | J632: 500000 | K632: IDR | L632: 500000 | M632: IDR | Q632: R124 | T632: BY COO KADIN & HC ASSUDAMAL EBP 2411776652 | X632: SA | Y632: 1557224 | Z632: 20250831
C633: 10000001 | D633: 31.08.2025 | F633: 1557224 | H633: 31.08.2025 | I633: 40 | J633: 250000 | K633: IDR | L633: 250000 | M633: IDR | Q633: R124 | T633: BY COO KADIN & HC GREENS L EBP 2411776571 | X633: SA | Y633: 1557224 | Z633: 20250831
... C768: 10000001 | D768: 31.08.2025 | F768: 1557224 | H768: 31.08.2025 | I768: 50 | J768: -34438078 | K768: IDR | L768: -34438078 | M768: IDR | Q768: R124 | T768: PETTY CASH RUNGKUT SURABAYA PERIODE 01-20 AGUST 25 | X768: SA | Y768: 1557224 | Z768: 20250831
C769: 10000001 | D769: 31.08.2025 | F769: 1575270 | H769: 31.08.2025 | I769: 50 | J769: 0 | K769: IDR | L769: 0 | M769: IDR | Q769: R124 | S769: FC Valuation | T769: 10000001 - Valuation on 20250831 | X769: SA | Y769: 1576930 | Z769: 20250831
C770: 10000001 | D770: 31.08.2025 | F770: 1575271 | H770: 01.09.2025 | I770: 40 | J770: 0 | K770: IDR | L770: 0 | M770: IDR | Q770: R124 | S770: Reverse posting | T770: 10000001 - Valuation on 20250831 Reversal | X770: SA | Y770: 1576930 | Z770: 20250901
C771: 10000001 | D771: 03.09.2025 | F771: 1576930 | H771: 03.09.2025 | I771: 40 | J771: 0 | K771: IDR | L771: 0 | M771: IDR | Q771: R124 | S771: Autom.clearing SAPF124 | T771: 10000001 - Valuation on 20250831 | X771: AB | Y771: 1576930 | Z771: 20250903
C772: 10000001 | D772: 03.09.2025 | F772: 1576930 | H772: 03.09.2025 | I772: 50 | J772: 0 | K772: IDR | L772: 0 | M772: IDR | Q772: R124 | S772: Autom.clearing SAPF124 | T772: 10000001 - Valuation on 20250831 Reversal | X772: AB | Y772: 1576930 | Z772: 20250903
C773: 10000001 | D773: 02.09.2025 | F773: 12007299 | H773: 02.09.2025 | I773: 50 | J773: -500000 | K773: IDR | L773: -500000 | M773: IDR | Q773: R124 | R773: 678/PPC/VIII/25 | S773: OLAHRAGA DAN PERMAINAN | T773: BY Olahraga cardio boxing 15 Agustus'25 | X773: SP | Y773: 1631293 | Z773: 20250902
C774: 10000001 | D774: 02.09.2025 | F774: 12007300 | H774: 02.09.2025 | I774: 50 | J774: -50000 | K774: IDR | L774: -50000 | M774: IDR | Q774: R124 | R774: 690/PPC/VIII/25 | S774: SURVEY DAN ANALISA | T774: BY HC SG OILSEED EBP/0825/0596-241177690 | X774: SP | Y774: 1631293 | Z774: 20250902
C775: 10000001 | D775: 02.09.2025 | F775: 12007301 | H775: 02.09.2025 | I775: 50 | J775: -50000 | K775: IDR | L775: -50000 | M775: IDR | Q775: R124 | R775: 690/PPC/VIII/25 | S775: SURVEY DAN ANALISA | T775: BY HC XIAMEN AOZHI EBP/0825/0436-2411776918 | X775: SP | Y775: 1631293 | Z775: 20250902
C776: 10000001 | D776: 02.09.2025 | F776: 12007302 | H776: 02.09.2025 | I776: 50 | J776: -50000 | K776: IDR | L776: -50000 | M776: IDR | Q776: R124 | R776: 690/PPC/VIII/25 | S776: SURVEY DAN ANALISA | T776: BY HC HORGOS EBP/0825/0588-2411776862 | X776: SP | Y776: 1631293 | Z776: 20250902
C777: 10000001 | D777: 02.09.2025 | F777: 12007303 | H777: 02.09.2025 | I777: 50 | J777: -50000 | K777: IDR | L777: -50000 | M777: IDR | Q777: R124 | R777: 690/PPC/VIII/25 | S777: SURVEY DAN ANALISA | T777: BY HC FUJIAN NANAN EBP/0825/0580-2411776818 | X777: SP | Y777: 1631293 | Z777: 20250902
...

Sheet Sheet2
A3: Sum of Amount in doc. curr. | B3: Column Labels
A4: Row Labels | B4: 07 | C4: 08 | D4: 09 | E4: 10 | F4: 11 | G4: 12 | H4: (blank) | I4: Grand Total
A5: - | B5: -131000 | C5: -930000 | D5: -1203853 | E5: -1469656 | F5: -4791052 | G5: -3214369 | I5: -11739930
A6: 15000900 | B6: -131000 | C6: -930000 | D6: -1203853 | E6: -1469656 | F6: -4791052 | G6: -3214369 | I6: -11739930
A7: C206D1SLSS | B7: -820000 | C7: -1870000 | D7: -1280000 | E7: -2775000 | F7: -1778000 | G7: -1630000 | I7: -10153000
A8: 70001110 | F8: -1420000 | G8: -1300000 | I8: -2720000
A9: 70009110 | B9: -400000 | C9: -1350000 | D9: -850000 | E9: -2400000 | I9: -5000000
A10: 70101202 | B10: -420000 | C10: -520000 | D10: -430000 | E10: -375000 | F10: -358000 | G10: -330000 | I10: -2433000
A11: H200D1MMDP | E11: -135000 | F11: -7478800 | G11: -1335000 | I11: -8948800
A12: 70110210 | E12: -135000 | F12: -7478800 | G12: -1335000 | I12: -8948800
A13: M204D1COMM | B13: -3702000 | C13: -4927000 | D13: -763000 | E13: -3540000 | F13: -1120000 | G13: -1730300 | I13: -15782300
A14: 70001110 | B14: -29000 | C14: -18000 | D14: -13000 | E14: -24000 | F14: -1120000 | G14: -1218000 | I14: -2422000
A15: 70009110 | B15: -1150000 | C15: -700000 | D15: -750000 | E15: -2600000 | I15: -5200000
A16: 70105321 | E16: -916000 | I16: -916000
A17: 70107600 | B17: -945000 | I17: -945000
A18: 70115100 | B18: -1578000 | C18: -4209000 | G18: -512300 | I18: -6299300
A19: P206D1SLSC | B19: -350000 | C19: -350000 | D19: -700000 | E19: -400000 | F19: -400000 | G19: -500000 | I19: -2700000
A20: 70001110 | F20: -400000 | G20: -500000 | I20: -900000
A21: 70009110 | B21: -350000 | C21: -350000 | D21: -700000 | E21: -400000 | I21: -1800000
A22: P206D1SLSS | B22: -6844000 | C22: -4844100 | D22: -3643000 | E22: -5837000 | F22: -6200000 | G22: -5701000 | I22: -33069100
A23: 70001110 | C23: -868100 | F23: -4250000 | G23: -3900000 | I23: -9018100
A24: 70009110 | B24: -5100000 | C24: -3200000 | D24: -2900000 | E24: -3950000 | I24: -15150000
A25: 70101202 | B25: -328000 | C25: -321000 | D25: -298000 | E25: -300000 | F25: -452000 | G25: -310000 | I25: -2009000
A26: 70106100 | B26: -394000 | C26: -382000 | D26: -445000 | E26: -422000 | F26: -432000 | G26: -437000 | I26: -2512000
A27: 70108110 | B27: -22000 | C27: -23000 | E27: -15000 | F27: -16000 | G27: -28000 | I27: -104000
A28: 70119300 | B28: -1000000 | C28: -50000 | E28: -1150000 | F28: -1050000 | G28: -1026000 | I28: -4276000
A29: R124BLR | E29: -2325000 | F29: -2821000 | I29: -5146000
A30: 70101114 | E30: -331000 | I30: -331000
A31: 70101202 | F31: -200000 | I31: -200000
A32: 70106100 | E32: -931500 | F32: -2121000 | I32: -3052500
A33: 70107600 | E33: -1062500 | F33: -500000 | I33: -1562500
A34: R124D1EHFS | B34: -1273180 | C34: -1113500 | D34: -100000 | E34: -999700 | F34: -876800 | G34: -996262 | I34: -5359442
A35: 70101114 | F35: -50000 | I35: -50000
A36: 70102300 | B36: -1116900 | I36: -1116900
A37: 70107600 | B37: -156280 | C37: -766500 | D37: -100000 | E37: -999700 | F37: -826800 | G37: -996262 | I37: -3845542
A38: 70108110 | C38: -347000 | I38: -347000
A39: R124D1FRCO | B39: -383350 | C39: -344000 | E39: -511000 | F39: -543200 | G39: -865000 | I39: -2646550
A40: 70101202 | C40: -269000 | E40: -361000 | G40: -637500 | I40: -1267500
A41: 70107600 | C41: -75000 | E41: -150000 | G41: -76000 | I41: -301000
A42: 70108100 | B42: -383350 | F42: -543200 | G42: -151500 | I42: -1078050
A43: R124D1HRDV | B43: -4618599 | C43: -1095000 | D43: -2100000 | E43: -3472235 | F43: -4637500 | G43: -6455430 | I43: -22378764
A44: 70107300 | B44: -2786599 | C44: -1000000 | D44: -1400000 | E44: -2330000 | F44: -2100000 | G44: -2239480 | I44: -11856079
A45: 70107600 | B45: -1132000 | C45: -95000 | E45: -1142235 | F45: -237500 | G45: -4215950 | I45: -6822685
A46: 70110110 | B46: -700000 | D46: -700000 | F46: -700000 | I46: -2100000
A47: 70110200 | F47: -600000 | I47: -600000
A48: 70119300 | F48: -1000000 | I48: -1000000
A49: R124D1HRGA | B49: -18188358 | C49: -14559402 | D49: -10663587 | E49: -20320035 | F49: -25204360 | G49: -18684041 | I49: -107619783
A50: 70101102 | B50: -1675420 | C50: -972000 | E50: -1980000 | F50: -1104800 | G50: -961250 | I50: -6693470
A51: 70101114 | B51: -2405138 | C51: -2690102 | D51: -2097757 | E51: -2667735 | F51: -959500 | G51: -2064491 | I51: -12884723
A52: 70101202 | B52: -275000 | I52: -275000
A53: 70105210 | F53: -420500 | G53: -515500 | I53: -936000
A54: 70105300 | B54: -57800 | C54: -57800 | D54: -29900 | E54: -57800 | F54: -210500 | G54: -57800 | I54: -471600
A55: 70106100 | B55: -4103300 | C55: -2838000 | D55: -2669000 | E55: -4213000 | F55: -7368500 | G55: -5144500 | I55: -26336300
A56: 70106400 | B56: -6890000 | C56: -5150000 | D56: -4330000 | E56: -7780000 | F56: -11610000 | G56: -8850000 | I56: -44610000
A57: 70107100 | B57: -290500 | C57: -1890500 | D57: -290500 | E57: -1890500 | F57: -1540500 | G57: -1090500 | I57: -6993000
A58: 70107600 | B58: -2205000 | D58: -973530 | F58: -993960 | I58: -4172490
A59: 70108100 | B59: -286200 | C59: -961000 | D59: -272900 | E59: -1731000 | F59: -996100 | I59: -4247200
A60: R124D1MGMT | B60: -1389800 | D60: -618300 | E60: -870000 | F60: -500000 | G60: -400000 | I60: -3778100
A61: 70107600 | B61: -1389800 | D61: -412800 | E61: -870000 | F61: -500000 | G61: -400000 | I61: -3572600
A62: 70108100 | D62: -105500 | I62: -105500
A63: 70119300 | D63: -100000 | I63: -100000
A64: R124D1PRCN | B64: -1000000 | C64: -600000 | G64: -1000000 | I64: -2600000
A65: 70107500 | C65: -600000 | I65: -600000
A66: 70119300 | B66: -1000000 | G66: -1000000 | I66: -2000000
A67: R124D1TPDU | F67: -385000 | I67: -385000
A68: 70119300 | F68: -385000 | I68: -385000
A69: R124FAM | G69: -2047748 | I69: -2047748
A70: 70101114 | G70: -2047748 | I70: -2047748
A71: R124FPO | C71: -145000 | D71: -2157121 | E71: -463000 | F71: -845510 | G71: -416100 | I71: -4026731
A72: 70101102 | E72: -463000 | F72: -543510 | I72: -1006510
A73: 70101114 | C73: -145000 | D73: -376000 | F73: -302000 | G73: -201100 | I73: -1024100
A74: 70101202 | D74: -916120 | G74: -215000 | I74: -1131120
A75: 70107600 | D75: -865001 | I75: -865001
A76: R124FRA | D76: -61000 | E76: -2325500 | G76: -256380 | I76: -2642880
A77: 70101114 | D77: -61000 | E77: -2325500 | I77: -2386500
A78: 70101202 | G78: -256380 | I78: -256380
A79: R124FRA3 | E79: -2869500 | F79: -625950 | G79: -800000 | I79: -4295450
A80: 70101202 | E80: -2869500 | F80: -362500 | G80: -800000 | I80: -4032000
A81: 70107600 | F81: -263450 | I81: -263450
A82: R124LOG | B82: -919650 | C82: -150000 | D82: -652000 | E82: -150000 | F82: -299200 | G82: -600000 | I82: -2770850
A83: 70101102 | B83: -60000 | I83: -60000
A84: 70101114 | B84: -172150 | D84: -70000 | I84: -242150
A85: 70107500 | G85: -600000 | I85: -600000
A86: 70107600 | B86: -687500 | C86: -150000 | D86: -332000 | F86: -299200 | I86: -1468700
A87: 70108100 | D87: -250000 | E87: -150000 | I87: -400000
A88: R124M09 | G88: -1295000 | I88: -1295000
A89: 70101102 | G89: -420000 | I89: -420000
A90: 70101202 | G90: -875000 | I90: -875000
A91: R124MIN | B91: -1793700 | C91: -816000 | D91: -2511000 | E91: -1529280 | I91: -6649980
A92: 70101114 | C92: -816000 | D92: -949000 | I92: -1765000
A93: 70101202 | B93: -1793700 | D93: -1562000 | E93: -1052280 | I93: -4407980
A94: 70107600 | E94: -477000 | I94: -477000
A95: R124MMP | B95: -322008 | C95: -428500 | E95: -519520 | F95: -591120 | I95: -1861148
A96: 70101202 | B96: -322008 | C96: -428500 | F96: -591120 | I96: -1341628
A97: 70107600 | E97: -519520 | I97: -519520
A98: R124MNT | B98: -193900 | C98: -70000 | D98: -50000 | E98: -402500 | F98: -525000 | G98: -50000 | I98: -1291400
A99: 70101114 | B99: -143900 | C99: -45000 | I99: -188900
A100: 70106100 | E100: -202500 | I100: -202500
A101: 70107600 | B101: -50000 | C101: -25000 | D101: -50000 | E101: -200000 | F101: -525000 | G101: -50000 | I101: -900000
A102: R124NSS | B102: -1894127 | E102: -2804000 | F102: -992050 | I102: -5690177
...

Sheet List Petty Cash Jul-Des 25
A2: G/L Account | E2: 10000001 | G2: Kas Kecil Unit 01
A3: Company Code | E3: 3300
C6: Account | D6: Doc. Date | F6: DocumentNo | H6: Pstng Date | I6: Month | J6: PK | K6: Amount in doc. curr. | L6: Curr. | M6: Amount in local cur. | N6: LCurr | O6: Quantity | P6: BUn | Q6: Cost Ctr | R6: Profit Ctr | S6: Reference | T6: Document Header Text | U6: Text | V6: GL Account | W6: Nama GL Account | X6: Cost Center | Y6: Type | Z6: Clrng doc. | AA6: Assignment | AB6: Amount in doc. curr.
C7: 10000001 | D7: 07.07.2025 | F7: 12005321 | H7: 07.07.2025 | I7: =+MID(H7,4,2) -> 07 | J7: 50 | K7: -400000 | L7: IDR | M7: -400000 | N7: IDR | R7: R124 | S7: 510/PPC/VI/2025 | T7: OLAHRAGA DAN PERMAINAN | U7: BY OLAHRAGA 20/06/2025 | V7: =+VLOOKUP(U7,'FBCJ Jul-Des 2025'!$G$10:$P$1302,8,0) -> 70107300 | W7: =+VLOOKUP(V7,Sheet1!$A$2:$B$27,2,0) -> Biaya Olahraga Dan Permainan | X7: =+VLOOKUP(U7,'FBCJ Jul-Des 2025'!$G$10:$P$1302,9,0) -> R124D1HRDV | Y7: SP | Z7: 1495275 | AA7: 20250707 | AB7: 400000
C8: 10000001 | D8: 07.07.2025 | F8: 12005322 | H8: 07.07.2025 | I8: =+MID(H8,4,2) -> 07 | J8: 50 | K8: -100000 | L8: IDR | M8: -100000 | N8: IDR | R8: R124 | S8: 498/PPC/VI/2025 | T8: SURVEY DAN ANALISA | U8: BY COO KADIN ASSUDAMAL EBP 2411775352 | V8: =+VLOOKUP(U8,'FBCJ Jul-Des 2025'!$G$10:$P$1302,8,0) -> 70009110 | W8: =+VLOOKUP(V8,Sheet1!$A$2:$B$27,2,0) -> Biaya Survey dan Analisa | X8: =+VLOOKUP(U8,'FBCJ Jul-Des 2025'!$G$10:$P$1302,9,0) -> P206D1SLSS | Y8: SP | Z8: 1495275 | AA8: 20250707 | AB8: 100000
C9: 10000001 | D9: 07.07.2025 | F9: 12005323 | H9: 07.07.2025 | I9: =+MID(H9,4,2) -> 07 | J9: 50 | K9: -100000 | L9: IDR | M9: -100000 | N9: IDR | R9: R124 | S9: 498/PPC/VI/2025 | T9: SURVEY DAN ANALISA | U9: BY COO KADIN ASSUDAMAL EBP 2411775353 | V9: =+VLOOKUP(U9,'FBCJ Jul-Des 2025'!$G$10:$P$1302,8,0) -> 70009110 | W9: =+VLOOKUP(V9,Sheet1!$A$2:$B$27,2,0) -> Biaya Survey dan Analisa | X9: =+VLOOKUP(U9,'FBCJ Jul-Des 2025'!$G$10:$P$1302,9,0) -> P206D1SLSS | Y9: SP | Z9: 1495275 | AA9: 20250707 | AB9: 100000
C10: 10000001 | D10: 07.07.2025 | F10: 12005324 | H10: 07.07.2025 | I10: =+MID(H10,4,2) -> 07 | J10: 50 | K10: -150000 | L10: IDR | M10: -150000 | N10: IDR | R10: R124 | S10: 498/PPC/VI/2025 | T10: SURVEY DAN ANALISA | U10: BY COO KADIN ASSUDAMAL EBP 2411775354 | V10: =+VLOOKUP(U10,'FBCJ Jul-Des 2025'!$G$10:$P$1302,8,0) -> 70009110 | W10: =+VLOOKUP(V10,Sheet1!$A$2:$B$27,2,0) -> Biaya Survey dan Analisa | X10: =+VLOOKUP(U10,'FBCJ Jul-Des 2025'!$G$10:$P$1302,9,0) -> P206D1SLSS | Y10: SP | Z10: 1495275 | AA10: 20250707 | AB10: 150000
C11: 10000001 | D11: 07.07.2025 | F11: 12005325 | H11: 07.07.2025 | I11: =+MID(H11,4,2) -> 07 | J11: 50 | K11: -100000 | L11: IDR | M11: -100000 | N11: IDR | R11: R124 | S11: 498/PPC/VI/2025 | T11: SURVEY DAN ANALISA | U11: BY COO KADIN ASSUDAMAL EBP 2411775666 | V11: =+VLOOKUP(U11,'FBCJ Jul-Des 2025'!$G$10:$P$1302,8,0) -> 70009110 | W11: =+VLOOKUP(V11,Sheet1!$A$2:$B$27,2,0) -> Biaya Survey dan Analisa | X11: =+VLOOKUP(U11,'FBCJ Jul-Des 2025'!$G$10:$P$1302,9,0) -> C206D1SLSS | Y11: SP | Z11: 1495275 | AA11: 20250707 | AB11: 100000
C12: 10000001 | D12: 07.07.2025 | F12: 12005326 | H12: 07.07.2025 | I12: =+MID(H12,4,2) -> 07 | J12: 50 | K12: -100000 | L12: IDR | M12: -100000 | N12: IDR | R12: R124 | S12: 498/PPC/VI/2025 | T12: SURVEY DAN ANALISA | U12: BY COO KADIN ASSUDAMAL EBP 2411775667 | V12: =+VLOOKUP(U12,'FBCJ Jul-Des 2025'!$G$10:$P$1302,8,0) -> 70009110 | W12: =+VLOOKUP(V12,Sheet1!$A$2:$B$27,2,0) -> Biaya Survey dan Analisa | X12: =+VLOOKUP(U12,'FBCJ Jul-Des 2025'!$G$10:$P$1302,9,0) -> P206D1SLSS | Y12: SP | Z12: 1495275 | AA12: 20250707 | AB12: 100000
C13: 10000001 | D13: 07.07.2025 | F13: 12005327 | H13: 07.07.2025 | I13: =+MID(H13,4,2) -> 07 | J13: 50 | K13: -100000 | L13: IDR | M13: -100000 | N13: IDR | R13: R124 | S13: 498/PPC/VI/2025 | T13: SURVEY DAN ANALISA | U13: BY COO KADIN ASSUDAMAL EBP 2411775668 | V13: =+VLOOKUP(U13,'FBCJ Jul-Des 2025'!$G$10:$P$1302,8,0) -> 70009110 | W13: =+VLOOKUP(V13,Sheet1!$A$2:$B$27,2,0) -> Biaya Survey dan Analisa | X13: =+VLOOKUP(U13,'FBCJ Jul-Des 2025'!$G$10:$P$1302,9,0) -> P206D1SLSS | Y13: SP | Z13: 1495275 | AA13: 20250707 | AB13: 100000
C14: 10000001 | D14: 07.07.2025 | F14: 12005328 | H14: 07.07.2025 | I14: =+MID(H14,4,2) -> 07 | J14: 50 | K14: -100000 | L14: IDR | M14: -100000 | N14: IDR | R14: R124 | S14: 498/PPC/VI/2025 | T14: SURVEY DAN ANALISA | U14: BY COO KADIN ASSUDAMAL EBP 2411775669 | V14: =+VLOOKUP(U14,'FBCJ Jul-Des 2025'!$G$10:$P$1302,8,0) -> 70009110 | W14: =+VLOOKUP(V14,Sheet1!$A$2:$B$27,2,0) -> Biaya Survey dan Analisa | X14: =+VLOOKUP(U14,'FBCJ Jul-Des 2025'!$G$10:$P$1302,9,0) -> C206D1SLSS | Y14: SP | Z14: 1495275 | AA14: 20250707 | AB14: 100000
C15: 10000001 | D15: 07.07.2025 | F15: 12005329 | H15: 07.07.2025 | I15: =+MID(H15,4,2) -> 07 | J15: 50 | K15: -100000 | L15: IDR | M15: -100000 | N15: IDR | R15: R124 | S15: 498/PPC/VI/2025 | T15: SURVEY DAN ANALISA | U15: BY COO KADIN ASSUDAMAL EBP 2411775670 | V15: =+VLOOKUP(U15,'FBCJ Jul-Des 2025'!$G$10:$P$1302,8,0) -> 70009110 | W15: =+VLOOKUP(V15,Sheet1!$A$2:$B$27,2,0) -> Biaya Survey dan Analisa | X15: =+VLOOKUP(U15,'FBCJ Jul-Des 2025'!$G$10:$P$1302,9,0) -> P206D1SLSS | Y15: SP | Z15: 1495275 | AA15: 20250707 | AB15: 100000
C16: 10000001 | D16: 07.07.2025 | F16: 12005330 | H16: 07.07.2025 | I16: =+MID(H16,4,2) -> 07 | J16: 50 | K16: -100000 | L16: IDR | M16: -100000 | N16: IDR | R16: R124 | S16: 498/PPC/VI/2025 | T16: SURVEY DAN ANALISA | U16: BY COO KADIN ASSUDAMAL EBP 2411775671 | V16: =+VLOOKUP(U16,'FBCJ Jul-Des 2025'!$G$10:$P$1302,8,0) -> 70009110 | W16: =+VLOOKUP(V16,Sheet1!$A$2:$B$27,2,0) -> Biaya Survey dan Analisa | X16: =+VLOOKUP(U16,'FBCJ Jul-Des 2025'!$G$10:$P$1302,9,0) -> P206D1SLSS | Y16: SP | Z16: 1495275 | AA16: 20250707 | AB16: 100000
C17: 10000001 | D17: 07.07.2025 | F17: 12005331 | H17: 07.07.2025 | I17: =+MID(H17,4,2) -> 07 | J17: 50 | K17: -50000 | L17: IDR | M17: -50000 | N17: IDR | R17: R124 | S17: 498/PPC/VI/2025 | T17: SURVEY DAN ANALISA | U17: BY HC BPOM AL JAZIRA EBP 2411775754 | V17: =+VLOOKUP(U17,'FBCJ Jul-Des 2025'!$G$10:$P$1302,8,0) -> 70009110 | W17: =+VLOOKUP(V17,Sheet1!$A$2:$B$27,2,0) -> Biaya Survey dan Analisa | X17: =+VLOOKUP(U17,'FBCJ Jul-Des 2025'!$G$10:$P$1302,9,0) -> P206D1SLSS | Y17: SP | Z17: 1495275 | AA17: 20250707 | AB17: 50000
C18: 10000001 | D18: 07.07.2025 | F18: 12005332 | H18: 07.07.2025 | I18: =+MID(H18,4,2) -> 07 | J18: 50 | K18: -940000 | L18: IDR | M18: -940000 | N18: IDR | R18: R124 | S18: 504/PPC/VI/2025 | T18: PEMEL.KEND&A.BERAT MATRL | U18: BY PEMBELIAN CAIRAN PENETRANT DAN CLEANER | V18: =+VLOOKUP(U18,'FBCJ Jul-Des 2025'!$G$10:$P$1302,8,0) -> 70101202 | W18: =+VLOOKUP(V18,Sheet1!$A$2:$B$27,2,0) -> By Pemeliharaan Kend,ABerat,Mesin-Material Pihak3 | X18: =+VLOOKUP(U18,'FBCJ Jul-Des 2025'!$G$10:$P$1302,9,0) -> R124NSS | Y18: SP | Z18: 1495275 | AA18: 20250707 | AB18: 940000
... C145: 10000001 | D145: 11.07.2025 | F145: 12005459 | H145: 11.07.2025 | I145: =+MID(H145,4,2) -> 07 | J145: 50 | K145: -50000 | L145: IDR | M145: -50000 | N145: IDR | R145: R124 | S145: 558/PPC/VII/2025 | T145: SURVEY DAN ANALISA | U145: BY HC HOME CHAIN EBP 2411775613 | V145: =+VLOOKUP(U145,'FBCJ Jul-Des 2025'!$G$10:$P$1302,8,0) -> 70009110 | W145: =+VLOOKUP(V145,Sheet1!$A$2:$B$27,2,0) -> Biaya Survey dan Analisa | X145: =+VLOOKUP(U145,'FBCJ Jul-Des 2025'!$G$10:$P$1302,9,0) -> P206D1SLSS | Y145: SP | Z145: 1495275 | AA145: 20250711 | AB145: 50000
C146: 10000001 | D146: 11.07.2025 | F146: 12005460 | H146: 11.07.2025 | I146: =+MID(H146,4,2) -> 07 | J146: 40 | K146: 32056775 | L146: IDR | M146: 32056775 | N146: IDR | R146: R124 | T146: BANK IN TRANSIT | U146: PETTY CASH RUNGKUT SURABAYA PERIODE 01-11 JULI 25 | Y146: SP | Z146: 1495275 | AA146: 20250711 | AB146: 32056775
C147: 10000001 | D147: 16.07.2025 | F147: 12005952 | H147: 16.07.2025 | I147: =+MID(H147,4,2) -> 07 | J147: 50 | K147: -629000 | L147: IDR | M147: -629000 | N147: IDR | R147: R124 | T147: PBAIKN&PRAWATN PRABT MATR | U147: BY PEMB EXHAUST FAN, TIMP FLOOR MARKING | V147: =+VLOOKUP(U147,'FBCJ Jul-Des 2025'!$G$10:$P$1302,8,0) -> 70101114 | W147: =+VLOOKUP(V147,Sheet1!$A$2:$B$27,2,0) -> By Perbaikan & Perawatan Perabot Material Pihak3 | X147: =+VLOOKUP(U147,'FBCJ Jul-Des 2025'!$G$10:$P$1302,9,0) -> R124TCP | Y147: SP | Z147: 1495275 | AA147: 20250716 | AB147: 629000
C148: 10000001 | D148: 16.07.2025 | F148: 12005953 | H148: 16.07.2025 | I148: =+MID(H148,4,2) -> 07 | J148: 50 | K148: -303100 | L148: IDR | M148: -303100 | N148: IDR | R148: R124 | T148: PEMEL.KEND&A.BERAT MATRL | U148: BY PEMB WIPER SPRING U/ MOTOR POMPA F204 | V148: =+VLOOKUP(U148,'FBCJ Jul-Des 2025'!$G$10:$P$1302,8,0) -> 70101202 | W148: =+VLOOKUP(V148,Sheet1!$A$2:$B$27,2,0) -> By Pemeliharaan Kend,ABerat,Mesin-Material Pihak3 | X148: =+VLOOKUP(U148,'FBCJ Jul-Des 2025'!$G$10:$P$1302,9,0) -> R124REF3 | Y148: SP | Z148: 1495275 | AA148: 20250716 | AB148: 303100
C149: 10000001 | D149: 16.07.2025 | F149: 12005954 | H149: 16.07.2025 | I149: =+MID(H149,4,2) -> 07 | J149: 50 | K149: -290500 | L149: IDR | M149: -290500 | N149: IDR | R149: R124 | T149: BIAYA MESS | U149: BY PDAM MESS PKTJAND JULI 2025 | V149: =+VLOOKUP(U149,'FBCJ Jul-Des 2025'!$G$10:$P$1302,8,0) -> 70107100 | W149: =+VLOOKUP(V149,Sheet1!$A$2:$B$27,2,0) -> Biaya Mess | X149: =+VLOOKUP(U149,'FBCJ Jul-Des 2025'!$G$10:$P$1302,9,0) -> R124D1HRGA | Y149: SP | Z149: 1495275 | AA149: 20250716 | AB149: 290500
C150: 10000001 | D150: 16.07.2025 | F150: 12005955 | H150: 16.07.2025 | I150: =+MID(H150,4,2) -> 07 | J150: 50 | K150: -304800 | L150: IDR | M150: -304800 | N150: IDR | R150: R124 | T150: PERLENGKAPAN FOTOCOPY | U150: BY CETAK POSTER, BANNER, TAGGING PRP | V150: =+VLOOKUP(U150,'FBCJ Jul-Des 2025'!$G$10:$P$1302,8,0) -> 70108110 | W150: =+VLOOKUP(V150,Sheet1!$A$2:$B$27,2,0) -> Biaya Fotocopy | X150: =+VLOOKUP(U150,'FBCJ Jul-Des 2025'!$G$10:$P$1302,9,0) -> R124QMR | Y150: SP | Z150: 1495275 | AA150: 20250716 | AB150: 304800
C151: 10000001 | D151: 16.07.2025 | F151: 12005956 | H151: 16.07.2025 | I151: =+MID(H151,4,2) -> 07 | J151: 50 | K151: -500000 | L151: IDR | M151: -500000 | N151: IDR | R151: R124 | T151: OLAHRAGA DAN PERMAINAN | U151: BY OLAHRAGA 11/07/2025 | V151: =+VLOOKUP(U151,'FBCJ Jul-Des 2025'!$G$10:$P$1302,8,0) -> 70107300 | W151: =+VLOOKUP(V151,Sheet1!$A$2:$B$27,2,0) -> Biaya Olahraga Dan Permainan | X151: =+VLOOKUP(U151,'FBCJ Jul-Des 2025'!$G$10:$P$1302,9,0) -> R124D1HRDV | Y151: SP | Z151: 1495275 | AA151: 20250716 | AB151: 500000
C152: 10000001 | D152: 16.07.2025 | F152: 12005957 | H152: 16.07.2025 | I152: =+MID(H152,4,2) -> 07 | J152: 50 | K152: -331500 | L152: IDR | M152: -331500 | N152: IDR | R152: R124 | T152: MAKANAN DAN MINUMAN | U152: BY SNACK KUNJUNGAN SLF | V152: =+VLOOKUP(U152,'FBCJ Jul-Des 2025'!$G$10:$P$1302,8,0) -> 70107600 | W152: =+VLOOKUP(V152,Sheet1!$A$2:$B$27,2,0) -> Biaya Konsumsi Kantor | X152: =+VLOOKUP(U152,'FBCJ Jul-Des 2025'!$G$10:$P$1302,9,0) -> R124D1HRGA | Y152: SP | Z152: 1495275 | AA152: 20250716 | AB152: 331500
C153: 10000001 | D153: 16.07.2025 | F153: 12005958 | H153: 16.07.2025 | I153: =+MID(H153,4,2) -> 07 | J153: 50 | K153: -1000000 | L153: IDR | M153: -1000000 | N153: IDR | R153: R124 | T153: UMUM & ADMIN LAIN | U153: BY PEMB MATERAI | V153: =+VLOOKUP(U153,'FBCJ Jul-Des 2025'!$G$10:$P$1302,8,0) -> 70119300 | W153: =+VLOOKUP(V153,Sheet1!$A$2:$B$27,2,0) -> Biaya Umum dan Administrasi | X153: =+VLOOKUP(U153,'FBCJ Jul-Des 2025'!$G$10:$P$1302,9,0) -> R124D1PRCN | Y153: SP | Z153: 1495275 | AA153: 20250716 | AB153: 1000000
C154: 10000001 | D154: 16.07.2025 | F154: 12005959 | H154: 16.07.2025 | I154: =+MID(H154,4,2) -> 07 | J154: 50 | K154: -153000 | L154: IDR | M154: -153000 | N154: IDR | R154: R124 | T154: PEMEL.BNGAN&PSARANA MATRL | U154: BY PEMB KUAS U/ CAT | V154: =+VLOOKUP(U154,'FBCJ Jul-Des 2025'!$G$10:$P$1302,8,0) -> 70101102 | W154: =+VLOOKUP(V154,Sheet1!$A$2:$B$27,2,0) -> By Pemeliharaan BgnanPrasarana Material Pihak3 | X154: =+VLOOKUP(U154,'FBCJ Jul-Des 2025'!$G$10:$P$1302,9,0) -> R124REF | Y154: SP | Z154: 1495275 | AA154: 20250716 | AB154: 153000
C155: 10000001 | D155: 16.07.2025 | F155: 12005960 | H155: 16.07.2025 | I155: =+MID(H155,4,2) -> 07 | J155: 50 | K155: -50000 | L155: IDR | M155: -50000 | N155: IDR | R155: R124 | T155: SURVEY DAN ANALISA | U155: BY HC SG OILSEED EBP 2411776092 | V155: =+VLOOKUP(U155,'FBCJ Jul-Des 2025'!$G$10:$P$1302,8,0) -> 70009110 | W155: =+VLOOKUP(V155,Sheet1!$A$2:$B$27,2,0) -> Biaya Survey dan Analisa | X155: =+VLOOKUP(U155,'FBCJ Jul-Des 2025'!$G$10:$P$1302,9,0) -> P206D1SLSS | Y155: SP | Z155: 1495275 | AA155: 20250716 | AB155: 50000
C156: 10000001 | D156: 16.07.2025 | F156: 12005961 | H156: 16.07.2025 | I156: =+MID(H156,4,2) -> 07 | J156: 50 | K156: -50000 | L156: IDR | M156: -50000 | N156: IDR | R156: R124 | T156: SURVEY DAN ANALISA | U156: BY HC SG OILSEED EBP 2411776096 | V156: =+VLOOKUP(U156,'FBCJ Jul-Des 2025'!$G$10:$P$1302,8,0) -> 70009110 | W156: =+VLOOKUP(V156,Sheet1!$A$2:$B$27,2,0) -> Biaya Survey dan Analisa | X156: =+VLOOKUP(U156,'FBCJ Jul-Des 2025'!$G$10:$P$1302,9,0) -> P206D1SLSS | Y156: SP | Z156: 1495275 | AA156: 20250716 | AB156: 50000
C157: 10000001 | D157: 16.07.2025 | F157: 12005962 | H157: 16.07.2025 | I157: =+MID(H157,4,2) -> 07 | J157: 50 | K157: -50000 | L157: IDR | M157: -50000 | N157: IDR | R157: R124 | T157: SURVEY DAN ANALISA | U157: BY HC MONDELEZ EBP 2411776205 | V157: =+VLOOKUP(U157,'FBCJ Jul-Des 2025'!$G$10:$P$1302,8,0) -> 70009110 | W157: =+VLOOKUP(V157,Sheet1!$A$2:$B$27,2,0) -> Biaya Survey dan Analisa | X157: =+VLOOKUP(U157,'FBCJ Jul-Des 2025'!$G$10:$P$1302,9,0) -> P206D1SLSS | Y157: SP | Z157: 1495275 | AA157: 20250716 | AB157: 50000
C158: 10000001 | D158: 16.07.2025 | F158: 12005963 | H158: 16.07.2025 | I158: =+MID(H158,4,2) -> 07 | J158: 50 | K158: -50000 | L158: IDR | M158: -50000 | N158: IDR | R158: R124 | T158: SURVEY DAN ANALISA | U158: BY HC THAI GLICO EBP 2411776134 | V158: =+VLOOKUP(U158,'FBCJ Jul-Des 2025'!$G$10:$P$1302,8,0) -> 70009110 | W158: =+VLOOKUP(V158,Sheet1!$A$2:$B$27,2,0) -> Biaya Survey dan Analisa | X158: =+VLOOKUP(U158,'FBCJ Jul-Des 2025'!$G$10:$P$1302,9,0) -> P206D1SLSS | Y158: SP | Z158: 1495275 | AA158: 20250716 | AB158: 50000
... C175: 10000001 | D175: 17.07.2025 | F175: 12005980 | H175: 17.07.2025 | I175: =+MID(H175,4,2) -> 07 | J175: 50 | K175: -500000 | L175: IDR | M175: -500000 | N175: IDR | R175: R124 | T175: MAKANAN DAN MINUMAN | U175: BY KONSUMSI SC MEETING 17/07/2025 | V175: =+VLOOKUP(U175,'FBCJ Jul-Des 2025'!$G$10:$P$1302,8,0) -> 70107600 | W175: =+VLOOKUP(V175,Sheet1!$A$2:$B$27,2,0) -> Biaya Konsumsi Kantor | X175: =+VLOOKUP(U175,'FBCJ Jul-Des 2025'!$G$10:$P$1302,9,0) -> R124D1MGMT | Y175: SP | Z175: 1495275 | AA175: 20250717 | AB175: 500000
C176: 10000001 | D176: 25.07.2025 | F176: 12005981 | H176: 25.07.2025 | I176: =+MID(H176,4,2) -> 07 | J176: 50 | K176: -991000 | L176: IDR | M176: -991000 | N176: IDR | R176: R124 | S176: 571/PPC/VII/2025 | T176: PEMEL.KEND&A.BERAT MATRL | U176: BY PEMB NIPPLE SELANG PVC, ELBOW SS, DLL | V176: =+VLOOKUP(U176,'FBCJ Jul-Des 2025'!$G$10:$P$1302,8,0) -> 70101202 | W176: =+VLOOKUP(V176,Sheet1!$A$2:$B$27,2,0) -> By Pemeliharaan Kend,ABerat,Mesin-Material Pihak3 | X176: =+VLOOKUP(U176,'FBCJ Jul-Des 2025'!$G$10:$P$1302,9,0) -> R124WTT | Y176: SP | Z176: 1495275 | AA176: 20250725 | AB176: 991000
C177: 10000001 | D177: 25.07.2025 | F177: 12005982 | H177: 25.07.2025 | I177: =+MID(H177,4,2) -> 07 | J177: 50 | K177: -904127 | L177: IDR | M177: -904127 | N177: IDR | R177: R124 | S177: 577/PPC/VII/2025 | T177: PBAIKN&PRAWATN PRABT MATR | U177: BY PEMB TANGGA LIPAT TELESKOPIK | V177: =+VLOOKUP(U177,'FBCJ Jul-Des 2025'!$G$10:$P$1302,8,0) -> 70101114 | W177: =+VLOOKUP(V177,Sheet1!$A$2:$B$27,2,0) -> By Perbaikan & Perawatan Perabot Material Pihak3 | X177: =+VLOOKUP(U177,'FBCJ Jul-Des 2025'!$G$10:$P$1302,9,0) -> R124NSS | Y177: SP | Z177: 1495275 | AA177: 20250725 | AB177: 904127
C178: 10000001 | D178: 25.07.2025 | F178: 12005983 | H178: 25.07.2025 | I178: =+MID(H178,4,2) -> 07 | J178: 50 | K178: -50000 | L178: IDR | M178: -50000 | N178: IDR | R178: R124 | S178: 587/PPC/VII/2025 | T178: SURVEY DAN ANALISA | U178: BY HC AST PVT EBP 2411776266 | V178: =+VLOOKUP(U178,'FBCJ Jul-Des 2025'!$G$10:$P$1302,8,0) -> 70009110 | W178: =+VLOOKUP(V178,Sheet1!$A$2:$B$27,2,0) -> Biaya Survey dan Analisa | X178: =+VLOOKUP(U178,'FBCJ Jul-Des 2025'!$G$10:$P$1302,9,0) -> P206D1SLSS | Y178: SP | Z178: 1495275 | AA178: 20250725 | AB178: 50000
C179: 10000001 | D179: 25.07.2025 | F179: 12005984 | H179: 25.07.2025 | I179: =+MID(H179,4,2) -> 07 | J179: 50 | K179: -50000 | L179: IDR | M179: -50000 | N179: IDR | R179: R124 | S179: 587/PPC/VII/2025 | T179: SURVEY DAN ANALISA | U179: BY HC SG OILSEED EBP 2411775747 | V179: =+VLOOKUP(U179,'FBCJ Jul-Des 2025'!$G$10:$P$1302,8,0) -> 70009110 | W179: =+VLOOKUP(V179,Sheet1!$A$2:$B$27,2,0) -> Biaya Survey dan Analisa | X179: =+VLOOKUP(U179,'FBCJ Jul-Des 2025'!$G$10:$P$1302,9,0) -> P206D1SLSS | Y179: SP | Z179: 1495275 | AA179: 20250725 | AB179: 50000
C180: 10000001 | D180: 25.07.2025 | F180: 12005985 | H180: 25.07.2025 | I180: =+MID(H180,4,2) -> 07 | J180: 50 | K180: -50000 | L180: IDR | M180: -50000 | N180: IDR | R180: R124 | S180: 587/PPC/VII/2025 | T180: SURVEY DAN ANALISA | U180: BY HC SG OILSEED EBP 2411776233 | V180: =+VLOOKUP(U180,'FBCJ Jul-Des 2025'!$G$10:$P$1302,8,0) -> 70009110 | W180: =+VLOOKUP(V180,Sheet1!$A$2:$B$27,2,0) -> Biaya Survey dan Analisa | X180: =+VLOOKUP(U180,'FBCJ Jul-Des 2025'!$G$10:$P$1302,9,0) -> P206D1SLSS | Y180: SP | Z180: 1495275 | AA180: 20250725 | AB180: 50000
C181: 10000001 | D181: 25.07.2025 | F181: 12005986 | H181: 25.07.2025 | I181: =+MID(H181,4,2) -> 07 | J181: 50 | K181: -200000 | L181: IDR | M181: -200000 | N181: IDR | R181: R124 | S181: 587/PPC/VII/2025 | T181: SURVEY DAN ANALISA | U181: BY COO KADIN AST PVT EBP 2411776266 | V181: =+VLOOKUP(U181,'FBCJ Jul-Des 2025'!$G$10:$P$1302,8,0) -> 70009110 | W181: =+VLOOKUP(V181,Sheet1!$A$2:$B$27,2,0) -> Biaya Survey dan Analisa | X181: =+VLOOKUP(U181,'FBCJ Jul-Des 2025'!$G$10:$P$1302,9,0) -> P206D1SLSS | Y181: SP | Z181: 1495275 | AA181: 20250725 | AB181: 200000
C182: 10000001 | D182: 25.07.2025 | F182: 12005987 | H182: 25.07.2025 | I182: =+MID(H182,4,2) -> 07 | J182: 50 | K182: -301000 | L182: IDR | M182: -301000 | N182: IDR | R182: R124 | S182: 592/PPC/VII/2025 | T182: RISET/PENGEMBANGAN PRODUK | U182: BY SENSORY KFC, McD | V182: =+VLOOKUP(U182,'FBCJ Jul-Des 2025'!$G$10:$P$1302,8,0) -> 70115100 | W182: =+VLOOKUP(V182,Sheet1!$A$2:$B$27,2,0) -> Biaya Riset, Pengembangan, dan Laboratorium | X182: =+VLOOKUP(U182,'FBCJ Jul-Des 2025'!$G$10:$P$1302,9,0) -> R124QCA | Y182: SP | Z182: 1495275 | AA182: 20250725 | AB182: 301000
C183: 10000001 | D183: 25.07.2025 | F183: 12005988 | H183: 25.07.2025 | I183: =+MID(H183,4,2) -> 07 | J183: 50 | K183: -264000 | L183: IDR | M183: -264000 | N183: IDR | R183: R124 | S183: 592/PPC/VII/2025 | T183: PBAIKN&PRAWATN PRABT MATR | U183: BY PEMB SLING | V183: =+VLOOKUP(U183,'FBCJ Jul-Des 2025'!$G$10:$P$1302,8,0) -> 70101114 | W183: =+VLOOKUP(V183,Sheet1!$A$2:$B$27,2,0) -> By Perbaikan & Perawatan Perabot Material Pihak3 | X183: =+VLOOKUP(U183,'FBCJ Jul-Des 2025'!$G$10:$P$1302,9,0) -> R124QCA | Y183: SP | Z183: 1495275 | AA183: 20250725 | AB183: 264000
C184: 10000001 | D184: 25.07.2025 | F184: 12005989 | H184: 25.07.2025 | I184: =+MID(H184,4,2) -> 07 | J184: 50 | K184: -44000 | L184: IDR | M184: -44000 | N184: IDR | R184: R124 | S184: 592/PPC/VII/2025 | T184: UMUM & ADMIN LAIN | U184: BY ONGKIR SAMPLE KE QUALIS | V184: =+VLOOKUP(U184,'FBCJ Jul-Des 2025'!$G$10:$P$1302,8,0) -> 70119300 | W184: =+VLOOKUP(V184,Sheet1!$A$2:$B$27,2,0) -> Biaya Umum dan Administrasi | X184: =+VLOOKUP(U184,'FBCJ Jul-Des 2025'!$G$10:$P$1302,9,0) -> R124QCA | Y184: SP | Z184: 1495275 | AA184: 20250725 | AB184: 44000
C185: 10000001 | D185: 25.07.2025 | F185: 12005990 | H185: 25.07.2025 | I185: =+MID(H185,4,2) -> 07 | J185: 50 | K185: -50000 | L185: IDR | M185: -50000 | N185: IDR | R185: R124 | S185: 593/PPC/VII/2025 | T185: SURVEY DAN ANALISA | U185: BY HC SG OILSEED EBP 2411775745 | V185: =+VLOOKUP(U185,'FBCJ Jul-Des 2025'!$G$10:$P$1302,8,0) -> 70009110 | W185: =+VLOOKUP(V185,Sheet1!$A$2:$B$27,2,0) -> Biaya Survey dan Analisa | X185: =+VLOOKUP(U185,'FBCJ Jul-Des 2025'!$G$10:$P$1302,9,0) -> P206D1SLSS | Y185: SP | Z185: 1495275 | AA185: 20250725 | AB185: 50000
C186: 10000001 | D186: 25.07.2025 | F186: 12005991 | H186: 25.07.2025 | I186: =+MID(H186,4,2) -> 07 | J186: 50 | K186: -50000 | L186: IDR | M186: -50000 | N186: IDR | R186: R124 | S186: 593/PPC/VII/2025 | T186: SURVEY DAN ANALISA | U186: BY HC SG OILSEED EBP 2411776321 | V186: =+VLOOKUP(U186,'FBCJ Jul-Des 2025'!$G$10:$P$1302,8,0) -> 70009110 | W186: =+VLOOKUP(V186,Sheet1!$A$2:$B$27,2,0) -> Biaya Survey dan Analisa | X186: =+VLOOKUP(U186,'FBCJ Jul-Des 2025'!$G$10:$P$1302,9,0) -> P206D1SLSS | Y186: SP | Z186: 1495275 | AA186: 20250725 | AB186: 50000
C187: 10000001 | D187: 25.07.2025 | F187: 12005992 | H187: 25.07.2025 | I187: =+MID(H187,4,2) -> 07 | J187: 50 | K187: -50000 | L187: IDR | M187: -50000 | N187: IDR | R187: R124 | S187: 593/PPC/VII/2025 | T187: SURVEY DAN ANALISA | U187: BY HC SG OILSEED EBP 2411776320 | V187: =+VLOOKUP(U187,'FBCJ Jul-Des 2025'!$G$10:$P$1302,8,0) -> 70009110 | W187: =+VLOOKUP(V187,Sheet1!$A$2:$B$27,2,0) -> Biaya Survey dan Analisa | X187: =+VLOOKUP(U187,'FBCJ Jul-Des 2025'!$G$10:$P$1302,9,0) -> P206D1SLSS | Y187: SP | Z187: 1495275 | AA187: 20250725 | AB187: 50000
... C235: 10000001 | D235: 29.07.2025 | F235: 12006040 | H235: 29.07.2025 | I235: =+MID(H235,4,2) -> 07 | J235: 50 | K235: -345000 | L235: IDR | M235: -345000 | N235: IDR | R235: R124 | S235: 528/PPV/VII/2025 | T235: PEMEL.KEND&A.BERAT MATRL | U235: BY PEMBELIAN B/M TWP SS | V235: =+VLOOKUP(U235,'FBCJ Jul-Des 2025'!$G$10:$P$1302,8,0) -> 70101202 | W235: =+VLOOKUP(V235,Sheet1!$A$2:$B$27,2,0) -> By Pemeliharaan Kend,ABerat,Mesin-Material Pihak3 | X235: =+VLOOKUP(U235,'FBCJ Jul-Des 2025'!$G$10:$P$1302,9,0) -> R124REF3 | Y235: SP | Z235: 1495275 | AA235: 20250729 | AB235: 345000
C236: 10000001 | D236: 29.07.2025 | F236: 12006041 | H236: 29.07.2025 | I236: =+MID(H236,4,2) -> 07 | J236: 50 | K236: -131000 | L236: IDR | M236: -131000 | N236: IDR | R236: R124 | S236: 528/PPV/VII/2025 | T236: UANG MUKA BIAYA | U236: BY FLANGE BADJA KARYA T FP 04002500197911271 | V236: 15000900 | W236: =+VLOOKUP(V236,Sheet1!$A$2:$B$27,2,0) -> Biaya Lainnya Yang Dibayar Di Muka | X236: - | Y236: SP | Z236: 1495275 | AA236: 20250729 | AB236: 131000
C237: 10000001 | D237: 29.07.2025 | F237: 12006042 | H237: 29.07.2025 | I237: =+MID(H237,4,2) -> 07 | J237: 40 | K237: 26532388 | L237: IDR | M237: 26532388 | N237: IDR | R237: R124 | T237: BANK IN TRANSIT | U237: PETTY CASH RUNGKUT SURABAYA PERIODE 15-29 JULI 25 | Y237: SP | Z237: 1495275 | AA237: 20250729 | AB237: 26532388
C238: 10000001 | D238: 04.08.2025 | F238: 12006510 | H238: 04.08.2025 | I238: =+MID(H238,4,2) -> 08 | J238: 50 | K238: -800000 | L238: IDR | M238: -800000 | N238: IDR | R238: R124 | S238: 620/PPC/VII/2025 | T238: BIAYA MESS | U238: BY IURAN RT BULANAN 8 UNIT, PDK TJANDRA INDAH JUL | V238: =+VLOOKUP(U238,'FBCJ Jul-Des 2025'!$G$10:$P$1302,8,0) -> 70107100 | W238: =+VLOOKUP(V238,Sheet1!$A$2:$B$27,2,0) -> Biaya Mess | X238: =+VLOOKUP(U238,'FBCJ Jul-Des 2025'!$G$10:$P$1302,9,0) -> R124D1HRGA | Y238: SP | Z238: 1557224 | AA238: 20250804 | AB238: 800000
C239: 10000001 | D239: 04.08.2025 | F239: 12006511 | H239: 04.08.2025 | I239: =+MID(H239,4,2) -> 08 | J239: 50 | K239: -50000 | L239: IDR | M239: -50000 | N239: IDR | R239: R124 | S239: 613/PPC/VII/2025 | T239: SURVEY DAN ANALISA | U239: BY HC SHENGRONG EBP/0725/0486-2411776274 | V239: =+VLOOKUP(U239,'FBCJ Jul-Des 2025'!$G$10:$P$1302,8,0) -> 70009110 | W239: =+VLOOKUP(V239,Sheet1!$A$2:$B$27,2,0) -> Biaya Survey dan Analisa | X239: =+VLOOKUP(U239,'FBCJ Jul-Des 2025'!$G$10:$P$1302,9,0) -> P206D1SLSS | Y239: SP | Z239: 1557224 | AA239: 20250804 | AB239: 50000
C240: 10000001 | D240: 04.08.2025 | F240: 12006512 | H240: 04.08.2025 | I240: =+MID(H240,4,2) -> 08 | J240: 50 | K240: -50000 | L240: IDR | M240: -50000 | N240: IDR | R240: R124 | S240: 613/PPC/VII/2025 | T240: SURVEY DAN ANALISA | U240: BY HC HOME CHAIN EBP/0725/0488-2411776293 | V240: =+VLOOKUP(U240,'FBCJ Jul-Des 2025'!$G$10:$P$1302,8,0) -> 70009110 | W240: =+VLOOKUP(V240,Sheet1!$A$2:$B$27,2,0) -> Biaya Survey dan Analisa | X240: =+VLOOKUP(U240,'FBCJ Jul-Des 2025'!$G$10:$P$1302,9,0) -> P206D1SLSS | Y240: SP | Z240: 1557224 | AA240: 20250804 | AB240: 50000
C241: 10000001 | D241: 04.08.2025 | F241: 12006513 | H241: 04.08.2025 | I241: =+MID(H241,4,2) -> 08 | J241: 50 | K241: -50000 | L241: IDR | M241: -50000 | N241: IDR | R241: R124 | S241: 613/PPC/VII/2025 | T241: SURVEY DAN ANALISA | U241: BY HC NESTLE SENEGAL ETP/0725/0140/2411776136 | V241: =+VLOOKUP(U241,'FBCJ Jul-Des 2025'!$G$10:$P$1302,8,0) -> 70009110 | W241: =+VLOOKUP(V241,Sheet1!$A$2:$B$27,2,0) -> Biaya Survey dan Analisa | X241: =+VLOOKUP(U241,'FBCJ Jul-Des 2025'!$G$10:$P$1302,9,0) -> M204D1COMM | Y241: SP | Z241: 1557224 | AA241: 20250804 | AB241: 50000
C242: 10000001 | D242: 04.08.2025 | F242: 12006514 | H242: 04.08.2025 | I242: =+MID(H242,4,2) -> 08 | J242: 50 | K242: -50000 | L242: IDR | M242: -50000 | N242: IDR | R242: R124 | S242: 613/PPC/VII/2025 | T242: SURVEY DAN ANALISA | U242: BY HC NESTLE SENEGAL ETP/0725/0140/2411776137 | V242: =+VLOOKUP(U242,'FBCJ Jul-Des 2025'!$G$10:$P$1302,8,0) -> 70009110 | W242: =+VLOOKUP(V242,Sheet1!$A$2:$B$27,2,0) -> Biaya Survey dan Analisa | X242: =+VLOOKUP(U242,'FBCJ Jul-Des 2025'!$G$10:$P$1302,9,0) -> M204D1COMM | Y242: SP | Z242: 1557224 | AA242: 20250804 | AB242: 50000
C243: 10000001 | D243: 04.08.2025 | F243: 12006515 | H243: 04.08.2025 | I243: =+MID(H243,4,2) -> 08 | J243: 50 | K243: -50000 | L243: IDR | M243: -50000 | N243: IDR | R243: R124 | S243: 613/PPC/VII/2025 | T243: SURVEY DAN ANALISA | U243: BY HC HOME CHAIN EBP/0625/0459-2411776133 | V243: =+VLOOKUP(U243,'FBCJ Jul-Des 2025'!$G$10:$P$1302,8,0) -> 70009110 | W243: =+VLOOKUP(V243,Sheet1!$A$2:$B$27,2,0) -> Biaya Survey dan Analisa | X243: =+VLOOKUP(U243,'FBCJ Jul-Des 2025'!$G$10:$P$1302,9,0) -> P206D1SLSS | Y243: SP | Z243: 1557224 | AA243: 20250804 | AB243: 50000
C244: 10000001 | D244: 04.08.2025 | F244: 12006516 | H244: 04.08.2025 | I244: =+MID(H244,4,2) -> 08 | J244: 50 | K244: -50000 | L244: IDR | M244: -50000 | N244: IDR | R244: R124 | S244: 613/PPC/VII/2025 | T244: SURVEY DAN ANALISA | U244: BY HC HOCHEE EBP/0625/0462-2411776138 | V244: =+VLOOKUP(U244,'FBCJ Jul-Des 2025'!$G$10:$P$1302,8,0) -> 70009110 | W244: =+VLOOKUP(V244,Sheet1!$A$2:$B$27,2,0) -> Biaya Survey dan Analisa | X244: =+VLOOKUP(U244,'FBCJ Jul-Des 2025'!$G$10:$P$1302,9,0) -> P206D1SLSS | Y244: SP | Z244: 1557224 | AA244: 20250804 | AB244: 50000
C245: 10000001 | D245: 04.08.2025 | F245: 12006517 | H245: 04.08.2025 | I245: =+MID(H245,4,2) -> 08 | J245: 50 | K245: -50000 | L245: IDR | M245: -50000 | N245: IDR | R245: R124 | S245: 613/PPC/VII/2025 | T245: SURVEY DAN ANALISA | U245: BY HC RAMFOOD EBP/0625/0453-2411776116 | V245: =+VLOOKUP(U245,'FBCJ Jul-Des 2025'!$G$10:$P$1302,8,0) -> 70009110 | W245: =+VLOOKUP(V245,Sheet1!$A$2:$B$27,2,0) -> Biaya Survey dan Analisa | X245: =+VLOOKUP(U245,'FBCJ Jul-Des 2025'!$G$10:$P$1302,9,0) -> C206D1SLSS | Y245: SP | Z245: 1557224 | AA245: 20250804 | AB245: 50000
C246: 10000001 | D246: 04.08.2025 | F246: 12006518 | H246: 04.08.2025 | I246: =+MID(H246,4,2) -> 08 | J246: 50 | K246: -50000 | L246: IDR | M246: -50000 | N246: IDR | R246: R124 | S246: 613/PPC/VII/2025 | T246: SURVEY DAN ANALISA | U246: BY HC RAMFOOD EBP/0625/0454-2411776117 | V246: =+VLOOKUP(U246,'FBCJ Jul-Des 2025'!$G$10:$P$1302,8,0) -> 70009110 | W246: =+VLOOKUP(V246,Sheet1!$A$2:$B$27,2,0) -> Biaya Survey dan Analisa | X246: =+VLOOKUP(U246,'FBCJ Jul-Des 2025'!$G$10:$P$1302,9,0) -> C206D1SLSS | Y246: SP | Z246: 1557224 | AA246: 20250804 | AB246: 50000
C247: 10000001 | D247: 04.08.2025 | F247: 12006519 | H247: 04.08.2025 | I247: =+MID(H247,4,2) -> 08 | J247: 50 | K247: -50000 | L247: IDR | M247: -50000 | N247: IDR | R247: R124 | S247: 613/PPC/VII/2025 | T247: SURVEY DAN ANALISA | U247: BY REPROSES HC HOME CHAIN EBP/0625/0454-2411776133 | V247: =+VLOOKUP(U247,'FBCJ Jul-Des 2025'!$G$10:$P$1302,8,0) -> 70009110 | W247: =+VLOOKUP(V247,Sheet1!$A$2:$B$27,2,0) -> Biaya Survey dan Analisa | X247: =+VLOOKUP(U247,'FBCJ Jul-Des 2025'!$G$10:$P$1302,9,0) -> P206D1SLSS | Y247: SP | Z247: 1557224 | AA247: 20250804 | AB247: 50000
C248: 10000001 | D248: 04.08.2025 | F248: 12006520 | H248: 04.08.2025 | I248: =+MID(H248,4,2) -> 08 | J248: 50 | K248: -50000 | L248: IDR | M248: -50000 | N248: IDR | R248: R124 | S248: 613/PPC/VII/2025 | T248: SURVEY DAN ANALISA | U248: BY HC SUNNY EBP/0725/0485-2411776270 | V248: =+VLOOKUP(U248,'FBCJ Jul-Des 2025'!$G$10:$P$1302,8,0) -> 70009110 | W248: =+VLOOKUP(V248,Sheet1!$A$2:$B$27,2,0) -> Biaya Survey dan Analisa | X248: =+VLOOKUP(U248,'FBCJ Jul-Des 2025'!$G$10:$P$1302,9,0) -> P206D1SLSS | Y248: SP | Z248: 1557224 | AA248: 20250804 | AB248: 50000
C249: 10000001 | D249: 04.08.2025 | F249: 12006521 | H249: 04.08.2025 | I249: =+MID(H249,4,2) -> 08 | J249: 50 | K249: -369000 | L249: IDR | M249: -369000 | N249: IDR | R249: R124 | S249: 622/PPC/VII/2025 | T249: TRANSPORTASI LOKAL | U249: BY TRANSPORTASI LOKAL 300725 | V249: =+VLOOKUP(U249,'FBCJ Jul-Des 2025'!$G$10:$P$1302,8,0) -> 70106100 | W249: =+VLOOKUP(V249,Sheet1!$A$2:$B$27,2,0) -> Biaya Transportasi Lokal | X249: =+VLOOKUP(U249,'FBCJ Jul-Des 2025'!$G$10:$P$1302,9,0) -> R124D1HRGA | Y249: SP | Z249: 1557224 | AA249: 20250804 | AB249: 369000
... C391: 10000001 | D391: 20.08.2025 | F391: 12006663 | H391: 20.08.2025 | I391: =+MID(H391,4,2) -> 08 | J391: 50 | K391: -604000 | L391: IDR | M391: -604000 | N391: IDR | R391: R124 | S391: 645/PPC/VIII/25 | T391: PEMEL.KEND&A.BERAT MATRL | U391: BY PEMB SKUN, CONNECTOR LIGHT, NIPLE DRAT,DLL | V391: =+VLOOKUP(U391,'FBCJ Jul-Des 2025'!$G$10:$P$1302,8,0) -> 70101202 | W391: =+VLOOKUP(V391,Sheet1!$A$2:$B$27,2,0) -> By Pemeliharaan Kend,ABerat,Mesin-Material Pihak3 | X391: =+VLOOKUP(U391,'FBCJ Jul-Des 2025'!$G$10:$P$1302,9,0) -> R124REF | Y391: SP | Z391: 1557224 | AA391: 20250820 | AB391: 604000
C392: 10000001 | D392: 20.08.2025 | F392: 12006664 | H392: 20.08.2025 | I392: =+MID(H392,4,2) -> 08 | J392: 50 | K392: -280000 | L392: IDR | M392: -280000 | N392: IDR | R392: R124 | S392: 645/PPC/VIII/25 | T392: UANG MUKA BIAYA | U392: BY STRAINER VALVE AMARTA T FP:04002500243246107 | V392: 15000900 | W392: =+VLOOKUP(V392,Sheet1!$A$2:$B$27,2,0) -> Biaya Lainnya Yang Dibayar Di Muka | X392: - | Y392: SP | Z392: 1557224 | AA392: 20250820 | AB392: 280000
C393: 10000001 | D393: 20.08.2025 | F393: 12006665 | H393: 20.08.2025 | I393: =+MID(H393,4,2) -> 08 | J393: 50 | K393: -650000 | L393: IDR | M393: -650000 | N393: IDR | R393: R124 | S393: 667/PPC/VIII/25 | T393: UANG MUKA BIAYA | U393: BY CHECK VALVE AMARTA T FP:04002500243246108 | V393: 15000900 | W393: =+VLOOKUP(V393,Sheet1!$A$2:$B$27,2,0) -> Biaya Lainnya Yang Dibayar Di Muka | X393: - | Y393: SP | Z393: 1557224 | AA393: 20250820 | AB393: 650000
C394: 10000001 | D394: 20.08.2025 | F394: 12006666 | H394: 20.08.2025 | I394: =+MID(H394,4,2) -> 08 | J394: 40 | K394: 34438078 | L394: IDR | M394: 34438078 | N394: IDR | R394: R124 | T394: BANK IN TRANSIT | U394: PETTY CASH RUNGKUT SURABAYA PERIODE 01-20 AGUST 25 | Y394: SP | Z394: 1557224 | AA394: 20250820 | AB394: 34438078
C395: 10000001 | D395: 02.09.2025 | F395: 12007299 | H395: 02.09.2025 | I395: =+MID(H395,4,2) -> 09 | J395: 50 | K395: -500000 | L395: IDR | M395: -500000 | N395: IDR | R395: R124 | S395: 678/PPC/VIII/25 | T395: OLAHRAGA DAN PERMAINAN | U395: BY Olahraga cardio boxing 15 Agustus'25 | V395: =+VLOOKUP(U395,'FBCJ Jul-Des 2025'!$G$10:$P$1302,8,0) -> 70107300 | W395: =+VLOOKUP(V395,Sheet1!$A$2:$B$27,2,0) -> Biaya Olahraga Dan Permainan | X395: =+VLOOKUP(U395,'FBCJ Jul-Des 2025'!$G$10:$P$1302,9,0) -> R124D1HRDV | Y395: SP | Z395: 1631293 | AA395: 20250902 | AB395: 500000
C396: 10000001 | D396: 02.09.2025 | F396: 12007300 | H396: 02.09.2025 | I396: =+MID(H396,4,2) -> 09 | J396: 50 | K396: -50000 | L396: IDR | M396: -50000 | N396: IDR | R396: R124 | S396: 690/PPC/VIII/25 | T396: SURVEY DAN ANALISA | U396: BY HC SG OILSEED EBP/0825/0596-241177690 | V396: =+VLOOKUP(U396,'FBCJ Jul-Des 2025'!$G$10:$P$1302,8,0) -> 70009110 | W396: =+VLOOKUP(V396,Sheet1!$A$2:$B$27,2,0) -> Biaya Survey dan Analisa | X396: =+VLOOKUP(U396,'FBCJ Jul-Des 2025'!$G$10:$P$1302,9,0) -> P206D1SLSC | Y396: SP | Z396: 1631293 | AA396: 20250902 | AB396: 50000
C397: 10000001 | D397: 02.09.2025 | F397: 12007301 | H397: 02.09.2025 | I397: =+MID(H397,4,2) -> 09 | J397: 50 | K397: -50000 | L397: IDR | M397: -50000 | N397: IDR | R397: R124 | S397: 690/PPC/VIII/25 | T397: SURVEY DAN ANALISA | U397: BY HC XIAMEN AOZHI EBP/0825/0436-2411776918 | V397: =+VLOOKUP(U397,'FBCJ Jul-Des 2025'!$G$10:$P$1302,8,0) -> 70009110 | W397: =+VLOOKUP(V397,Sheet1!$A$2:$B$27,2,0) -> Biaya Survey dan Analisa | X397: =+VLOOKUP(U397,'FBCJ Jul-Des 2025'!$G$10:$P$1302,9,0) -> P206D1SLSC | Y397: SP | Z397: 1631293 | AA397: 20250902 | AB397: 50000
C398: 10000001 | D398: 02.09.2025 | F398: 12007302 | H398: 02.09.2025 | I398: =+MID(H398,4,2) -> 09 | J398: 50 | K398: -50000 | L398: IDR | M398: -50000 | N398: IDR | R398: R124 | S398: 690/PPC/VIII/25 | T398: SURVEY DAN ANALISA | U398: BY HC HORGOS EBP/0825/0588-2411776862 | V398: =+VLOOKUP(U398,'FBCJ Jul-Des 2025'!$G$10:$P$1302,8,0) -> 70009110 | W398: =+VLOOKUP(V398,Sheet1!$A$2:$B$27,2,0) -> Biaya Survey dan Analisa | X398: =+VLOOKUP(U398,'FBCJ Jul-Des 2025'!$G$10:$P$1302,9,0) -> P206D1SLSC | Y398: SP | Z398: 1631293 | AA398: 20250902 | AB398: 50000
C399: 10000001 | D399: 02.09.2025 | F399: 12007303 | H399: 02.09.2025 | I399: =+MID(H399,4,2) -> 09 | J399: 50 | K399: -50000 | L399: IDR | M399: -50000 | N399: IDR | R399: R124 | S399: 690/PPC/VIII/25 | T399: SURVEY DAN ANALISA | U399: BY HC FUJIAN NANAN EBP/0825/0580-2411776818 | V399: =+VLOOKUP(U399,'FBCJ Jul-Des 2025'!$G$10:$P$1302,8,0) -> 70009110 | W399: =+VLOOKUP(V399,Sheet1!$A$2:$B$27,2,0) -> Biaya Survey dan Analisa | X399: =+VLOOKUP(U399,'FBCJ Jul-Des 2025'!$G$10:$P$1302,9,0) -> P206D1SLSC | Y399: SP | Z399: 1631293 | AA399: 20250902 | AB399: 50000
C400: 10000001 | D400: 02.09.2025 | F400: 12007304 | H400: 02.09.2025 | I400: =+MID(H400,4,2) -> 09 | J400: 50 | K400: -50000 | L400: IDR | M400: -50000 | N400: IDR | R400: R124 | S400: 690/PPC/VIII/25 | T400: SURVEY DAN ANALISA | U400: BY HC HORGOS EBP/0825/0620-2411776989 | V400: =+VLOOKUP(U400,'FBCJ Jul-Des 2025'!$G$10:$P$1302,8,0) -> 70009110 | W400: =+VLOOKUP(V400,Sheet1!$A$2:$B$27,2,0) -> Biaya Survey dan Analisa | X400: =+VLOOKUP(U400,'FBCJ Jul-Des 2025'!$G$10:$P$1302,9,0) -> P206D1SLSC | Y400: SP | Z400: 1631293 | AA400: 20250902 | AB400: 50000
C401: 10000001 | D401: 02.09.2025 | F401: 12007305 | H401: 02.09.2025 | I401: =+MID(H401,4,2) -> 09 | J401: 50 | K401: -50000 | L401: IDR | M401: -50000 | N401: IDR | R401: R124 | S401: 692/PPC/VIII/25 | T401: SURVEY DAN ANALISA | U401: BY HC HORGOS BAIPENG 2411776885 | V401: =+VLOOKUP(U401,'FBCJ Jul-Des 2025'!$G$10:$P$1302,8,0) -> 70009110 | W401: =+VLOOKUP(V401,Sheet1!$A$2:$B$27,2,0) -> Biaya Survey dan Analisa | X401: =+VLOOKUP(U401,'FBCJ Jul-Des 2025'!$G$10:$P$1302,9,0) -> P206D1SLSS | Y401: SP | Z401: 1631293 | AA401: 20250902 | AB401: 50000
C402: 10000001 | D402: 02.09.2025 | F402: 12007306 | H402: 02.09.2025 | I402: =+MID(H402,4,2) -> 09 | J402: 50 | K402: -50000 | L402: IDR | M402: -50000 | N402: IDR | R402: R124 | S402: 692/PPC/VIII/25 | T402: SURVEY DAN ANALISA | U402: BY HC HORGOS BAIPENG 2411776884 | V402: =+VLOOKUP(U402,'FBCJ Jul-Des 2025'!$G$10:$P$1302,8,0) -> 70009110 | W402: =+VLOOKUP(V402,Sheet1!$A$2:$B$27,2,0) -> Biaya Survey dan Analisa | X402: =+VLOOKUP(U402,'FBCJ Jul-Des 2025'!$G$10:$P$1302,9,0) -> P206D1SLSS | Y402: SP | Z402: 1631293 | AA402: 20250902 | AB402: 50000
C403: 10000001 | D403: 02.09.2025 | F403: 12007307 | H403: 02.09.2025 | I403: =+MID(H403,4,2) -> 09 | J403: 50 | K403: -50000 | L403: IDR | M403: -50000 | N403: IDR | R403: R124 | S403: 692/PPC/VIII/25 | T403: SURVEY DAN ANALISA | U403: BY HC SG OIL SEED 2411776891 | V403: =+VLOOKUP(U403,'FBCJ Jul-Des 2025'!$G$10:$P$1302,8,0) -> 70009110 | W403: =+VLOOKUP(V403,Sheet1!$A$2:$B$27,2,0) -> Biaya Survey dan Analisa | X403: =+VLOOKUP(U403,'FBCJ Jul-Des 2025'!$G$10:$P$1302,9,0) -> P206D1SLSS | Y403: SP | Z403: 1631293 | AA403: 20250902 | AB403: 50000
C404: 10000001 | D404: 02.09.2025 | F404: 12007308 | H404: 02.09.2025 | I404: =+MID(H404,4,2) -> 09 | J404: 50 | K404: -50000 | L404: IDR | M404: -50000 | N404: IDR | R404: R124 | S404: 692/PPC/VIII/25 | T404: SURVEY DAN ANALISA | U404: BY HC HORGOS BAIPENG 2411776863 | V404: =+VLOOKUP(U404,'FBCJ Jul-Des 2025'!$G$10:$P$1302,8,0) -> 70009110 | W404: =+VLOOKUP(V404,Sheet1!$A$2:$B$27,2,0) -> Biaya Survey dan Analisa | X404: =+VLOOKUP(U404,'FBCJ Jul-Des 2025'!$G$10:$P$1302,9,0) -> P206D1SLSS | Y404: SP | Z404: 1631293 | AA404: 20250902 | AB404: 50000
C405: 10000001 | D405: 02.09.2025 | F405: 12007309 | H405: 02.09.2025 | I405: =+MID(H405,4,2) -> 09 | J405: 50 | K405: -50000 | L405: IDR | M405: -50000 | N405: IDR | R405: R124 | S405: 692/PPC/VIII/25 | T405: SURVEY DAN ANALISA | U405: BY HC GUANGDONG SHENGRONG 2411776775 | V405: =+VLOOKUP(U405,'FBCJ Jul-Des 2025'!$G$10:$P$1302,8,0) -> 70009110 | W405: =+VLOOKUP(V405,Sheet1!$A$2:$B$27,2,0) -> Biaya Survey dan Analisa | X405: =+VLOOKUP(U405,'FBCJ Jul-Des 2025'!$G$10:$P$1302,9,0) -> P206D1SLSS | Y405: SP | Z405: 1631293 | AA405: 20250902 | AB405: 50000
C406: 10000001 | D406: 02.09.2025 | F406: 12007310 | H406: 02.09.2025 | I406: =+MID(H406,4,2) -> 09 | J406: 50 | K406: -50000 | L406: IDR | M406: -50000 | N406: IDR | R406: R124 | S406: 692/PPC/VIII/25 | T406: SURVEY DAN ANALISA | U406: BY HC SG OILSEED 2411776838 | V406: =+VLOOKUP(U406,'FBCJ Jul-Des 2025'!$G$10:$P$1302,8,0) -> 70009110 | W406: =+VLOOKUP(V406,Sheet1!$A$2:$B$27,2,0) -> Biaya Survey dan Analisa | X406: =+VLOOKUP(U406,'FBCJ Jul-Des 2025'!$G$10:$P$1302,9,0) -> P206D1SLSS | Y406: SP | Z406: 1631293 | AA406: 20250902 | AB406: 50000
... C545: 10000001 | D545: 15.09.2025 | F545: 12007445 | H545: 15.09.2025 | I545: =+MID(H545,4,2) -> 09 | J545: 50 | K545: -800000 | L545: IDR | M545: -800000 | N545: IDR | R545: R124 | S545: 738/PPC/IX/25 | T545: PEMEL.KEND&A.BERAT MATRL | U545: BY PEMB. Bearing Fan BAC | V545: =+VLOOKUP(U545,'FBCJ Jul-Des 2025'!$G$10:$P$1302,8,0) -> 70101202 | W545: =+VLOOKUP(V545,Sheet1!$A$2:$B$27,2,0) -> By Pemeliharaan Kend,ABerat,Mesin-Material Pihak3 | X545: =+VLOOKUP(U545,'FBCJ Jul-Des 2025'!$G$10:$P$1302,9,0) -> R124REF | Y545: SP | Z545: 1631293 | AA545: 20250915 | AB545: 800000
C546: 10000001 | D546: 15.09.2025 | F546: 12007446 | H546: 15.09.2025 | I546: =+MID(H546,4,2) -> 09 | J546: 50 | K546: -690000 | L546: IDR | M546: -690000 | N546: IDR | R546: R124 | S546: 694/PPC/VIII/25 | T546: UANG MUKA BIAYA | U546: BY PEMB.PRESSR SWITCH HYDRANT FP04002500244949528 | V546: 15000900 | W546: =+VLOOKUP(V546,Sheet1!$A$2:$B$27,2,0) -> Biaya Lainnya Yang Dibayar Di Muka | X546: - | Y546: SP | Z546: 1631293 | AA546: 20250915 | AB546: 690000
C547: 10000001 | D547: 15.09.2025 | F547: 12007447 | H547: 15.09.2025 | I547: =+MID(H547,4,2) -> 09 | J547: 50 | K547: -40770 | L547: IDR | M547: -40770 | N547: IDR | R547: R124 | S547: 699/PPC/VIII/25 | T547: UANG MUKA BIAYA | U547: BY PEMBELIAN DOUBLE NIPLE FP 04002500260289183 | V547: 15000900 | W547: =+VLOOKUP(V547,Sheet1!$A$2:$B$27,2,0) -> Biaya Lainnya Yang Dibayar Di Muka | X547: - | Y547: SP | Z547: 1631293 | AA547: 20250915 | AB547: 40770
C548: 10000001 | D548: 15.09.2025 | F548: 12007448 | H548: 15.09.2025 | I548: =+MID(H548,4,2) -> 09 | J548: 50 | K548: -321404 | L548: IDR | M548: -321404 | N548: IDR | R548: R124 | S548: 726/PPC/IX/25 | T548: UANG MUKA BIAYA | U548: BY PEMB. DUNLOP P.430& 5/16 NB FP04002500262634254 | V548: 15000900 | W548: =+VLOOKUP(V548,Sheet1!$A$2:$B$27,2,0) -> Biaya Lainnya Yang Dibayar Di Muka | X548: - | Y548: SP | Z548: 1631293 | AA548: 20250915 | AB548: 321404
C549: 10000001 | D549: 15.09.2025 | F549: 12007449 | H549: 15.09.2025 | I549: =+MID(H549,4,2) -> 09 | J549: 50 | K549: -151679 | L549: IDR | M549: -151679 | N549: IDR | R549: R124 | S549: 697/PPC/VIII/25 | T549: UANG MUKA BIAYA | U549: BY PEMB. STRAIGHT MALE FP04002500259735097 | V549: 15000900 | W549: =+VLOOKUP(V549,Sheet1!$A$2:$B$27,2,0) -> Biaya Lainnya Yang Dibayar Di Muka | X549: - | Y549: SP | Z549: 1631293 | AA549: 20250915 | AB549: 151679
C550: 10000001 | D550: 15.09.2025 | F550: 12007450 | H550: 15.09.2025 | I550: =+MID(H550,4,2) -> 09 | J550: 50 | K550: -61000 | L550: IDR | M550: -61000 | N550: IDR | R550: R124 | S550: 697/PPC/VIII/25 | T550: PBAIKN&PRAWATN PRABT MATR | U550: BY PEMB. SUNLIGHT 5PCS | V550: =+VLOOKUP(U550,'FBCJ Jul-Des 2025'!$G$10:$P$1302,8,0) -> 70101114 | W550: =+VLOOKUP(V550,Sheet1!$A$2:$B$27,2,0) -> By Perbaikan & Perawatan Perabot Material Pihak3 | X550: =+VLOOKUP(U550,'FBCJ Jul-Des 2025'!$G$10:$P$1302,9,0) -> R124FRA | Y550: SP | Z550: 1631293 | AA550: 20250915 | AB550: 61000
C551: 10000001 | D551: 15.09.2025 | F551: 12007451 | H551: 15.09.2025 | I551: =+MID(H551,4,2) -> 09 | J551: 50 | K551: -133500 | L551: IDR | M551: -133500 | N551: IDR | R551: R124 | S551: 741/PPC/IX/25 | T551: PEMEL.KEND&A.BERAT MATRL | U551: BY PERBAIKAN MOTOR POMPA KMSC & TANKI P10 | V551: =+VLOOKUP(U551,'FBCJ Jul-Des 2025'!$G$10:$P$1302,8,0) -> 70101202 | W551: =+VLOOKUP(V551,Sheet1!$A$2:$B$27,2,0) -> By Pemeliharaan Kend,ABerat,Mesin-Material Pihak3 | X551: =+VLOOKUP(U551,'FBCJ Jul-Des 2025'!$G$10:$P$1302,9,0) -> R124STTRK | Y551: SP | Z551: 1631293 | AA551: 20250915 | AB551: 133500
C552: 10000001 | D552: 15.09.2025 | F552: 12007452 | H552: 15.09.2025 | I552: =+MID(H552,4,2) -> 09 | J552: 50 | K552: -290500 | L552: IDR | M552: -290500 | N552: IDR | R552: R124 | S552: 737/PPC/IX/25 | T552: BIAYA MESS | U552: BY PDAM BULANAN MESS PT SMART PTI SEPT 25 | V552: =+VLOOKUP(U552,'FBCJ Jul-Des 2025'!$G$10:$P$1302,8,0) -> 70107100 | W552: =+VLOOKUP(V552,Sheet1!$A$2:$B$27,2,0) -> Biaya Mess | X552: =+VLOOKUP(U552,'FBCJ Jul-Des 2025'!$G$10:$P$1302,9,0) -> R124D1HRGA | Y552: SP | Z552: 1631293 | AA552: 20250915 | AB552: 290500
C553: 10000001 | D553: 15.09.2025 | F553: 12007453 | H553: 15.09.2025 | I553: =+MID(H553,4,2) -> 09 | J553: 50 | K553: -430000 | L553: IDR | M553: -430000 | N553: IDR | R553: R124 | S553: 723/PPC/IX/25 | T553: PEMEL.KEND&A.BERAT MATRL | U553: BY PERAWATAN BERKALA KENDARAAN NOPOL L2167FT | V553: =+VLOOKUP(U553,'FBCJ Jul-Des 2025'!$G$10:$P$1302,8,0) -> 70101202 | W553: =+VLOOKUP(V553,Sheet1!$A$2:$B$27,2,0) -> By Pemeliharaan Kend,ABerat,Mesin-Material Pihak3 | X553: =+VLOOKUP(U553,'FBCJ Jul-Des 2025'!$G$10:$P$1302,9,0) -> C206D1SLSS | Y553: SP | Z553: 1631293 | AA553: 20250915 | AB553: 430000
C554: 10000001 | D554: 15.09.2025 | F554: 12007454 | H554: 15.09.2025 | I554: =+MID(H554,4,2) -> 09 | J554: 50 | K554: -298000 | L554: IDR | M554: -298000 | N554: IDR | R554: R124 | S554: 720/PPC/IX/25 | T554: PEMEL.KEND&A.BERAT MATRL | U554: BY PERAWATAN BERKALA KENDARAAN NOPOL L2057EK | V554: =+VLOOKUP(U554,'FBCJ Jul-Des 2025'!$G$10:$P$1302,8,0) -> 70101202 | W554: =+VLOOKUP(V554,Sheet1!$A$2:$B$27,2,0) -> By Pemeliharaan Kend,ABerat,Mesin-Material Pihak3 | X554: =+VLOOKUP(U554,'FBCJ Jul-Des 2025'!$G$10:$P$1302,9,0) -> P206D1SLSS | Y554: SP | Z554: 1631293 | AA554: 20250915 | AB554: 298000
C555: 10000001 | D555: 15.09.2025 | F555: 12007455 | H555: 15.09.2025 | I555: =+MID(H555,4,2) -> 09 | J555: 40 | K555: 30159697 | L555: IDR | M555: 30159697 | N555: IDR | R555: R124 | T555: BANK IN TRANSIT | U555: PETTY CASH RUNGKUT SURABAYA PERIODE 01-15 SEPT 25 | Y555: SP | Z555: 1631293 | AA555: 20250915 | AB555: 30159697
C556: 10000001 | D556: 01.10.2025 | F556: 12008043 | H556: 01.10.2025 | I556: =+MID(H556,4,2) -> 10 | J556: 50 | K556: -990000 | L556: IDR | M556: -990000 | N556: IDR | R556: R124 | S556: 746/PPC/IX/2025 | T556: PEMEL.BNGAN&PSARANA MATRL | U556: BY PEMB SIKA GROUT U/ PERBAIKAN JALAN PARKIR SPD M | V556: =+VLOOKUP(U556,'FBCJ Jul-Des 2025'!$G$10:$P$1302,8,0) -> 70101102 | W556: =+VLOOKUP(V556,Sheet1!$A$2:$B$27,2,0) -> By Pemeliharaan BgnanPrasarana Material Pihak3 | X556: =+VLOOKUP(U556,'FBCJ Jul-Des 2025'!$G$10:$P$1302,9,0) -> R124D1HRGA | Y556: SP | Z556: 1719278 | AA556: 20251001 | AB556: 990000
C557: 10000001 | D557: 02.10.2025 | F557: 12008044 | H557: 02.10.2025 | I557: =+MID(H557,4,2) -> 10 | J557: 50 | K557: -1000000 | L557: IDR | M557: -1000000 | N557: IDR | R557: R124 | S557: 747/PPC/IX/2025 | T557: UMUM & ADMIN LAIN | U557: BY PEMB MATERAI U/ ADM EXPORT | V557: =+VLOOKUP(U557,'FBCJ Jul-Des 2025'!$G$10:$P$1302,8,0) -> 70119300 | W557: =+VLOOKUP(V557,Sheet1!$A$2:$B$27,2,0) -> Biaya Umum dan Administrasi | X557: =+VLOOKUP(U557,'FBCJ Jul-Des 2025'!$G$10:$P$1302,9,0) -> P206D1SLSS | Y557: SP | Z557: 1719278 | AA557: 20251002 | AB557: 1000000
C558: 10000001 | D558: 02.10.2025 | F558: 12008045 | H558: 02.10.2025 | I558: =+MID(H558,4,2) -> 10 | J558: 50 | K558: -480000 | L558: IDR | M558: -480000 | N558: IDR | R558: R124 | S558: 757/PPC/IX/2025 | T558: OLAHRAGA DAN PERMAINAN | U558: BY OLAHRAGA 12/09/2025 | V558: =+VLOOKUP(U558,'FBCJ Jul-Des 2025'!$G$10:$P$1302,8,0) -> 70107300 | W558: =+VLOOKUP(V558,Sheet1!$A$2:$B$27,2,0) -> Biaya Olahraga Dan Permainan | X558: =+VLOOKUP(U558,'FBCJ Jul-Des 2025'!$G$10:$P$1302,9,0) -> R124D1HRDV | Y558: SP | Z558: 1719278 | AA558: 20251002 | AB558: 480000
C559: 10000001 | D559: 02.10.2025 | F559: 12008046 | H559: 02.10.2025 | I559: =+MID(H559,4,2) -> 10 | J559: 50 | K559: -80000 | L559: IDR | M559: -80000 | N559: IDR | R559: R124 | S559: 758/PPC/IX/2025 | T559: PEMEL.KEND&A.BERAT MATRL | U559: BY PEMB RODA SELING IBC | V559: =+VLOOKUP(U559,'FBCJ Jul-Des 2025'!$G$10:$P$1302,8,0) -> 70101202 | W559: =+VLOOKUP(V559,Sheet1!$A$2:$B$27,2,0) -> By Pemeliharaan Kend,ABerat,Mesin-Material Pihak3 | X559: =+VLOOKUP(U559,'FBCJ Jul-Des 2025'!$G$10:$P$1302,9,0) -> R124TCP | Y559: SP | Z559: 1719278 | AA559: 20251002 | AB559: 80000
C560: 10000001 | D560: 02.10.2025 | F560: 12008047 | H560: 02.10.2025 | I560: =+MID(H560,4,2) -> 10 | J560: 50 | K560: -990000 | L560: IDR | M560: -990000 | N560: IDR | R560: R124 | S560: 759/PPC/IX/2025 | T560: PEMEL.BNGAN&PSARANA MATRL | U560: BY PEMB SIKA GROUT U/ PERBAIKAN JALAN UMUM | V560: =+VLOOKUP(U560,'FBCJ Jul-Des 2025'!$G$10:$P$1302,8,0) -> 70101102 | W560: =+VLOOKUP(V560,Sheet1!$A$2:$B$27,2,0) -> By Pemeliharaan BgnanPrasarana Material Pihak3 | X560: =+VLOOKUP(U560,'FBCJ Jul-Des 2025'!$G$10:$P$1302,9,0) -> R124D1HRGA | Y560: SP | Z560: 1719278 | AA560: 20251002 | AB560: 990000
C561: 10000001 | D561: 02.10.2025 | F561: 12008048 | H561: 02.10.2025 | I561: =+MID(H561,4,2) -> 10 | J561: 50 | K561: -225000 | L561: IDR | M561: -225000 | N561: IDR | R561: R124 | S561: 760/PPC/IX/2025 | T561: PBAIKN&PRAWATN PRABT MATR | U561: BY PEMB DUCTING PSD U/ PENGRAPIAN KABEL KANTOR LOG | V561: =+VLOOKUP(U561,'FBCJ Jul-Des 2025'!$G$10:$P$1302,8,0) -> 70101114 | W561: =+VLOOKUP(V561,Sheet1!$A$2:$B$27,2,0) -> By Perbaikan & Perawatan Perabot Material Pihak3 | X561: =+VLOOKUP(U561,'FBCJ Jul-Des 2025'!$G$10:$P$1302,9,0) -> R124D1HRGA | Y561: SP | Z561: 1719278 | AA561: 20251002 | AB561: 225000
C562: 10000001 | D562: 02.10.2025 | F562: 12008049 | H562: 02.10.2025 | I562: =+MID(H562,4,2) -> 10 | J562: 50 | K562: -100000 | L562: IDR | M562: -100000 | N562: IDR | R562: R124 | S562: 754/PPC/IX/2025 | T562: SURVEY DAN ANALISA | U562: BY HC DINKES POLIVA ETP 2411777074 | V562: =+VLOOKUP(U562,'FBCJ Jul-Des 2025'!$G$10:$P$1302,8,0) -> 70009110 | W562: =+VLOOKUP(V562,Sheet1!$A$2:$B$27,2,0) -> Biaya Survey dan Analisa | X562: =+VLOOKUP(U562,'FBCJ Jul-Des 2025'!$G$10:$P$1302,9,0) -> M204D1COMM | Y562: SP | Z562: 1719278 | AA562: 20251002 | AB562: 100000
C563: 10000001 | D563: 02.10.2025 | F563: 12008050 | H563: 02.10.2025 | I563: =+MID(H563,4,2) -> 10 | J563: 50 | K563: -350000 | L563: IDR | M563: -350000 | N563: IDR | R563: R124 | S563: 754/PPC/IX/2025 | T563: SURVEY DAN ANALISA | U563: BY COO KADIN ASSUDAMAL EBP 2411777285 | V563: =+VLOOKUP(U563,'FBCJ Jul-Des 2025'!$G$10:$P$1302,8,0) -> 70009110 | W563: =+VLOOKUP(V563,Sheet1!$A$2:$B$27,2,0) -> Biaya Survey dan Analisa | X563: =+VLOOKUP(U563,'FBCJ Jul-Des 2025'!$G$10:$P$1302,9,0) -> C206D1SLSS | Y563: SP | Z563: 1719278 | AA563: 20251002 | AB563: 350000
C564: 10000001 | D564: 02.10.2025 | F564: 12008051 | H564: 02.10.2025 | I564: =+MID(H564,4,2) -> 10 | J564: 50 | K564: -200000 | L564: IDR | M564: -200000 | N564: IDR | R564: R124 | S564: 754/PPC/IX/2025 | T564: SURVEY DAN ANALISA | U564: BY COO KADIN AL JAZIRA EBP 2411777288 | V564: =+VLOOKUP(U564,'FBCJ Jul-Des 2025'!$G$10:$P$1302,8,0) -> 70009110 | W564: =+VLOOKUP(V564,Sheet1!$A$2:$B$27,2,0) -> Biaya Survey dan Analisa | X564: =+VLOOKUP(U564,'FBCJ Jul-Des 2025'!$G$10:$P$1302,9,0) -> P206D1SLSS | Y564: SP | Z564: 1719278 | AA564: 20251002 | AB564: 200000
C565: 10000001 | D565: 02.10.2025 | F565: 12008052 | H565: 02.10.2025 | I565: =+MID(H565,4,2) -> 10 | J565: 50 | K565: -50000 | L565: IDR | M565: -50000 | N565: IDR | R565: R124 | S565: 762/PPC/IX/2025 | T565: SURVEY DAN ANALISA | U565: BY HC SG OILSEED EBP 2411777314 | V565: =+VLOOKUP(U565,'FBCJ Jul-Des 2025'!$G$10:$P$1302,8,0) -> 70009110 | W565: =+VLOOKUP(V565,Sheet1!$A$2:$B$27,2,0) -> Biaya Survey dan Analisa | X565: =+VLOOKUP(U565,'FBCJ Jul-Des 2025'!$G$10:$P$1302,9,0) -> P206D1SLSS | Y565: SP | Z565: 1719278 | AA565: 20251002 | AB565: 50000
C566: 10000001 | D566: 02.10.2025 | F566: 12008053 | H566: 02.10.2025 | I566: =+MID(H566,4,2) -> 10 | J566: 50 | K566: -50000 | L566: IDR | M566: -50000 | N566: IDR | R566: R124 | S566: 762/PPC/IX/2025 | T566: SURVEY DAN ANALISA | U566: BY HC FUJIAN NANAN EBP 2411777254 | V566: =+VLOOKUP(U566,'FBCJ Jul-Des 2025'!$G$10:$P$1302,8,0) -> 70009110 | W566: =+VLOOKUP(V566,Sheet1!$A$2:$B$27,2,0) -> Biaya Survey dan Analisa | X566: =+VLOOKUP(U566,'FBCJ Jul-Des 2025'!$G$10:$P$1302,9,0) -> P206D1SLSS | Y566: SP | Z566: 1719278 | AA566: 20251002 | AB566: 50000
C567: 10000001 | D567: 02.10.2025 | F567: 12008054 | H567: 02.10.2025 | I567: =+MID(H567,4,2) -> 10 | J567: 50 | K567: -50000 | L567: IDR | M567: -50000 | N567: IDR | R567: R124 | S567: 762/PPC/IX/2025 | T567: SURVEY DAN ANALISA | U567: BY HC FUJIAN NANAN EBP 2411777221 | V567: =+VLOOKUP(U567,'FBCJ Jul-Des 2025'!$G$10:$P$1302,8,0) -> 70009110 | W567: =+VLOOKUP(V567,Sheet1!$A$2:$B$27,2,0) -> Biaya Survey dan Analisa | X567: =+VLOOKUP(U567,'FBCJ Jul-Des 2025'!$G$10:$P$1302,9,0) -> P206D1SLSS | Y567: SP | Z567: 1719278 | AA567: 20251002 | AB567: 50000
... C694: 10000001 | D694: 03.10.2025 | F694: 12008180 | H694: 03.10.2025 | I694: =+MID(H694,4,2) -> 10 | J694: 50 | K694: -50000 | L694: IDR | M694: -50000 | N694: IDR | R694: R124 | S694: 774/PPC/IX/2025 | T694: SURVEY DAN ANALISA | U694: BY HC TALENT FAREAST EBP 2411777305 | V694: =+VLOOKUP(U694,'FBCJ Jul-Des 2025'!$G$10:$P$1302,8,0) -> 70009110 | W694: =+VLOOKUP(V694,Sheet1!$A$2:$B$27,2,0) -> Biaya Survey dan Analisa | X694: =+VLOOKUP(U694,'FBCJ Jul-Des 2025'!$G$10:$P$1302,9,0) -> P206D1SLSS | Y694: SP | Z694: 1719278 | AA694: 20251003 | AB694: 50000
C695: 10000001 | D695: 03.10.2025 | F695: 12008181 | H695: 03.10.2025 | I695: =+MID(H695,4,2) -> 10 | J695: 50 | K695: -545000 | L695: IDR | M695: -545000 | N695: IDR | R695: R124 | S695: 774/PPC/IX/2025 | T695: UANG MUKA BIAYA | U695: BY TELEX FRNAKIE PACIFIC I FP:04002500293417593 | V695: 15000900 | W695: =+VLOOKUP(V695,Sheet1!$A$2:$B$27,2,0) -> Biaya Lainnya Yang Dibayar Di Muka | X695: - | Y695: SP | Z695: 1719278 | AA695: 20251003 | AB695: 545000
C696: 10000001 | D696: 03.10.2025 | F696: 12008182 | H696: 03.10.2025 | I696: =+MID(H696,4,2) -> 10 | J696: 50 | K696: -198106 | L696: IDR | M696: -198106 | N696: IDR | R696: R124 | S696: 781/PPC/IX/2025 | T696: UANG MUKA BIAYA | U696: BY R2 1/4 DUNLOP SDA G FP:04002500279083808 | V696: 15000900 | W696: =+VLOOKUP(V696,Sheet1!$A$2:$B$27,2,0) -> Biaya Lainnya Yang Dibayar Di Muka | X696: - | Y696: SP | Z696: 1719278 | AA696: 20251003 | AB696: 198106
C697: 10000001 | D697: 03.10.2025 | F697: 12008183 | H697: 03.10.2025 | I697: =+MID(H697,4,2) -> 10 | J697: 50 | K697: -516150 | L697: IDR | M697: -516150 | N697: IDR | R697: R124 | S697: 740/PPC/IX/2025 | T697: UANG MUKA BIAYA | U697: BY BEARING SENTRAL L FP:04002500283362509 | V697: 15000900 | W697: =+VLOOKUP(V697,Sheet1!$A$2:$B$27,2,0) -> Biaya Lainnya Yang Dibayar Di Muka | X697: - | Y697: SP | Z697: 1719278 | AA697: 20251003 | AB697: 516150
...

Sheet Sheet1
C1: 07 | D1: 08 | E1: 09 | F1: 10 | G1: 11 | H1: 12 | I1: Total | L1: 07 | M1: 08 | N1: 09 | O1: 10 | P1: 11 | Q1: 12 | R1: Total | AA1: Cost Center | AB1: Total | AK1: Cost Center | AL1: Total
A2: 15000900 | B2: Biaya Lainnya Yang Dibayar Di Muka | C2: =+SUMIFS('List Petty Cash Jul-Des 25'!$AB:$AB,'List Petty Cash Jul-Des 25'!$I:$I,Sheet1!C$1,'List Petty Cash Jul-Des 25'!$V:$V,Sheet1!$A2) -> 131000 | D2: =+SUMIFS('List Petty Cash Jul-Des 25'!$AB:$AB,'List Petty Cash Jul-Des 25'!$I:$I,Sheet1!D$1,'List Petty Cash Jul-Des 25'!$V:$V,Sheet1!$A2) -> 930000 | E2: =+SUMIFS('List Petty Cash Jul-Des 25'!$AB:$AB,'List Petty Cash Jul-Des 25'!$I:$I,Sheet1!E$1,'List Petty Cash Jul-Des 25'!$V:$V,Sheet1!$A2) -> 1203853 | F2: =+SUMIFS('List Petty Cash Jul-Des 25'!$AB:$AB,'List Petty Cash Jul-Des 25'!$I:$I,Sheet1!F$1,'List Petty Cash Jul-Des 25'!$V:$V,Sheet1!$A2) -> 1469656 | G2: =+SUMIFS('List Petty Cash Jul-Des 25'!$AB:$AB,'List Petty Cash Jul-Des 25'!$I:$I,Sheet1!G$1,'List Petty Cash Jul-Des 25'!$V:$V,Sheet1!$A2) -> 4791052 | H2: =+SUMIFS('List Petty Cash Jul-Des 25'!$AB:$AB,'List Petty Cash Jul-Des 25'!$I:$I,Sheet1!H$1,'List Petty Cash Jul-Des 25'!$V:$V,Sheet1!$A2) -> 3214369 | I2: =+SUM(C2:H2) -> 11739930 | K2: - | L2: =+SUMIFS('List Petty Cash Jul-Des 25'!$AB:$AB,'List Petty Cash Jul-Des 25'!$I:$I,Sheet1!L$1,'List Petty Cash Jul-Des 25'!$X:$X,Sheet1!$K2) -> 131000 | M2: =+SUMIFS('List Petty Cash Jul-Des 25'!$AB:$AB,'List Petty Cash Jul-Des 25'!$I:$I,Sheet1!M$1,'List Petty Cash Jul-Des 25'!$X:$X,Sheet1!$K2) -> 930000 | N2: =+SUMIFS('List Petty Cash Jul-Des 25'!$AB:$AB,'List Petty Cash Jul-Des 25'!$I:$I,Sheet1!N$1,'List Petty Cash Jul-Des 25'!$X:$X,Sheet1!$K2) -> 1203853 | O2: =+SUMIFS('List Petty Cash Jul-Des 25'!$AB:$AB,'List Petty Cash Jul-Des 25'!$I:$I,Sheet1!O$1,'List Petty Cash Jul-Des 25'!$X:$X,Sheet1!$K2) -> 1469656 | P2: =+SUMIFS('List Petty Cash Jul-Des 25'!$AB:$AB,'List Petty Cash Jul-Des 25'!$I:$I,Sheet1!P$1,'List Petty Cash Jul-Des 25'!$X:$X,Sheet1!$K2) -> 4791052 | Q2: =+SUMIFS('List Petty Cash Jul-Des 25'!$AB:$AB,'List Petty Cash Jul-Des 25'!$I:$I,Sheet1!Q$1,'List Petty Cash Jul-Des 25'!$X:$X,Sheet1!$K2) -> 3214369 | R2: =+SUM(L2:Q2) -> 11739930 | S2: =+R2/$R$38*100% -> 0.036720098 | T2: 15000900 | AA2: R124D1HRGA | AB2: 107619783 | AE2: R124D1HRGA | AK2: R124D1HRGA | AL2: 107619783
A3: 70001110 | B3: Biaya Ekspor lainnya | C3: =+SUMIFS('List Petty Cash Jul-Des 25'!$AB:$AB,'List Petty Cash Jul-Des 25'!$I:$I,Sheet1!C$1,'List Petty Cash Jul-Des 25'!$V:$V,Sheet1!$A3) -> 29000 | D3: =+SUMIFS('List Petty Cash Jul-Des 25'!$AB:$AB,'List Petty Cash Jul-Des 25'!$I:$I,Sheet1!D$1,'List Petty Cash Jul-Des 25'!$V:$V,Sheet1!$A3) -> 886100 | E3: =+SUMIFS('List Petty Cash Jul-Des 25'!$AB:$AB,'List Petty Cash Jul-Des 25'!$I:$I,Sheet1!E$1,'List Petty Cash Jul-Des 25'!$V:$V,Sheet1!$A3) -> 13000 | F3: =+SUMIFS('List Petty Cash Jul-Des 25'!$AB:$AB,'List Petty Cash Jul-Des 25'!$I:$I,Sheet1!F$1,'List Petty Cash Jul-Des 25'!$V:$V,Sheet1!$A3) -> 24000 | G3: =+SUMIFS('List Petty Cash Jul-Des 25'!$AB:$AB,'List Petty Cash Jul-Des 25'!$I:$I,Sheet1!G$1,'List Petty Cash Jul-Des 25'!$V:$V,Sheet1!$A3) -> 7190000 | H3: =+SUMIFS('List Petty Cash Jul-Des 25'!$AB:$AB,'List Petty Cash Jul-Des 25'!$I:$I,Sheet1!H$1,'List Petty Cash Jul-Des 25'!$V:$V,Sheet1!$A3) -> 6918000 | I3: =+SUM(C3:H3) -> 15060100 | K3: C206D1SLSS | L3: =+SUMIFS('List Petty Cash Jul-Des 25'!$AB:$AB,'List Petty Cash Jul-Des 25'!$I:$I,Sheet1!L$1,'List Petty Cash Jul-Des 25'!$X:$X,Sheet1!$K3) -> 820000 | M3: =+SUMIFS('List Petty Cash Jul-Des 25'!$AB:$AB,'List Petty Cash Jul-Des 25'!$I:$I,Sheet1!M$1,'List Petty Cash Jul-Des 25'!$X:$X,Sheet1!$K3) -> 1870000 | N3: =+SUMIFS('List Petty Cash Jul-Des 25'!$AB:$AB,'List Petty Cash Jul-Des 25'!$I:$I,Sheet1!N$1,'List Petty Cash Jul-Des 25'!$X:$X,Sheet1!$K3) -> 1280000 | O3: =+SUMIFS('List Petty Cash Jul-Des 25'!$AB:$AB,'List Petty Cash Jul-Des 25'!$I:$I,Sheet1!O$1,'List Petty Cash Jul-Des 25'!$X:$X,Sheet1!$K3) -> 2775000 | P3: =+SUMIFS('List Petty Cash Jul-Des 25'!$AB:$AB,'List Petty Cash Jul-Des 25'!$I:$I,Sheet1!P$1,'List Petty Cash Jul-Des 25'!$X:$X,Sheet1!$K3) -> 1778000 | Q3: =+SUMIFS('List Petty Cash Jul-Des 25'!$AB:$AB,'List Petty Cash Jul-Des 25'!$I:$I,Sheet1!Q$1,'List Petty Cash Jul-Des 25'!$X:$X,Sheet1!$K3) -> 1630000 | R3: =+SUM(L3:Q3) -> 10153000 | S3: =+R3/$R$38*100% -> 0.031756506 | T3: 70001110 | AA3: P206D1SLSS | AB3: 33069100 | AE3: 70106400 | AF3: Biaya Bahan Bakar | AG3: 44610000 | AK3: P206D1SLSS | AL3: 33069100
A4: 70009110 | B4: Biaya Survey dan Analisa | C4: =+SUMIFS('List Petty Cash Jul-Des 25'!$AB:$AB,'List Petty Cash Jul-Des 25'!$I:$I,Sheet1!C$1,'List Petty Cash Jul-Des 25'!$V:$V,Sheet1!$A4) -> 7000000 | D4: =+SUMIFS('List Petty Cash Jul-Des 25'!$AB:$AB,'List Petty Cash Jul-Des 25'!$I:$I,Sheet1!D$1,'List Petty Cash Jul-Des 25'!$V:$V,Sheet1!$A4) -> 5600000 | E4: =+SUMIFS('List Petty Cash Jul-Des 25'!$AB:$AB,'List Petty Cash Jul-Des 25'!$I:$I,Sheet1!E$1,'List Petty Cash Jul-Des 25'!$V:$V,Sheet1!$A4) -> 5200000 | F4: =+SUMIFS('List Petty Cash Jul-Des 25'!$AB:$AB,'List Petty Cash Jul-Des 25'!$I:$I,Sheet1!F$1,'List Petty Cash Jul-Des 25'!$V:$V,Sheet1!$A4) -> 9350000 | G4: =+SUMIFS('List Petty Cash Jul-Des 25'!$AB:$AB,'List Petty Cash Jul-Des 25'!$I:$I,Sheet1!G$1,'List Petty Cash Jul-Des 25'!$V:$V,Sheet1!$A4) -> 0 | H4: =+SUMIFS('List Petty Cash Jul-Des 25'!$AB:$AB,'List Petty Cash Jul-Des 25'!$I:$I,Sheet1!H$1,'List Petty Cash Jul-Des 25'!$V:$V,Sheet1!$A4) -> 0 | I4: =+SUM(C4:H4) -> 27150000 | K4: H200D1MMDP | L4: =+SUMIFS('List Petty Cash Jul-Des 25'!$AB:$AB,'List Petty Cash Jul-Des 25'!$I:$I,Sheet1!L$1,'List Petty Cash Jul-Des 25'!$X:$X,Sheet1!$K4) -> 0 | M4: =+SUMIFS('List Petty Cash Jul-Des 25'!$AB:$AB,'List Petty Cash Jul-Des 25'!$I:$I,Sheet1!M$1,'List Petty Cash Jul-Des 25'!$X:$X,Sheet1!$K4) -> 0 | N4: =+SUMIFS('List Petty Cash Jul-Des 25'!$AB:$AB,'List Petty Cash Jul-Des 25'!$I:$I,Sheet1!N$1,'List Petty Cash Jul-Des 25'!$X:$X,Sheet1!$K4) -> 0 | O4: =+SUMIFS('List Petty Cash Jul-Des 25'!$AB:$AB,'List Petty Cash Jul-Des 25'!$I:$I,Sheet1!O$1,'List Petty Cash Jul-Des 25'!$X:$X,Sheet1!$K4) -> 135000 | P4: =+SUMIFS('List Petty Cash Jul-Des 25'!$AB:$AB,'List Petty Cash Jul-Des 25'!$I:$I,Sheet1!P$1,'List Petty Cash Jul-Des 25'!$X:$X,Sheet1!$K4) -> 7478800 | Q4: =+SUMIFS('List Petty Cash Jul-Des 25'!$AB:$AB,'List Petty Cash Jul-Des 25'!$I:$I,Sheet1!Q$1,'List Petty Cash Jul-Des 25'!$X:$X,Sheet1!$K4) -> 1335000 | R4: =+SUM(L4:Q4) -> 8948800 | S4: =+R4/$R$38*100% -> 0.027990015 | T4: 70009110 | AA4: R124D1HRDV | AB4: 22378764 | AE4: 70106100 | AF4: Biaya Transportasi Lokal | AG4: 26336300 | AK4: R124D1HRDV | AL4: 22378764
A5: 70101102 | B5: By Pemeliharaan BgnanPrasarana Material Pihak3 | C5: =+SUMIFS('List Petty Cash Jul-Des 25'!$AB:$AB,'List Petty Cash Jul-Des 25'!$I:$I,Sheet1!C$1,'List Petty Cash Jul-Des 25'!$V:$V,Sheet1!$A5) -> 2744420 | D5: =+SUMIFS('List Petty Cash Jul-Des 25'!$AB:$AB,'List Petty Cash Jul-Des 25'!$I:$I,Sheet1!D$1,'List Petty Cash Jul-Des 25'!$V:$V,Sheet1!$A5) -> 1138300 | E5: =+SUMIFS('List Petty Cash Jul-Des 25'!$AB:$AB,'List Petty Cash Jul-Des 25'!$I:$I,Sheet1!E$1,'List Petty Cash Jul-Des 25'!$V:$V,Sheet1!$A5) -> 0 | F5: =+SUMIFS('List Petty Cash Jul-Des 25'!$AB:$AB,'List Petty Cash Jul-Des 25'!$I:$I,Sheet1!F$1,'List Petty Cash Jul-Des 25'!$V:$V,Sheet1!$A5) -> 2443000 | G5: =+SUMIFS('List Petty Cash Jul-Des 25'!$AB:$AB,'List Petty Cash Jul-Des 25'!$I:$I,Sheet1!G$1,'List Petty Cash Jul-Des 25'!$V:$V,Sheet1!$A5) -> 1956310 | H5: =+SUMIFS('List Petty Cash Jul-Des 25'!$AB:$AB,'List Petty Cash Jul-Des 25'!$I:$I,Sheet1!H$1,'List Petty Cash Jul-Des 25'!$V:$V,Sheet1!$A5) -> 1890250 | I5: =+SUM(C5:H5) -> 10172280 | K5: M204D1COMM | L5: =+SUMIFS('List Petty Cash Jul-Des 25'!$AB:$AB,'List Petty Cash Jul-Des 25'!$I:$I,Sheet1!L$1,'List Petty Cash Jul-Des 25'!$X:$X,Sheet1!$K5) -> 3702000 | M5: =+SUMIFS('List Petty Cash Jul-Des 25'!$AB:$AB,'List Petty Cash Jul-Des 25'!$I:$I,Sheet1!M$1,'List Petty Cash Jul-Des 25'!$X:$X,Sheet1!$K5) -> 4927000 | N5: =+SUMIFS('List Petty Cash Jul-Des 25'!$AB:$AB,'List Petty Cash Jul-Des 25'!$I:$I,Sheet1!N$1,'List Petty Cash Jul-Des 25'!$X:$X,Sheet1!$K5) -> 763000 | O5: =+SUMIFS('List Petty Cash Jul-Des 25'!$AB:$AB,'List Petty Cash Jul-Des 25'!$I:$I,Sheet1!O$1,'List Petty Cash Jul-Des 25'!$X:$X,Sheet1!$K5) -> 3540000 | P5: =+SUMIFS('List Petty Cash Jul-Des 25'!$AB:$AB,'List Petty Cash Jul-Des 25'!$I:$I,Sheet1!P$1,'List Petty Cash Jul-Des 25'!$X:$X,Sheet1!$K5) -> 1120000 | Q5: =+SUMIFS('List Petty Cash Jul-Des 25'!$AB:$AB,'List Petty Cash Jul-Des 25'!$I:$I,Sheet1!Q$1,'List Petty Cash Jul-Des 25'!$X:$X,Sheet1!$K5) -> 1730300 | R5: =+SUM(L5:Q5) -> 15782300 | S5: =+R5/$R$38*100% -> 0.049363804 | T5: 70101102 | AA5: R124QCA | AB5: 19964591 | AE5: 70101114 | AF5: By Perbaikan & Perawatan Perabot Material Pihak3 | AG5: 12884723 | AK5: R124QCA | AL5: 19964591
A6: 70101114 | B6: By Perbaikan & Perawatan Perabot Material Pihak3 | C6: =+SUMIFS('List Petty Cash Jul-Des 25'!$AB:$AB,'List Petty Cash Jul-Des 25'!$I:$I,Sheet1!C$1,'List Petty Cash Jul-Des 25'!$V:$V,Sheet1!$A6) -> 8742306 | D6: =+SUMIFS('List Petty Cash Jul-Des 25'!$AB:$AB,'List Petty Cash Jul-Des 25'!$I:$I,Sheet1!D$1,'List Petty Cash Jul-Des 25'!$V:$V,Sheet1!$A6) -> 4004078 | E6: =+SUMIFS('List Petty Cash Jul-Des 25'!$AB:$AB,'List Petty Cash Jul-Des 25'!$I:$I,Sheet1!E$1,'List Petty Cash Jul-Des 25'!$V:$V,Sheet1!$A6) -> 5781593 | F6: =+SUMIFS('List Petty Cash Jul-Des 25'!$AB:$AB,'List Petty Cash Jul-Des 25'!$I:$I,Sheet1!F$1,'List Petty Cash Jul-Des 25'!$V:$V,Sheet1!$A6) -> 7588405 | G6: =+SUMIFS('List Petty Cash Jul-Des 25'!$AB:$AB,'List Petty Cash Jul-Des 25'!$I:$I,Sheet1!G$1,'List Petty Cash Jul-Des 25'!$V:$V,Sheet1!$A6) -> 2812320 | H6: =+SUMIFS('List Petty Cash Jul-Des 25'!$AB:$AB,'List Petty Cash Jul-Des 25'!$I:$I,Sheet1!H$1,'List Petty Cash Jul-Des 25'!$V:$V,Sheet1!$A6) -> 12627978 | I6: =+SUM(C6:H6) -> 41556680 | K6: P206D1SLSC | L6: =+SUMIFS('List Petty Cash Jul-Des 25'!$AB:$AB,'List Petty Cash Jul-Des 25'!$I:$I,Sheet1!L$1,'List Petty Cash Jul-Des 25'!$X:$X,Sheet1!$K6) -> 350000 | M6: =+SUMIFS('List Petty Cash Jul-Des 25'!$AB:$AB,'List Petty Cash Jul-Des 25'!$I:$I,Sheet1!M$1,'List Petty Cash Jul-Des 25'!$X:$X,Sheet1!$K6) -> 350000 | N6: =+SUMIFS('List Petty Cash Jul-Des 25'!$AB:$AB,'List Petty Cash Jul-Des 25'!$I:$I,Sheet1!N$1,'List Petty Cash Jul-Des 25'!$X:$X,Sheet1!$K6) -> 700000 | O6: =+SUMIFS('List Petty Cash Jul-Des 25'!$AB:$AB,'List Petty Cash Jul-Des 25'!$I:$I,Sheet1!O$1,'List Petty Cash Jul-Des 25'!$X:$X,Sheet1!$K6) -> 400000 | P6: =+SUMIFS('List Petty Cash Jul-Des 25'!$AB:$AB,'List Petty Cash Jul-Des 25'!$I:$I,Sheet1!P$1,'List Petty Cash Jul-Des 25'!$X:$X,Sheet1!$K6) -> 400000 | Q6: =+SUMIFS('List Petty Cash Jul-Des 25'!$AB:$AB,'List Petty Cash Jul-Des 25'!$I:$I,Sheet1!Q$1,'List Petty Cash Jul-Des 25'!$X:$X,Sheet1!$K6) -> 500000 | R6: =+SUM(L6:Q6) -> 2700000 | S6: =+R6/$R$38*100% -> 0.0084450474 | T6: 70101114 | AA6: M204D1COMM | AB6: 15782300 | AE6: 70107100 | AF6: Biaya Mess | AG6: 6993000 | AK6: M204D1COMM | AL6: 15782300
A7: 70101202 | B7: By Pemeliharaan Kend,ABerat,Mesin-Material Pihak3 | C7: =+SUMIFS('List Petty Cash Jul-Des 25'!$AB:$AB,'List Petty Cash Jul-Des 25'!$I:$I,Sheet1!C$1,'List Petty Cash Jul-Des 25'!$V:$V,Sheet1!$A7) -> 6020808 | D7: =+SUMIFS('List Petty Cash Jul-Des 25'!$AB:$AB,'List Petty Cash Jul-Des 25'!$I:$I,Sheet1!D$1,'List Petty Cash Jul-Des 25'!$V:$V,Sheet1!$A7) -> 2452500 | E7: =+SUMIFS('List Petty Cash Jul-Des 25'!$AB:$AB,'List Petty Cash Jul-Des 25'!$I:$I,Sheet1!E$1,'List Petty Cash Jul-Des 25'!$V:$V,Sheet1!$A7) -> 4139620 | F7: =+SUMIFS('List Petty Cash Jul-Des 25'!$AB:$AB,'List Petty Cash Jul-Des 25'!$I:$I,Sheet1!F$1,'List Petty Cash Jul-Des 25'!$V:$V,Sheet1!$A7) -> 12044280 | G7: =+SUMIFS('List Petty Cash Jul-Des 25'!$AB:$AB,'List Petty Cash Jul-Des 25'!$I:$I,Sheet1!G$1,'List Petty Cash Jul-Des 25'!$V:$V,Sheet1!$A7) -> 2950976 | H7: =+SUMIFS('List Petty Cash Jul-Des 25'!$AB:$AB,'List Petty Cash Jul-Des 25'!$I:$I,Sheet1!H$1,'List Petty Cash Jul-Des 25'!$V:$V,Sheet1!$A7) -> 7628680 | I7: =+SUM(C7:H7) -> 35236864 | K7: P206D1SLSS | L7: =+SUMIFS('List Petty Cash Jul-Des 25'!$AB:$AB,'List Petty Cash Jul-Des 25'!$I:$I,Sheet1!L$1,'List Petty Cash Jul-Des 25'!$X:$X,Sheet1!$K7) -> 6844000 | M7: =+SUMIFS('List Petty Cash Jul-Des 25'!$AB:$AB,'List Petty Cash Jul-Des 25'!$I:$I,Sheet1!M$1,'List Petty Cash Jul-Des 25'!$X:$X,Sheet1!$K7) -> 4844100 | N7: =+SUMIFS('List Petty Cash Jul-Des 25'!$AB:$AB,'List Petty Cash Jul-Des 25'!$I:$I,Sheet1!N$1,'List Petty Cash Jul-Des 25'!$X:$X,Sheet1!$K7) -> 3643000 | O7: =+SUMIFS('List Petty Cash Jul-Des 25'!$AB:$AB,'List Petty Cash Jul-Des 25'!$I:$I,Sheet1!O$1,'List Petty Cash Jul-Des 25'!$X:$X,Sheet1!$K7) -> 5837000 | P7: =+SUMIFS('List Petty Cash Jul-Des 25'!$AB:$AB,'List Petty Cash Jul-Des 25'!$I:$I,Sheet1!P$1,'List Petty Cash Jul-Des 25'!$X:$X,Sheet1!$K7) -> 6200000 | Q7: =+SUMIFS('List Petty Cash Jul-Des 25'!$AB:$AB,'List Petty Cash Jul-Des 25'!$I:$I,Sheet1!Q$1,'List Petty Cash Jul-Des 25'!$X:$X,Sheet1!$K7) -> 5701000 | R7: =+SUM(L7:Q7) -> 33069100 | S7: =+R7/$R$38*100% -> 0.10343338 | T7: 70101202 | AA7: - | AB7: 11739930 | AE7: 70101102 | AF7: By Pemeliharaan BgnanPrasarana Material Pihak3 | AG7: 6693470
A8: 70101230 | B8: Pemakaian Sparepart Kend & A.Berat | C8: =+SUMIFS('List Petty Cash Jul-Des 25'!$AB:$AB,'List Petty Cash Jul-Des 25'!$I:$I,Sheet1!C$1,'List Petty Cash Jul-Des 25'!$V:$V,Sheet1!$A8) -> 1800000 | D8: =+SUMIFS('List Petty Cash Jul-Des 25'!$AB:$AB,'List Petty Cash Jul-Des 25'!$I:$I,Sheet1!D$1,'List Petty Cash Jul-Des 25'!$V:$V,Sheet1!$A8) -> 0 | E8: =+SUMIFS('List Petty Cash Jul-Des 25'!$AB:$AB,'List Petty Cash Jul-Des 25'!$I:$I,Sheet1!E$1,'List Petty Cash Jul-Des 25'!$V:$V,Sheet1!$A8) -> 0 | F8: =+SUMIFS('List Petty Cash Jul-Des 25'!$AB:$AB,'List Petty Cash Jul-Des 25'!$I:$I,Sheet1!F$1,'List Petty Cash Jul-Des 25'!$V:$V,Sheet1!$A8) -> 0 | G8: =+SUMIFS('List Petty Cash Jul-Des 25'!$AB:$AB,'List Petty Cash Jul-Des 25'!$I:$I,Sheet1!G$1,'List Petty Cash Jul-Des 25'!$V:$V,Sheet1!$A8) -> 0 | H8: =+SUMIFS('List Petty Cash Jul-Des 25'!$AB:$AB,'List Petty Cash Jul-Des 25'!$I:$I,Sheet1!H$1,'List Petty Cash Jul-Des 25'!$V:$V,Sheet1!$A8) -> 0 | I8: =+SUM(C8:H8) -> 1800000 | K8: R124BLR | L8: =+SUMIFS('List Petty Cash Jul-Des 25'!$AB:$AB,'List Petty Cash Jul-Des 25'!$I:$I,Sheet1!L$1,'List Petty Cash Jul-Des 25'!$X:$X,Sheet1!$K8) -> 0 | M8: =+SUMIFS('List Petty Cash Jul-Des 25'!$AB:$AB,'List Petty Cash Jul-Des 25'!$I:$I,Sheet1!M$1,'List Petty Cash Jul-Des 25'!$X:$X,Sheet1!$K8) -> 0 | N8: =+SUMIFS('List Petty Cash Jul-Des 25'!$AB:$AB,'List Petty Cash Jul-Des 25'!$I:$I,Sheet1!N$1,'List Petty Cash Jul-Des 25'!$X:$X,Sheet1!$K8) -> 0 | O8: =+SUMIFS('List Petty Cash Jul-Des 25'!$AB:$AB,'List Petty Cash Jul-Des 25'!$I:$I,Sheet1!O$1,'List Petty Cash Jul-Des 25'!$X:$X,Sheet1!$K8) -> 2325000 | P8: =+SUMIFS('List Petty Cash Jul-Des 25'!$AB:$AB,'List Petty Cash Jul-Des 25'!$I:$I,Sheet1!P$1,'List Petty Cash Jul-Des 25'!$X:$X,Sheet1!$K8) -> 2821000 | Q8: =+SUMIFS('List Petty Cash Jul-Des 25'!$AB:$AB,'List Petty Cash Jul-Des 25'!$I:$I,Sheet1!Q$1,'List Petty Cash Jul-Des 25'!$X:$X,Sheet1!$K8) -> 0 | R8: =+SUM(L8:Q8) -> 5146000 | S8: =+R8/$R$38*100% -> 0.016095635 | T8: 70101230 | AA8: C206D1SLSS | AB8: 10153000 | AE8: 70108100 | AF8: Biaya Peralatan Dan Perabot Kantor | AG8: 4247200
A9: 70102300 | B9: Biaya Poliklinik | C9: =+SUMIFS('List Petty Cash Jul-Des 25'!$AB:$AB,'List Petty Cash Jul-Des 25'!$I:$I,Sheet1!C$1,'List Petty Cash Jul-Des 25'!$V:$V,Sheet1!$A9) -> 1116900 | D9: =+SUMIFS('List Petty Cash Jul-Des 25'!$AB:$AB,'List Petty Cash Jul-Des 25'!$I:$I,Sheet1!D$1,'List Petty Cash Jul-Des 25'!$V:$V,Sheet1!$A9) -> 0 | E9: =+SUMIFS('List Petty Cash Jul-Des 25'!$AB:$AB,'List Petty Cash Jul-Des 25'!$I:$I,Sheet1!E$1,'List Petty Cash Jul-Des 25'!$V:$V,Sheet1!$A9) -> 0 | F9: =+SUMIFS('List Petty Cash Jul-Des 25'!$AB:$AB,'List Petty Cash Jul-Des 25'!$I:$I,Sheet1!F$1,'List Petty Cash Jul-Des 25'!$V:$V,Sheet1!$A9) -> 0 | G9: =+SUMIFS('List Petty Cash Jul-Des 25'!$AB:$AB,'List Petty Cash Jul-Des 25'!$I:$I,Sheet1!G$1,'List Petty Cash Jul-Des 25'!$V:$V,Sheet1!$A9) -> 0 | H9: =+SUMIFS('List Petty Cash Jul-Des 25'!$AB:$AB,'List Petty Cash Jul-Des 25'!$I:$I,Sheet1!H$1,'List Petty Cash Jul-Des 25'!$V:$V,Sheet1!$A9) -> 0 | I9: =+SUM(C9:H9) -> 1116900 | K9: R124D1EHFS | L9: =+SUMIFS('List Petty Cash Jul-Des 25'!$AB:$AB,'List Petty Cash Jul-Des 25'!$I:$I,Sheet1!L$1,'List Petty Cash Jul-Des 25'!$X:$X,Sheet1!$K9) -> 1273180 | M9: =+SUMIFS('List Petty Cash Jul-Des 25'!$AB:$AB,'List Petty Cash Jul-Des 25'!$I:$I,Sheet1!M$1,'List Petty Cash Jul-Des 25'!$X:$X,Sheet1!$K9) -> 1113500 | N9: =+SUMIFS('List Petty Cash Jul-Des 25'!$AB:$AB,'List Petty Cash Jul-Des 25'!$I:$I,Sheet1!N$1,'List Petty Cash Jul-Des 25'!$X:$X,Sheet1!$K9) -> 100000 | O9: =+SUMIFS('List Petty Cash Jul-Des 25'!$AB:$AB,'List Petty Cash Jul-Des 25'!$I:$I,Sheet1!O$1,'List Petty Cash Jul-Des 25'!$X:$X,Sheet1!$K9) -> 999700 | P9: =+SUMIFS('List Petty Cash Jul-Des 25'!$AB:$AB,'List Petty Cash Jul-Des 25'!$I:$I,Sheet1!P$1,'List Petty Cash Jul-Des 25'!$X:$X,Sheet1!$K9) -> 876800 | Q9: =+SUMIFS('List Petty Cash Jul-Des 25'!$AB:$AB,'List Petty Cash Jul-Des 25'!$I:$I,Sheet1!Q$1,'List Petty Cash Jul-Des 25'!$X:$X,Sheet1!$K9) -> 996262 | R9: =+SUM(L9:Q9) -> 5359442 | S9: =+R9/$R$38*100% -> 0.016763238 | T9: 70102300 | AA9: H200D1MMDP | AB9: 8948800 | AE9: 70107600 | AF9: Biaya Konsumsi Kantor | AG9: 4172490
A10: 70105210 | B10: Biaya Pajak Kendaraan Bermotor & Alat Berat | C10: =+SUMIFS('List Petty Cash Jul-Des 25'!$AB:$AB,'List Petty Cash Jul-Des 25'!$I:$I,Sheet1!C$1,'List Petty Cash Jul-Des 25'!$V:$V,Sheet1!$A10) -> 0 | D10: =+SUMIFS('List Petty Cash Jul-Des 25'!$AB:$AB,'List Petty Cash Jul-Des 25'!$I:$I,Sheet1!D$1,'List Petty Cash Jul-Des 25'!$V:$V,Sheet1!$A10) -> 0 | E10: =+SUMIFS('List Petty Cash Jul-Des 25'!$AB:$AB,'List Petty Cash Jul-Des 25'!$I:$I,Sheet1!E$1,'List Petty Cash Jul-Des 25'!$V:$V,Sheet1!$A10) -> 0 | F10: =+SUMIFS('List Petty Cash Jul-Des 25'!$AB:$AB,'List Petty Cash Jul-Des 25'!$I:$I,Sheet1!F$1,'List Petty Cash Jul-Des 25'!$V:$V,Sheet1!$A10) -> 0 | G10: =+SUMIFS('List Petty Cash Jul-Des 25'!$AB:$AB,'List Petty Cash Jul-Des 25'!$I:$I,Sheet1!G$1,'List Petty Cash Jul-Des 25'!$V:$V,Sheet1!$A10) -> 420500 | H10: =+SUMIFS('List Petty Cash Jul-Des 25'!$AB:$AB,'List Petty Cash Jul-Des 25'!$I:$I,Sheet1!H$1,'List Petty Cash Jul-Des 25'!$V:$V,Sheet1!$A10) -> 515500 | I10: =+SUM(C10:H10) -> 936000 | K10: R124D1FRCO | L10: =+SUMIFS('List Petty Cash Jul-Des 25'!$AB:$AB,'List Petty Cash Jul-Des 25'!$I:$I,Sheet1!L$1,'List Petty Cash Jul-Des 25'!$X:$X,Sheet1!$K10) -> 383350 | M10: =+SUMIFS('List Petty Cash Jul-Des 25'!$AB:$AB,'List Petty Cash Jul-Des 25'!$I:$I,Sheet1!M$1,'List Petty Cash Jul-Des 25'!$X:$X,Sheet1!$K10) -> 344000 | N10: =+SUMIFS('List Petty Cash Jul-Des 25'!$AB:$AB,'List Petty Cash Jul-Des 25'!$I:$I,Sheet1!N$1,'List Petty Cash Jul-Des 25'!$X:$X,Sheet1!$K10) -> 0 | O10: =+SUMIFS('List Petty Cash Jul-Des 25'!$AB:$AB,'List Petty Cash Jul-Des 25'!$I:$I,Sheet1!O$1,'List Petty Cash Jul-Des 25'!$X:$X,Sheet1!$K10) -> 511000 | P10: =+SUMIFS('List Petty Cash Jul-Des 25'!$AB:$AB,'List Petty Cash Jul-Des 25'!$I:$I,Sheet1!P$1,'List Petty Cash Jul-Des 25'!$X:$X,Sheet1!$K10) -> 543200 | Q10: =+SUMIFS('List Petty Cash Jul-Des 25'!$AB:$AB,'List Petty Cash Jul-Des 25'!$I:$I,Sheet1!Q$1,'List Petty Cash Jul-Des 25'!$X:$X,Sheet1!$K10) -> 865000 | R10: =+SUM(L10:Q10) -> 2646550 | S10: =+R10/$R$38*100% -> 0.0082778668 | T10: 70105210 | AA10: R124REF | AB10: 7294000 | AE10: 70105210 | AF10: Biaya Pajak Kendaraan Bermotor & Alat Berat | AG10: 936000
A11: 70105300 | B11: Biaya Perizinan Pemerintah | C11: =+SUMIFS('List Petty Cash Jul-Des 25'!$AB:$AB,'List Petty Cash Jul-Des 25'!$I:$I,Sheet1!C$1,'List Petty Cash Jul-Des 25'!$V:$V,Sheet1!$A11) -> 57800 | D11: =+SUMIFS('List Petty Cash Jul-Des 25'!$AB:$AB,'List Petty Cash Jul-Des 25'!$I:$I,Sheet1!D$1,'List Petty Cash Jul-Des 25'!$V:$V,Sheet1!$A11) -> 57800 | E11: =+SUMIFS('List Petty Cash Jul-Des 25'!$AB:$AB,'List Petty Cash Jul-Des 25'!$I:$I,Sheet1!E$1,'List Petty Cash Jul-Des 25'!$V:$V,Sheet1!$A11) -> 29900 | F11: =+SUMIFS('List Petty Cash Jul-Des 25'!$AB:$AB,'List Petty Cash Jul-Des 25'!$I:$I,Sheet1!F$1,'List Petty Cash Jul-Des 25'!$V:$V,Sheet1!$A11) -> 57800 | G11: =+SUMIFS('List Petty Cash Jul-Des 25'!$AB:$AB,'List Petty Cash Jul-Des 25'!$I:$I,Sheet1!G$1,'List Petty Cash Jul-Des 25'!$V:$V,Sheet1!$A11) -> 210500 | H11: =+SUMIFS('List Petty Cash Jul-Des 25'!$AB:$AB,'List Petty Cash Jul-Des 25'!$I:$I,Sheet1!H$1,'List Petty Cash Jul-Des 25'!$V:$V,Sheet1!$A11) -> 57800 | I11: =+SUM(C11:H11) -> 471600 | K11: R124D1HRDV | L11: =+SUMIFS('List Petty Cash Jul-Des 25'!$AB:$AB,'List Petty Cash Jul-Des 25'!$I:$I,Sheet1!L$1,'List Petty Cash Jul-Des 25'!$X:$X,Sheet1!$K11) -> 4618599 | M11: =+SUMIFS('List Petty Cash Jul-Des 25'!$AB:$AB,'List Petty Cash Jul-Des 25'!$I:$I,Sheet1!M$1,'List Petty Cash Jul-Des 25'!$X:$X,Sheet1!$K11) -> 1095000 | N11: =+SUMIFS('List Petty Cash Jul-Des 25'!$AB:$AB,'List Petty Cash Jul-Des 25'!$I:$I,Sheet1!N$1,'List Petty Cash Jul-Des 25'!$X:$X,Sheet1!$K11) -> 2100000 | O11: =+SUMIFS('List Petty Cash Jul-Des 25'!$AB:$AB,'List Petty Cash Jul-Des 25'!$I:$I,Sheet1!O$1,'List Petty Cash Jul-Des 25'!$X:$X,Sheet1!$K11) -> 3472235 | P11: =+SUMIFS('List Petty Cash Jul-Des 25'!$AB:$AB,'List Petty Cash Jul-Des 25'!$I:$I,Sheet1!P$1,'List Petty Cash Jul-Des 25'!$X:$X,Sheet1!$K11) -> 4637500 | Q11: =+SUMIFS('List Petty Cash Jul-Des 25'!$AB:$AB,'List Petty Cash Jul-Des 25'!$I:$I,Sheet1!Q$1,'List Petty Cash Jul-Des 25'!$X:$X,Sheet1!$K11) -> 6455430 | R11: =+SUM(L11:Q11) -> 22378764 | S11: =+R11/$R$38*100% -> 0.069996194 | T11: 70105300 | AA11: R124MIN | AB11: 6649980 | AE11: 70105300 | AF11: Biaya Perizinan Pemerintah | AG11: 471600
A12: 70105321 | B12: By Sertifikasi Non Quality Food Safety (Non QFS) | C12: =+SUMIFS('List Petty Cash Jul-Des 25'!$AB:$AB,'List Petty Cash Jul-Des 25'!$I:$I,Sheet1!C$1,'List Petty Cash Jul-Des 25'!$V:$V,Sheet1!$A12) -> 0 | D12: =+SUMIFS('List Petty Cash Jul-Des 25'!$AB:$AB,'List Petty Cash Jul-Des 25'!$I:$I,Sheet1!D$1,'List Petty Cash Jul-Des 25'!$V:$V,Sheet1!$A12) -> 0 | E12: =+SUMIFS('List Petty Cash Jul-Des 25'!$AB:$AB,'List Petty Cash Jul-Des 25'!$I:$I,Sheet1!E$1,'List Petty Cash Jul-Des 25'!$V:$V,Sheet1!$A12) -> 0 | F12: =+SUMIFS('List Petty Cash Jul-Des 25'!$AB:$AB,'List Petty Cash Jul-Des 25'!$I:$I,Sheet1!F$1,'List Petty Cash Jul-Des 25'!$V:$V,Sheet1!$A12) -> 916000 | G12: =+SUMIFS('List Petty Cash Jul-Des 25'!$AB:$AB,'List Petty Cash Jul-Des 25'!$I:$I,Sheet1!G$1,'List Petty Cash Jul-Des 25'!$V:$V,Sheet1!$A12) -> 0 | H12: =+SUMIFS('List Petty Cash Jul-Des 25'!$AB:$AB,'List Petty Cash Jul-Des 25'!$I:$I,Sheet1!H$1,'List Petty Cash Jul-Des 25'!$V:$V,Sheet1!$A12) -> 0 | I12: =+SUM(C12:H12) -> 916000 | K12: R124D1HRGA | L12: =+SUMIFS('List Petty Cash Jul-Des 25'!$AB:$AB,'List Petty Cash Jul-Des 25'!$I:$I,Sheet1!L$1,'List Petty Cash Jul-Des 25'!$X:$X,Sheet1!$K12) -> 18188358 | M12: =+SUMIFS('List Petty Cash Jul-Des 25'!$AB:$AB,'List Petty Cash Jul-Des 25'!$I:$I,Sheet1!M$1,'List Petty Cash Jul-Des 25'!$X:$X,Sheet1!$K12) -> 14559402 | N12: =+SUMIFS('List Petty Cash Jul-Des 25'!$AB:$AB,'List Petty Cash Jul-Des 25'!$I:$I,Sheet1!N$1,'List Petty Cash Jul-Des 25'!$X:$X,Sheet1!$K12) -> 10663587 | O12: =+SUMIFS('List Petty Cash Jul-Des 25'!$AB:$AB,'List Petty Cash Jul-Des 25'!$I:$I,Sheet1!O$1,'List Petty Cash Jul-Des 25'!$X:$X,Sheet1!$K12) -> 20320035 | P12: =+SUMIFS('List Petty Cash Jul-Des 25'!$AB:$AB,'List Petty Cash Jul-Des 25'!$I:$I,Sheet1!P$1,'List Petty Cash Jul-Des 25'!$X:$X,Sheet1!$K12) -> 25204360 | Q12: =+SUMIFS('List Petty Cash Jul-Des 25'!$AB:$AB,'List Petty Cash Jul-Des 25'!$I:$I,Sheet1!Q$1,'List Petty Cash Jul-Des 25'!$X:$X,Sheet1!$K12) -> 18684041 | R12: =+SUM(L12:Q12) -> 107619783 | S12: =+R12/$R$38*100% -> 0.33661266 | T12: 70105321 | AA12: R124REF3 | AB12: 6084036 | AE12: 70101202 | AF12: By Pemeliharaan Kend,ABerat,Mesin-Material Pihak3 | AG12: 275000 | AK12: Cost Center | AL12: Total
A13: 70106100 | B13: Biaya Transportasi Lokal | C13: =+SUMIFS('List Petty Cash Jul-Des 25'!$AB:$AB,'List Petty Cash Jul-Des 25'!$I:$I,Sheet1!C$1,'List Petty Cash Jul-Des 25'!$V:$V,Sheet1!$A13) -> 4714300 | D13: =+SUMIFS('List Petty Cash Jul-Des 25'!$AB:$AB,'List Petty Cash Jul-Des 25'!$I:$I,Sheet1!D$1,'List Petty Cash Jul-Des 25'!$V:$V,Sheet1!$A13) -> 3220000 | E13: =+SUMIFS('List Petty Cash Jul-Des 25'!$AB:$AB,'List Petty Cash Jul-Des 25'!$I:$I,Sheet1!E$1,'List Petty Cash Jul-Des 25'!$V:$V,Sheet1!$A13) -> 3209000 | F13: =+SUMIFS('List Petty Cash Jul-Des 25'!$AB:$AB,'List Petty Cash Jul-Des 25'!$I:$I,Sheet1!F$1,'List Petty Cash Jul-Des 25'!$V:$V,Sheet1!$A13) -> 5769000 | G13: =+SUMIFS('List Petty Cash Jul-Des 25'!$AB:$AB,'List Petty Cash Jul-Des 25'!$I:$I,Sheet1!G$1,'List Petty Cash Jul-Des 25'!$V:$V,Sheet1!$A13) -> 9921500 | H13: =+SUMIFS('List Petty Cash Jul-Des 25'!$AB:$AB,'List Petty Cash Jul-Des 25'!$I:$I,Sheet1!H$1,'List Petty Cash Jul-Des 25'!$V:$V,Sheet1!$A13) -> 5718500 | I13: =+SUM(C13:H13) -> 32552300 | K13: R124D1MGMT | L13: =+SUMIFS('List Petty Cash Jul-Des 25'!$AB:$AB,'List Petty Cash Jul-Des 25'!$I:$I,Sheet1!L$1,'List Petty Cash Jul-Des 25'!$X:$X,Sheet1!$K13) -> 1389800 | M13: =+SUMIFS('List Petty Cash Jul-Des 25'!$AB:$AB,'List Petty Cash Jul-Des 25'!$I:$I,Sheet1!M$1,'List Petty Cash Jul-Des 25'!$X:$X,Sheet1!$K13) -> 0 | N13: =+SUMIFS('List Petty Cash Jul-Des 25'!$AB:$AB,'List Petty Cash Jul-Des 25'!$I:$I,Sheet1!N$1,'List Petty Cash Jul-Des 25'!$X:$X,Sheet1!$K13) -> 618300 | O13: =+SUMIFS('List Petty Cash Jul-Des 25'!$AB:$AB,'List Petty Cash Jul-Des 25'!$I:$I,Sheet1!O$1,'List Petty Cash Jul-Des 25'!$X:$X,Sheet1!$K13) -> 870000 | P13: =+SUMIFS('List Petty Cash Jul-Des 25'!$AB:$AB,'List Petty Cash Jul-Des 25'!$I:$I,Sheet1!P$1,'List Petty Cash Jul-Des 25'!$X:$X,Sheet1!$K13) -> 500000 | Q13: =+SUMIFS('List Petty Cash Jul-Des 25'!$AB:$AB,'List Petty Cash Jul-Des 25'!$I:$I,Sheet1!Q$1,'List Petty Cash Jul-Des 25'!$X:$X,Sheet1!$K13) -> 400000 | R13: =+SUM(L13:Q13) -> 3778100 | S13: =+R13/$R$38*100% -> 0.011817124 | T13: 70106100 | AA13: R124NSS | AB13: 5690177 | AG13: =SUM(AG3:AG12) -> 107619783 | AK13: R124D1HRGA | AL13: 107619783
A14: 70106400 | B14: Biaya Bahan Bakar | C14: =+SUMIFS('List Petty Cash Jul-Des 25'!$AB:$AB,'List Petty Cash Jul-Des 25'!$I:$I,Sheet1!C$1,'List Petty Cash Jul-Des 25'!$V:$V,Sheet1!$A14) -> 6890000 | D14: =+SUMIFS('List Petty Cash Jul-Des 25'!$AB:$AB,'List Petty Cash Jul-Des 25'!$I:$I,Sheet1!D$1,'List Petty Cash Jul-Des 25'!$V:$V,Sheet1!$A14) -> 5150000 | E14: =+SUMIFS('List Petty Cash Jul-Des 25'!$AB:$AB,'List Petty Cash Jul-Des 25'!$I:$I,Sheet1!E$1,'List Petty Cash Jul-Des 25'!$V:$V,Sheet1!$A14) -> 4330000 | F14: =+SUMIFS('List Petty Cash Jul-Des 25'!$AB:$AB,'List Petty Cash Jul-Des 25'!$I:$I,Sheet1!F$1,'List Petty Cash Jul-Des 25'!$V:$V,Sheet1!$A14) -> 7780000 | G14: =+SUMIFS('List Petty Cash Jul-Des 25'!$AB:$AB,'List Petty Cash Jul-Des 25'!$I:$I,Sheet1!G$1,'List Petty Cash Jul-Des 25'!$V:$V,Sheet1!$A14) -> 11610000 | H14: =+SUMIFS('List Petty Cash Jul-Des 25'!$AB:$AB,'List Petty Cash Jul-Des 25'!$I:$I,Sheet1!H$1,'List Petty Cash Jul-Des 25'!$V:$V,Sheet1!$A14) -> 8850000 | I14: =+SUM(C14:H14) -> 44610000 | K14: R124D1PRCN | L14: =+SUMIFS('List Petty Cash Jul-Des 25'!$AB:$AB,'List Petty Cash Jul-Des 25'!$I:$I,Sheet1!L$1,'List Petty Cash Jul-Des 25'!$X:$X,Sheet1!$K14) -> 1000000 | M14: =+SUMIFS('List Petty Cash Jul-Des 25'!$AB:$AB,'List Petty Cash Jul-Des 25'!$I:$I,Sheet1!M$1,'List Petty Cash Jul-Des 25'!$X:$X,Sheet1!$K14) -> 600000 | N14: =+SUMIFS('List Petty Cash Jul-Des 25'!$AB:$AB,'List Petty Cash Jul-Des 25'!$I:$I,Sheet1!N$1,'List Petty Cash Jul-Des 25'!$X:$X,Sheet1!$K14) -> 0 | O14: =+SUMIFS('List Petty Cash Jul-Des 25'!$AB:$AB,'List Petty Cash Jul-Des 25'!$I:$I,Sheet1!O$1,'List Petty Cash Jul-Des 25'!$X:$X,Sheet1!$K14) -> 0 | P14: =+SUMIFS('List Petty Cash Jul-Des 25'!$AB:$AB,'List Petty Cash Jul-Des 25'!$I:$I,Sheet1!P$1,'List Petty Cash Jul-Des 25'!$X:$X,Sheet1!$K14) -> 0 | Q14: =+SUMIFS('List Petty Cash Jul-Des 25'!$AB:$AB,'List Petty Cash Jul-Des 25'!$I:$I,Sheet1!Q$1,'List Petty Cash Jul-Des 25'!$X:$X,Sheet1!$K14) -> 1000000 | R14: =+SUM(L14:Q14) -> 2600000 | S14: =+R14/$R$38*100% -> 0.0081322679 | T14: 70106400 | AA14: R124D1EHFS | AB14: 5359442 | AK14: P206D1SLSS | AL14: 33069100
A15: 70107100 | B15: Biaya Mess | C15: =+SUMIFS('List Petty Cash Jul-Des 25'!$AB:$AB,'List Petty Cash Jul-Des 25'!$I:$I,Sheet1!C$1,'List Petty Cash Jul-Des 25'!$V:$V,Sheet1!$A15) -> 290500 | D15: =+SUMIFS('List Petty Cash Jul-Des 25'!$AB:$AB,'List Petty Cash Jul-Des 25'!$I:$I,Sheet1!D$1,'List Petty Cash Jul-Des 25'!$V:$V,Sheet1!$A15) -> 1890500 | E15: =+SUMIFS('List Petty Cash Jul-Des 25'!$AB:$AB,'List Petty Cash Jul-Des 25'!$I:$I,Sheet1!E$1,'List Petty Cash Jul-Des 25'!$V:$V,Sheet1!$A15) -> 290500 | F15: =+SUMIFS('List Petty Cash Jul-Des 25'!$AB:$AB,'List Petty Cash Jul-Des 25'!$I:$I,Sheet1!F$1,'List Petty Cash Jul-Des 25'!$V:$V,Sheet1!$A15) -> 1890500 | G15: =+SUMIFS('List Petty Cash Jul-Des 25'!$AB:$AB,'List Petty Cash Jul-Des 25'!$I:$I,Sheet1!G$1,'List Petty Cash Jul-Des 25'!$V:$V,Sheet1!$A15) -> 1540500 | H15: =+SUMIFS('List Petty Cash Jul-Des 25'!$AB:$AB,'List Petty Cash Jul-Des 25'!$I:$I,Sheet1!H$1,'List Petty Cash Jul-Des 25'!$V:$V,Sheet1!$A15) -> 1090500 | I15: =+SUM(C15:H15) -> 6993000 | K15: R124D1TPDU | L15: =+SUMIFS('List Petty Cash Jul-Des 25'!$AB:$AB,'List Petty Cash Jul-Des 25'!$I:$I,Sheet1!L$1,'List Petty Cash Jul-Des 25'!$X:$X,Sheet1!$K15) -> 0 | M15: =+SUMIFS('List Petty Cash Jul-Des 25'!$AB:$AB,'List Petty Cash Jul-Des 25'!$I:$I,Sheet1!M$1,'List Petty Cash Jul-Des 25'!$X:$X,Sheet1!$K15) -> 0 | N15: =+SUMIFS('List Petty Cash Jul-Des 25'!$AB:$AB,'List Petty Cash Jul-Des 25'!$I:$I,Sheet1!N$1,'List Petty Cash Jul-Des 25'!$X:$X,Sheet1!$K15) -> 0 | O15: =+SUMIFS('List Petty Cash Jul-Des 25'!$AB:$AB,'List Petty Cash Jul-Des 25'!$I:$I,Sheet1!O$1,'List Petty Cash Jul-Des 25'!$X:$X,Sheet1!$K15) -> 0 | P15: =+SUMIFS('List Petty Cash Jul-Des 25'!$AB:$AB,'List Petty Cash Jul-Des 25'!$I:$I,Sheet1!P$1,'List Petty Cash Jul-Des 25'!$X:$X,Sheet1!$K15) -> 385000 | Q15: =+SUMIFS('List Petty Cash Jul-Des 25'!$AB:$AB,'List Petty Cash Jul-Des 25'!$I:$I,Sheet1!Q$1,'List Petty Cash Jul-Des 25'!$X:$X,Sheet1!$K15) -> 0 | R15: =+SUM(L15:Q15) -> 385000 | S15: =+R15/$R$38*100% -> 0.0012042012 | T15: 70107100 | AA15: R124BLR | AB15: 5146000 | AK15: R124D1HRDV | AL15: 22378764
A16: 70107300 | B16: Biaya Olahraga Dan Permainan | C16: =+SUMIFS('List Petty Cash Jul-Des 25'!$AB:$AB,'List Petty Cash Jul-Des 25'!$I:$I,Sheet1!C$1,'List Petty Cash Jul-Des 25'!$V:$V,Sheet1!$A16) -> 2786599 | D16: =+SUMIFS('List Petty Cash Jul-Des 25'!$AB:$AB,'List Petty Cash Jul-Des 25'!$I:$I,Sheet1!D$1,'List Petty Cash Jul-Des 25'!$V:$V,Sheet1!$A16) -> 1000000 | E16: =+SUMIFS('List Petty Cash Jul-Des 25'!$AB:$AB,'List Petty Cash Jul-Des 25'!$I:$I,Sheet1!E$1,'List Petty Cash Jul-Des 25'!$V:$V,Sheet1!$A16) -> 1400000 | F16: =+SUMIFS('List Petty Cash Jul-Des 25'!$AB:$AB,'List Petty Cash Jul-Des 25'!$I:$I,Sheet1!F$1,'List Petty Cash Jul-Des 25'!$V:$V,Sheet1!$A16) -> 2330000 | G16: =+SUMIFS('List Petty Cash Jul-Des 25'!$AB:$AB,'List Petty Cash Jul-Des 25'!$I:$I,Sheet1!G$1,'List Petty Cash Jul-Des 25'!$V:$V,Sheet1!$A16) -> 2100000 | H16: =+SUMIFS('List Petty Cash Jul-Des 25'!$AB:$AB,'List Petty Cash Jul-Des 25'!$I:$I,Sheet1!H$1,'List Petty Cash Jul-Des 25'!$V:$V,Sheet1!$A16) -> 2239480 | I16: =+SUM(C16:H16) -> 11856079 | K16: R124FAM | L16: =+SUMIFS('List Petty Cash Jul-Des 25'!$AB:$AB,'List Petty Cash Jul-Des 25'!$I:$I,Sheet1!L$1,'List Petty Cash Jul-Des 25'!$X:$X,Sheet1!$K16) -> 0 | M16: =+SUMIFS('List Petty Cash Jul-Des 25'!$AB:$AB,'List Petty Cash Jul-Des 25'!$I:$I,Sheet1!M$1,'List Petty Cash Jul-Des 25'!$X:$X,Sheet1!$K16) -> 0 | N16: =+SUMIFS('List Petty Cash Jul-Des 25'!$AB:$AB,'List Petty Cash Jul-Des 25'!$I:$I,Sheet1!N$1,'List Petty Cash Jul-Des 25'!$X:$X,Sheet1!$K16) -> 0 | O16: =+SUMIFS('List Petty Cash Jul-Des 25'!$AB:$AB,'List Petty Cash Jul-Des 25'!$I:$I,Sheet1!O$1,'List Petty Cash Jul-Des 25'!$X:$X,Sheet1!$K16) -> 0 | P16: =+SUMIFS('List Petty Cash Jul-Des 25'!$AB:$AB,'List Petty Cash Jul-Des 25'!$I:$I,Sheet1!P$1,'List Petty Cash Jul-Des 25'!$X:$X,Sheet1!$K16) -> 0 | Q16: =+SUMIFS('List Petty Cash Jul-Des 25'!$AB:$AB,'List Petty Cash Jul-Des 25'!$I:$I,Sheet1!Q$1,'List Petty Cash Jul-Des 25'!$X:$X,Sheet1!$K16) -> 2047748 | R16: =+SUM(L16:Q16) -> 2047748 | S16: =+R16/$R$38*100% -> 0.0064049367 | T16: 70107300 | AA16: R124TCP | AB16: 4769040 | AK16: R124QCA | AL16: 19964591
A17: 70107500 | B17: Biaya Sumbangan Sosial | C17: =+SUMIFS('List Petty Cash Jul-Des 25'!$AB:$AB,'List Petty Cash Jul-Des 25'!$I:$I,Sheet1!C$1,'List Petty Cash Jul-Des 25'!$V:$V,Sheet1!$A17) -> 0 | D17: =+SUMIFS('List Petty Cash Jul-Des 25'!$AB:$AB,'List Petty Cash Jul-Des 25'!$I:$I,Sheet1!D$1,'List Petty Cash Jul-Des 25'!$V:$V,Sheet1!$A17) -> 600000 | E17: =+SUMIFS('List Petty Cash Jul-Des 25'!$AB:$AB,'List Petty Cash Jul-Des 25'!$I:$I,Sheet1!E$1,'List Petty Cash Jul-Des 25'!$V:$V,Sheet1!$A17) -> 0 | F17: =+SUMIFS('List Petty Cash Jul-Des 25'!$AB:$AB,'List Petty Cash Jul-Des 25'!$I:$I,Sheet1!F$1,'List Petty Cash Jul-Des 25'!$V:$V,Sheet1!$A17) -> 600000 | G17: =+SUMIFS('List Petty Cash Jul-Des 25'!$AB:$AB,'List Petty Cash Jul-Des 25'!$I:$I,Sheet1!G$1,'List Petty Cash Jul-Des 25'!$V:$V,Sheet1!$A17) -> 0 | H17: =+SUMIFS('List Petty Cash Jul-Des 25'!$AB:$AB,'List Petty Cash Jul-Des 25'!$I:$I,Sheet1!H$1,'List Petty Cash Jul-Des 25'!$V:$V,Sheet1!$A17) -> 1800000 | I17: =+SUM(C17:H17) -> 3000000 | K17: R124FPO | L17: =+SUMIFS('List Petty Cash Jul-Des 25'!$AB:$AB,'List Petty Cash Jul-Des 25'!$I:$I,Sheet1!L$1,'List Petty Cash Jul-Des 25'!$X:$X,Sheet1!$K17) -> 0 | M17: =+SUMIFS('List Petty Cash Jul-Des 25'!$AB:$AB,'List Petty Cash Jul-Des 25'!$I:$I,Sheet1!M$1,'List Petty Cash Jul-Des 25'!$X:$X,Sheet1!$K17) -> 145000 | N17: =+SUMIFS('List Petty Cash Jul-Des 25'!$AB:$AB,'List Petty Cash Jul-Des 25'!$I:$I,Sheet1!N$1,'List Petty Cash Jul-Des 25'!$X:$X,Sheet1!$K17) -> 2157121 | O17: =+SUMIFS('List Petty Cash Jul-Des 25'!$AB:$AB,'List Petty Cash Jul-Des 25'!$I:$I,Sheet1!O$1,'List Petty Cash Jul-Des 25'!$X:$X,Sheet1!$K17) -> 463000 | P17: =+SUMIFS('List Petty Cash Jul-Des 25'!$AB:$AB,'List Petty Cash Jul-Des 25'!$I:$I,Sheet1!P$1,'List Petty Cash Jul-Des 25'!$X:$X,Sheet1!$K17) -> 845510 | Q17: =+SUMIFS('List Petty Cash Jul-Des 25'!$AB:$AB,'List Petty Cash Jul-Des 25'!$I:$I,Sheet1!Q$1,'List Petty Cash Jul-Des 25'!$X:$X,Sheet1!$K17) -> 416100 | R17: =+SUM(L17:Q17) -> 4026731 | S17: =+R17/$R$38*100% -> 0.01259479 | T17: 70107500 | AA17: R124FRA3 | AB17: 4295450 | AK17: M204D1COMM | AL17: 15782300
A18: 70107600 | B18: Biaya Konsumsi Kantor | C18: =+SUMIFS('List Petty Cash Jul-Des 25'!$AB:$AB,'List Petty Cash Jul-Des 25'!$I:$I,Sheet1!C$1,'List Petty Cash Jul-Des 25'!$V:$V,Sheet1!$A18) -> 7481180 | D18: =+SUMIFS('List Petty Cash Jul-Des 25'!$AB:$AB,'List Petty Cash Jul-Des 25'!$I:$I,Sheet1!D$1,'List Petty Cash Jul-Des 25'!$V:$V,Sheet1!$A18) -> 1231500 | E18: =+SUMIFS('List Petty Cash Jul-Des 25'!$AB:$AB,'List Petty Cash Jul-Des 25'!$I:$I,Sheet1!E$1,'List Petty Cash Jul-Des 25'!$V:$V,Sheet1!$A18) -> 3109831 | F18: =+SUMIFS('List Petty Cash Jul-Des 25'!$AB:$AB,'List Petty Cash Jul-Des 25'!$I:$I,Sheet1!F$1,'List Petty Cash Jul-Des 25'!$V:$V,Sheet1!$A18) -> 6498955 | G18: =+SUMIFS('List Petty Cash Jul-Des 25'!$AB:$AB,'List Petty Cash Jul-Des 25'!$I:$I,Sheet1!G$1,'List Petty Cash Jul-Des 25'!$V:$V,Sheet1!$A18) -> 7327260 | H18: =+SUMIFS('List Petty Cash Jul-Des 25'!$AB:$AB,'List Petty Cash Jul-Des 25'!$I:$I,Sheet1!H$1,'List Petty Cash Jul-Des 25'!$V:$V,Sheet1!$A18) -> 7150212 | I18: =+SUM(C18:H18) -> 32798938 | K18: R124FRA | L18: =+SUMIFS('List Petty Cash Jul-Des 25'!$AB:$AB,'List Petty Cash Jul-Des 25'!$I:$I,Sheet1!L$1,'List Petty Cash Jul-Des 25'!$X:$X,Sheet1!$K18) -> 0 | M18: =+SUMIFS('List Petty Cash Jul-Des 25'!$AB:$AB,'List Petty Cash Jul-Des 25'!$I:$I,Sheet1!M$1,'List Petty Cash Jul-Des 25'!$X:$X,Sheet1!$K18) -> 0 | N18: =+SUMIFS('List Petty Cash Jul-Des 25'!$AB:$AB,'List Petty Cash Jul-Des 25'!$I:$I,Sheet1!N$1,'List Petty Cash Jul-Des 25'!$X:$X,Sheet1!$K18) -> 61000 | O18: =+SUMIFS('List Petty Cash Jul-Des 25'!$AB:$AB,'List Petty Cash Jul-Des 25'!$I:$I,Sheet1!O$1,'List Petty Cash Jul-Des 25'!$X:$X,Sheet1!$K18) -> 2325500 | P18: =+SUMIFS('List Petty Cash Jul-Des 25'!$AB:$AB,'List Petty Cash Jul-Des 25'!$I:$I,Sheet1!P$1,'List Petty Cash Jul-Des 25'!$X:$X,Sheet1!$K18) -> 0 | Q18: =+SUMIFS('List Petty Cash Jul-Des 25'!$AB:$AB,'List Petty Cash Jul-Des 25'!$I:$I,Sheet1!Q$1,'List Petty Cash Jul-Des 25'!$X:$X,Sheet1!$K18) -> 256380 | R18: =+SUM(L18:Q18) -> 2642880 | S18: =+R18/$R$38*100% -> 0.0082663877 | T18: 70107600 | AA18: R124WHFSB | AB18: 4171300 | AK18: C206D1SLSS | AL18: 10153000
A19: 70108100 | B19: Biaya Peralatan Dan Perabot Kantor | C19: =+SUMIFS('List Petty Cash Jul-Des 25'!$AB:$AB,'List Petty Cash Jul-Des 25'!$I:$I,Sheet1!C$1,'List Petty Cash Jul-Des 25'!$V:$V,Sheet1!$A19) -> 1632050 | D19: =+SUMIFS('List Petty Cash Jul-Des 25'!$AB:$AB,'List Petty Cash Jul-Des 25'!$I:$I,Sheet1!D$1,'List Petty Cash Jul-Des 25'!$V:$V,Sheet1!$A19) -> 961000 | E19: =+SUMIFS('List Petty Cash Jul-Des 25'!$AB:$AB,'List Petty Cash Jul-Des 25'!$I:$I,Sheet1!E$1,'List Petty Cash Jul-Des 25'!$V:$V,Sheet1!$A19) -> 652400 | F19: =+SUMIFS('List Petty Cash Jul-Des 25'!$AB:$AB,'List Petty Cash Jul-Des 25'!$I:$I,Sheet1!F$1,'List Petty Cash Jul-Des 25'!$V:$V,Sheet1!$A19) -> 1881000 | G19: =+SUMIFS('List Petty Cash Jul-Des 25'!$AB:$AB,'List Petty Cash Jul-Des 25'!$I:$I,Sheet1!G$1,'List Petty Cash Jul-Des 25'!$V:$V,Sheet1!$A19) -> 1539300 | H19: =+SUMIFS('List Petty Cash Jul-Des 25'!$AB:$AB,'List Petty Cash Jul-Des 25'!$I:$I,Sheet1!H$1,'List Petty Cash Jul-Des 25'!$V:$V,Sheet1!$A19) -> 569516 | I19: =+SUM(C19:H19) -> 7235266 | K19: R124FRA3 | L19: =+SUMIFS('List Petty Cash Jul-Des 25'!$AB:$AB,'List Petty Cash Jul-Des 25'!$I:$I,Sheet1!L$1,'List Petty Cash Jul-Des 25'!$X:$X,Sheet1!$K19) -> 0 | M19: =+SUMIFS('List Petty Cash Jul-Des 25'!$AB:$AB,'List Petty Cash Jul-Des 25'!$I:$I,Sheet1!M$1,'List Petty Cash Jul-Des 25'!$X:$X,Sheet1!$K19) -> 0 | N19: =+SUMIFS('List Petty Cash Jul-Des 25'!$AB:$AB,'List Petty Cash Jul-Des 25'!$I:$I,Sheet1!N$1,'List Petty Cash Jul-Des 25'!$X:$X,Sheet1!$K19) -> 0 | O19: =+SUMIFS('List Petty Cash Jul-Des 25'!$AB:$AB,'List Petty Cash Jul-Des 25'!$I:$I,Sheet1!O$1,'List Petty Cash Jul-Des 25'!$X:$X,Sheet1!$K19) -> 2869500 | P19: =+SUMIFS('List Petty Cash Jul-Des 25'!$AB:$AB,'List Petty Cash Jul-Des 25'!$I:$I,Sheet1!P$1,'List Petty Cash Jul-Des 25'!$X:$X,Sheet1!$K19) -> 625950 | Q19: =+SUMIFS('List Petty Cash Jul-Des 25'!$AB:$AB,'List Petty Cash Jul-Des 25'!$I:$I,Sheet1!Q$1,'List Petty Cash Jul-Des 25'!$X:$X,Sheet1!$K19) -> 800000 | R19: =+SUM(L19:Q19) -> 4295450 | S19: =+R19/$R$38*100% -> 0.013435288 | T19: 70108100 | AA19: R124FPO | AB19: 4026731 | AK19: H200D1MMDP | AL19: 8948800
A20: 70108110 | B20: Biaya Fotocopy | C20: =+SUMIFS('List Petty Cash Jul-Des 25'!$AB:$AB,'List Petty Cash Jul-Des 25'!$I:$I,Sheet1!C$1,'List Petty Cash Jul-Des 25'!$V:$V,Sheet1!$A20) -> 398800 | D20: =+SUMIFS('List Petty Cash Jul-Des 25'!$AB:$AB,'List Petty Cash Jul-Des 25'!$I:$I,Sheet1!D$1,'List Petty Cash Jul-Des 25'!$V:$V,Sheet1!$A20) -> 441400 | E20: =+SUMIFS('List Petty Cash Jul-Des 25'!$AB:$AB,'List Petty Cash Jul-Des 25'!$I:$I,Sheet1!E$1,'List Petty Cash Jul-Des 25'!$V:$V,Sheet1!$A20) -> 0 | F20: =+SUMIFS('List Petty Cash Jul-Des 25'!$AB:$AB,'List Petty Cash Jul-Des 25'!$I:$I,Sheet1!F$1,'List Petty Cash Jul-Des 25'!$V:$V,Sheet1!$A20) -> 601500 | G20: =+SUMIFS('List Petty Cash Jul-Des 25'!$AB:$AB,'List Petty Cash Jul-Des 25'!$I:$I,Sheet1!G$1,'List Petty Cash Jul-Des 25'!$V:$V,Sheet1!$A20) -> 196000 | H20: =+SUMIFS('List Petty Cash Jul-Des 25'!$AB:$AB,'List Petty Cash Jul-Des 25'!$I:$I,Sheet1!H$1,'List Petty Cash Jul-Des 25'!$V:$V,Sheet1!$A20) -> 28000 | I20: =+SUM(C20:H20) -> 1665700 | K20: R124LOG | L20: =+SUMIFS('List Petty Cash Jul-Des 25'!$AB:$AB,'List Petty Cash Jul-Des 25'!$I:$I,Sheet1!L$1,'List Petty Cash Jul-Des 25'!$X:$X,Sheet1!$K20) -> 919650 | M20: =+SUMIFS('List Petty Cash Jul-Des 25'!$AB:$AB,'List Petty Cash Jul-Des 25'!$I:$I,Sheet1!M$1,'List Petty Cash Jul-Des 25'!$X:$X,Sheet1!$K20) -> 150000 | N20: =+SUMIFS('List Petty Cash Jul-Des 25'!$AB:$AB,'List Petty Cash Jul-Des 25'!$I:$I,Sheet1!N$1,'List Petty Cash Jul-Des 25'!$X:$X,Sheet1!$K20) -> 652000 | O20: =+SUMIFS('List Petty Cash Jul-Des 25'!$AB:$AB,'List Petty Cash Jul-Des 25'!$I:$I,Sheet1!O$1,'List Petty Cash Jul-Des 25'!$X:$X,Sheet1!$K20) -> 150000 | P20: =+SUMIFS('List Petty Cash Jul-Des 25'!$AB:$AB,'List Petty Cash Jul-Des 25'!$I:$I,Sheet1!P$1,'List Petty Cash Jul-Des 25'!$X:$X,Sheet1!$K20) -> 299200 | Q20: =+SUMIFS('List Petty Cash Jul-Des 25'!$AB:$AB,'List Petty Cash Jul-Des 25'!$I:$I,Sheet1!Q$1,'List Petty Cash Jul-Des 25'!$X:$X,Sheet1!$K20) -> 600000 | R20: =+SUM(L20:Q20) -> 2770850 | S20: =+R20/$R$38*100% -> 0.0086666517 | T20: 70108110 | AA20: R124D1MGMT | AB20: 3778100 | AK20: R124REF | AL20: 7294000
A21: 70110110 | B21: Biaya Organisasi Professional Nasional | C21: =+SUMIFS('List Petty Cash Jul-Des 25'!$AB:$AB,'List Petty Cash Jul-Des 25'!$I:$I,Sheet1!C$1,'List Petty Cash Jul-Des 25'!$V:$V,Sheet1!$A21) -> 700000 | D21: =+SUMIFS('List Petty Cash Jul-Des 25'!$AB:$AB,'List Petty Cash Jul-Des 25'!$I:$I,Sheet1!D$1,'List Petty Cash Jul-Des 25'!$V:$V,Sheet1!$A21) -> 0 | E21: =+SUMIFS('List Petty Cash Jul-Des 25'!$AB:$AB,'List Petty Cash Jul-Des 25'!$I:$I,Sheet1!E$1,'List Petty Cash Jul-Des 25'!$V:$V,Sheet1!$A21) -> 700000 | F21: =+SUMIFS('List Petty Cash Jul-Des 25'!$AB:$AB,'List Petty Cash Jul-Des 25'!$I:$I,Sheet1!F$1,'List Petty Cash Jul-Des 25'!$V:$V,Sheet1!$A21) -> 0 | G21: =+SUMIFS('List Petty Cash Jul-Des 25'!$AB:$AB,'List Petty Cash Jul-Des 25'!$I:$I,Sheet1!G$1,'List Petty Cash Jul-Des 25'!$V:$V,Sheet1!$A21) -> 700000 | H21: =+SUMIFS('List Petty Cash Jul-Des 25'!$AB:$AB,'List Petty Cash Jul-Des 25'!$I:$I,Sheet1!H$1,'List Petty Cash Jul-Des 25'!$V:$V,Sheet1!$A21) -> 0 | I21: =+SUM(C21:H21) -> 2100000 | K21: R124M09 | L21: =+SUMIFS('List Petty Cash Jul-Des 25'!$AB:$AB,'List Petty Cash Jul-Des 25'!$I:$I,Sheet1!L$1,'List Petty Cash Jul-Des 25'!$X:$X,Sheet1!$K21) -> 0 | M21: =+SUMIFS('List Petty Cash Jul-Des 25'!$AB:$AB,'List Petty Cash Jul-Des 25'!$I:$I,Sheet1!M$1,'List Petty Cash Jul-Des 25'!$X:$X,Sheet1!$K21) -> 0 | N21: =+SUMIFS('List Petty Cash Jul-Des 25'!$AB:$AB,'List Petty Cash Jul-Des 25'!$I:$I,Sheet1!N$1,'List Petty Cash Jul-Des 25'!$X:$X,Sheet1!$K21) -> 0 | O21: =+SUMIFS('List Petty Cash Jul-Des 25'!$AB:$AB,'List Petty Cash Jul-Des 25'!$I:$I,Sheet1!O$1,'List Petty Cash Jul-Des 25'!$X:$X,Sheet1!$K21) -> 0 | P21: =+SUMIFS('List Petty Cash Jul-Des 25'!$AB:$AB,'List Petty Cash Jul-Des 25'!$I:$I,Sheet1!P$1,'List Petty Cash Jul-Des 25'!$X:$X,Sheet1!$K21) -> 0 | Q21: =+SUMIFS('List Petty Cash Jul-Des 25'!$AB:$AB,'List Petty Cash Jul-Des 25'!$I:$I,Sheet1!Q$1,'List Petty Cash Jul-Des 25'!$X:$X,Sheet1!$K21) -> 1295000 | R21: =+SUM(L21:Q21) -> 1295000 | S21: =+R21/$R$38*100% -> 0.004050495 | T21: 70110110 | AA21: R124REF4 | AB21: 3140100 | AK21: R124MIN | AL21: 6649980
A22: 70110200 | B22: Biaya Pelatihan External Pihak ke-3 | C22: =+SUMIFS('List Petty Cash Jul-Des 25'!$AB:$AB,'List Petty Cash Jul-Des 25'!$I:$I,Sheet1!C$1,'List Petty Cash Jul-Des 25'!$V:$V,Sheet1!$A22) -> 0 | D22: =+SUMIFS('List Petty Cash Jul-Des 25'!$AB:$AB,'List Petty Cash Jul-Des 25'!$I:$I,Sheet1!D$1,'List Petty Cash Jul-Des 25'!$V:$V,Sheet1!$A22) -> 0 | E22: =+SUMIFS('List Petty Cash Jul-Des 25'!$AB:$AB,'List Petty Cash Jul-Des 25'!$I:$I,Sheet1!E$1,'List Petty Cash Jul-Des 25'!$V:$V,Sheet1!$A22) -> 0 | F22: =+SUMIFS('List Petty Cash Jul-Des 25'!$AB:$AB,'List Petty Cash Jul-Des 25'!$I:$I,Sheet1!F$1,'List Petty Cash Jul-Des 25'!$V:$V,Sheet1!$A22) -> 0 | G22: =+SUMIFS('List Petty Cash Jul-Des 25'!$AB:$AB,'List Petty Cash Jul-Des 25'!$I:$I,Sheet1!G$1,'List Petty Cash Jul-Des 25'!$V:$V,Sheet1!$A22) -> 600000 | H22: =+SUMIFS('List Petty Cash Jul-Des 25'!$AB:$AB,'List Petty Cash Jul-Des 25'!$I:$I,Sheet1!H$1,'List Petty Cash Jul-Des 25'!$V:$V,Sheet1!$A22) -> 0 | I22: =+SUM(C22:H22) -> 600000 | K22: R124MIN | L22: =+SUMIFS('List Petty Cash Jul-Des 25'!$AB:$AB,'List Petty Cash Jul-Des 25'!$I:$I,Sheet1!L$1,'List Petty Cash Jul-Des 25'!$X:$X,Sheet1!$K22) -> 1793700 | M22: =+SUMIFS('List Petty Cash Jul-Des 25'!$AB:$AB,'List Petty Cash Jul-Des 25'!$I:$I,Sheet1!M$1,'List Petty Cash Jul-Des 25'!$X:$X,Sheet1!$K22) -> 816000 | N22: =+SUMIFS('List Petty Cash Jul-Des 25'!$AB:$AB,'List Petty Cash Jul-Des 25'!$I:$I,Sheet1!N$1,'List Petty Cash Jul-Des 25'!$X:$X,Sheet1!$K22) -> 2511000 | O22: =+SUMIFS('List Petty Cash Jul-Des 25'!$AB:$AB,'List Petty Cash Jul-Des 25'!$I:$I,Sheet1!O$1,'List Petty Cash Jul-Des 25'!$X:$X,Sheet1!$K22) -> 1529280 | P22: =+SUMIFS('List Petty Cash Jul-Des 25'!$AB:$AB,'List Petty Cash Jul-Des 25'!$I:$I,Sheet1!P$1,'List Petty Cash Jul-Des 25'!$X:$X,Sheet1!$K22) -> 0 | Q22: =+SUMIFS('List Petty Cash Jul-Des 25'!$AB:$AB,'List Petty Cash Jul-Des 25'!$I:$I,Sheet1!Q$1,'List Petty Cash Jul-Des 25'!$X:$X,Sheet1!$K22) -> 0 | R22: =+SUM(L22:Q22) -> 6649980 | S22: =+R22/$R$38*100% -> 0.020799776 | T22: 70110200 | AA22: R124LOG | AB22: 2770850 | AK22: R124REF3 | AL22: 6084036
A23: 70110210 | C23: =+SUMIFS('List Petty Cash Jul-Des 25'!$AB:$AB,'List Petty Cash Jul-Des 25'!$I:$I,Sheet1!C$1,'List Petty Cash Jul-Des 25'!$V:$V,Sheet1!$A23) -> 0 | D23: =+SUMIFS('List Petty Cash Jul-Des 25'!$AB:$AB,'List Petty Cash Jul-Des 25'!$I:$I,Sheet1!D$1,'List Petty Cash Jul-Des 25'!$V:$V,Sheet1!$A23) -> 0 | E23: =+SUMIFS('List Petty Cash Jul-Des 25'!$AB:$AB,'List Petty Cash Jul-Des 25'!$I:$I,Sheet1!E$1,'List Petty Cash Jul-Des 25'!$V:$V,Sheet1!$A23) -> 0 | F23: =+SUMIFS('List Petty Cash Jul-Des 25'!$AB:$AB,'List Petty Cash Jul-Des 25'!$I:$I,Sheet1!F$1,'List Petty Cash Jul-Des 25'!$V:$V,Sheet1!$A23) -> 135000 | G23: =+SUMIFS('List Petty Cash Jul-Des 25'!$AB:$AB,'List Petty Cash Jul-Des 25'!$I:$I,Sheet1!G$1,'List Petty Cash Jul-Des 25'!$V:$V,Sheet1!$A23) -> 7478800 | H23: =+SUMIFS('List Petty Cash Jul-Des 25'!$AB:$AB,'List Petty Cash Jul-Des 25'!$I:$I,Sheet1!H$1,'List Petty Cash Jul-Des 25'!$V:$V,Sheet1!$A23) -> 1335000 | I23: =+SUM(C23:H23) -> 8948800 | K23: R124MMP | L23: =+SUMIFS('List Petty Cash Jul-Des 25'!$AB:$AB,'List Petty Cash Jul-Des 25'!$I:$I,Sheet1!L$1,'List Petty Cash Jul-Des 25'!$X:$X,Sheet1!$K23) -> 322008 | M23: =+SUMIFS('List Petty Cash Jul-Des 25'!$AB:$AB,'List Petty Cash Jul-Des 25'!$I:$I,Sheet1!M$1,'List Petty Cash Jul-Des 25'!$X:$X,Sheet1!$K23) -> 428500 | N23: =+SUMIFS('List Petty Cash Jul-Des 25'!$AB:$AB,'List Petty Cash Jul-Des 25'!$I:$I,Sheet1!N$1,'List Petty Cash Jul-Des 25'!$X:$X,Sheet1!$K23) -> 0 | O23: =+SUMIFS('List Petty Cash Jul-Des 25'!$AB:$AB,'List Petty Cash Jul-Des 25'!$I:$I,Sheet1!O$1,'List Petty Cash Jul-Des 25'!$X:$X,Sheet1!$K23) -> 519520 | P23: =+SUMIFS('List Petty Cash Jul-Des 25'!$AB:$AB,'List Petty Cash Jul-Des 25'!$I:$I,Sheet1!P$1,'List Petty Cash Jul-Des 25'!$X:$X,Sheet1!$K23) -> 591120 | Q23: =+SUMIFS('List Petty Cash Jul-Des 25'!$AB:$AB,'List Petty Cash Jul-Des 25'!$I:$I,Sheet1!Q$1,'List Petty Cash Jul-Des 25'!$X:$X,Sheet1!$K23) -> 0 | R23: =+SUM(L23:Q23) -> 1861148 | S23: =+R23/$R$38*100% -> 0.00582129 | T23: 70110210 | AA23: P206D1SLSC | AB23: 2700000
A24: 70110400 | B24: Biaya Langganan Buku, Jurnal, Koran, dan Lainnya | C24: =+SUMIFS('List Petty Cash Jul-Des 25'!$AB:$AB,'List Petty Cash Jul-Des 25'!$I:$I,Sheet1!C$1,'List Petty Cash Jul-Des 25'!$V:$V,Sheet1!$A24) -> 0 | D24: =+SUMIFS('List Petty Cash Jul-Des 25'!$AB:$AB,'List Petty Cash Jul-Des 25'!$I:$I,Sheet1!D$1,'List Petty Cash Jul-Des 25'!$V:$V,Sheet1!$A24) -> 0 | E24: =+SUMIFS('List Petty Cash Jul-Des 25'!$AB:$AB,'List Petty Cash Jul-Des 25'!$I:$I,Sheet1!E$1,'List Petty Cash Jul-Des 25'!$V:$V,Sheet1!$A24) -> 0 | F24: =+SUMIFS('List Petty Cash Jul-Des 25'!$AB:$AB,'List Petty Cash Jul-Des 25'!$I:$I,Sheet1!F$1,'List Petty Cash Jul-Des 25'!$V:$V,Sheet1!$A24) -> 0 | G24: =+SUMIFS('List Petty Cash Jul-Des 25'!$AB:$AB,'List Petty Cash Jul-Des 25'!$I:$I,Sheet1!G$1,'List Petty Cash Jul-Des 25'!$V:$V,Sheet1!$A24) -> 0 | H24: =+SUMIFS('List Petty Cash Jul-Des 25'!$AB:$AB,'List Petty Cash Jul-Des 25'!$I:$I,Sheet1!H$1,'List Petty Cash Jul-Des 25'!$V:$V,Sheet1!$A24) -> 0 | I24: =+SUM(C24:H24) -> 0 | K24: R124MNT | L24: =+SUMIFS('List Petty Cash Jul-Des 25'!$AB:$AB,'List Petty Cash Jul-Des 25'!$I:$I,Sheet1!L$1,'List Petty Cash Jul-Des 25'!$X:$X,Sheet1!$K24) -> 193900 | M24: =+SUMIFS('List Petty Cash Jul-Des 25'!$AB:$AB,'List Petty Cash Jul-Des 25'!$I:$I,Sheet1!M$1,'List Petty Cash Jul-Des 25'!$X:$X,Sheet1!$K24) -> 70000 | N24: =+SUMIFS('List Petty Cash Jul-Des 25'!$AB:$AB,'List Petty Cash Jul-Des 25'!$I:$I,Sheet1!N$1,'List Petty Cash Jul-Des 25'!$X:$X,Sheet1!$K24) -> 50000 | O24: =+SUMIFS('List Petty Cash Jul-Des 25'!$AB:$AB,'List Petty Cash Jul-Des 25'!$I:$I,Sheet1!O$1,'List Petty Cash Jul-Des 25'!$X:$X,Sheet1!$K24) -> 402500 | P24: =+SUMIFS('List Petty Cash Jul-Des 25'!$AB:$AB,'List Petty Cash Jul-Des 25'!$I:$I,Sheet1!P$1,'List Petty Cash Jul-Des 25'!$X:$X,Sheet1!$K24) -> 525000 | Q24: =+SUMIFS('List Petty Cash Jul-Des 25'!$AB:$AB,'List Petty Cash Jul-Des 25'!$I:$I,Sheet1!Q$1,'List Petty Cash Jul-Des 25'!$X:$X,Sheet1!$K24) -> 50000 | R24: =+SUM(L24:Q24) -> 1291400 | S24: =+R24/$R$38*100% -> 0.0040392349 | T24: 70115100 | AA24: R124D1FRCO | AB24: 2646550
A25: 70115100 | B25: Biaya Riset, Pengembangan, dan Laboratorium | C25: =+SUMIFS('List Petty Cash Jul-Des 25'!$AB:$AB,'List Petty Cash Jul-Des 25'!$I:$I,Sheet1!C$1,'List Petty Cash Jul-Des 25'!$V:$V,Sheet1!$A25) -> 3966500 | D25: =+SUMIFS('List Petty Cash Jul-Des 25'!$AB:$AB,'List Petty Cash Jul-Des 25'!$I:$I,Sheet1!D$1,'List Petty Cash Jul-Des 25'!$V:$V,Sheet1!$A25) -> 4734000 | E25: =+SUMIFS('List Petty Cash Jul-Des 25'!$AB:$AB,'List Petty Cash Jul-Des 25'!$I:$I,Sheet1!E$1,'List Petty Cash Jul-Des 25'!$V:$V,Sheet1!$A25) -> 0 | F25: =+SUMIFS('List Petty Cash Jul-Des 25'!$AB:$AB,'List Petty Cash Jul-Des 25'!$I:$I,Sheet1!F$1,'List Petty Cash Jul-Des 25'!$V:$V,Sheet1!$A25) -> 764725 | G25: =+SUMIFS('List Petty Cash Jul-Des 25'!$AB:$AB,'List Petty Cash Jul-Des 25'!$I:$I,Sheet1!G$1,'List Petty Cash Jul-Des 25'!$V:$V,Sheet1!$A25) -> 365900 | H25: =+SUMIFS('List Petty Cash Jul-Des 25'!$AB:$AB,'List Petty Cash Jul-Des 25'!$I:$I,Sheet1!H$1,'List Petty Cash Jul-Des 25'!$V:$V,Sheet1!$A25) -> 3072091 | I25: =+SUM(C25:H25) -> 12903216 | K25: R124NSS | L25: =+SUMIFS('List Petty Cash Jul-Des 25'!$AB:$AB,'List Petty Cash Jul-Des 25'!$I:$I,Sheet1!L$1,'List Petty Cash Jul-Des 25'!$X:$X,Sheet1!$K25) -> 1894127 | M25: =+SUMIFS('List Petty Cash Jul-Des 25'!$AB:$AB,'List Petty Cash Jul-Des 25'!$I:$I,Sheet1!M$1,'List Petty Cash Jul-Des 25'!$X:$X,Sheet1!$K25) -> 0 | N25: =+SUMIFS('List Petty Cash Jul-Des 25'!$AB:$AB,'List Petty Cash Jul-Des 25'!$I:$I,Sheet1!N$1,'List Petty Cash Jul-Des 25'!$X:$X,Sheet1!$K25) -> 0 | O25: =+SUMIFS('List Petty Cash Jul-Des 25'!$AB:$AB,'List Petty Cash Jul-Des 25'!$I:$I,Sheet1!O$1,'List Petty Cash Jul-Des 25'!$X:$X,Sheet1!$K25) -> 2804000 | P25: =+SUMIFS('List Petty Cash Jul-Des 25'!$AB:$AB,'List Petty Cash Jul-Des 25'!$I:$I,Sheet1!P$1,'List Petty Cash Jul-Des 25'!$X:$X,Sheet1!$K25) -> 992050 | Q25: =+SUMIFS('List Petty Cash Jul-Des 25'!$AB:$AB,'List Petty Cash Jul-Des 25'!$I:$I,Sheet1!Q$1,'List Petty Cash Jul-Des 25'!$X:$X,Sheet1!$K25) -> 0 | R25: =+SUM(L25:Q25) -> 5690177 | S25: =+R25/$R$38*100% -> 0.017797709 | T25: 70119300 | AA25: R124FRA | AB25: 2642880
A26: 70119300 | B26: Biaya Umum dan Administrasi | C26: =+SUMIFS('List Petty Cash Jul-Des 25'!$AB:$AB,'List Petty Cash Jul-Des 25'!$I:$I,Sheet1!C$1,'List Petty Cash Jul-Des 25'!$V:$V,Sheet1!$A26) -> 2087000 | D26: =+SUMIFS('List Petty Cash Jul-Des 25'!$AB:$AB,'List Petty Cash Jul-Des 25'!$I:$I,Sheet1!D$1,'List Petty Cash Jul-Des 25'!$V:$V,Sheet1!$A26) -> 140900 | E26: =+SUMIFS('List Petty Cash Jul-Des 25'!$AB:$AB,'List Petty Cash Jul-Des 25'!$I:$I,Sheet1!E$1,'List Petty Cash Jul-Des 25'!$V:$V,Sheet1!$A26) -> 100000 | F26: =+SUMIFS('List Petty Cash Jul-Des 25'!$AB:$AB,'List Petty Cash Jul-Des 25'!$I:$I,Sheet1!F$1,'List Petty Cash Jul-Des 25'!$V:$V,Sheet1!$A26) -> 1322000 | G26: =+SUMIFS('List Petty Cash Jul-Des 25'!$AB:$AB,'List Petty Cash Jul-Des 25'!$I:$I,Sheet1!G$1,'List Petty Cash Jul-Des 25'!$V:$V,Sheet1!$A26) -> 2435000 | H26: =+SUMIFS('List Petty Cash Jul-Des 25'!$AB:$AB,'List Petty Cash Jul-Des 25'!$I:$I,Sheet1!H$1,'List Petty Cash Jul-Des 25'!$V:$V,Sheet1!$A26) -> 2209460 | I26: =+SUM(C26:H26) -> 8294360 | K26: R124QCA | L26: =+SUMIFS('List Petty Cash Jul-Des 25'!$AB:$AB,'List Petty Cash Jul-Des 25'!$I:$I,Sheet1!L$1,'List Petty Cash Jul-Des 25'!$X:$X,Sheet1!$K26) -> 4121804 | M26: =+SUMIFS('List Petty Cash Jul-Des 25'!$AB:$AB,'List Petty Cash Jul-Des 25'!$I:$I,Sheet1!M$1,'List Petty Cash Jul-Des 25'!$X:$X,Sheet1!$K26) -> 823876 | N26: =+SUMIFS('List Petty Cash Jul-Des 25'!$AB:$AB,'List Petty Cash Jul-Des 25'!$I:$I,Sheet1!N$1,'List Petty Cash Jul-Des 25'!$X:$X,Sheet1!$K26) -> 1880800 | O26: =+SUMIFS('List Petty Cash Jul-Des 25'!$AB:$AB,'List Petty Cash Jul-Des 25'!$I:$I,Sheet1!O$1,'List Petty Cash Jul-Des 25'!$X:$X,Sheet1!$K26) -> 1916925 | P26: =+SUMIFS('List Petty Cash Jul-Des 25'!$AB:$AB,'List Petty Cash Jul-Des 25'!$I:$I,Sheet1!P$1,'List Petty Cash Jul-Des 25'!$X:$X,Sheet1!$K26) -> 1658720 | Q26: =+SUMIFS('List Petty Cash Jul-Des 25'!$AB:$AB,'List Petty Cash Jul-Des 25'!$I:$I,Sheet1!Q$1,'List Petty Cash Jul-Des 25'!$X:$X,Sheet1!$K26) -> 9562466 | R26: =+SUM(L26:Q26) -> 19964591 | S26: =+R26/$R$38*100% -> 0.062445155 | AA26: R124D1PRCN | AB26: 2600000
A27: 70119500 | B27: Biaya Transportasi Barang - Pihak Ketiga | C27: =+SUMIFS('List Petty Cash Jul-Des 25'!$AB:$AB,'List Petty Cash Jul-Des 25'!$I:$I,Sheet1!C$1,'List Petty Cash Jul-Des 25'!$V:$V,Sheet1!$A27) -> 0 | D27: =+SUMIFS('List Petty Cash Jul-Des 25'!$AB:$AB,'List Petty Cash Jul-Des 25'!$I:$I,Sheet1!D$1,'List Petty Cash Jul-Des 25'!$V:$V,Sheet1!$A27) -> 0 | E27: =+SUMIFS('List Petty Cash Jul-Des 25'!$AB:$AB,'List Petty Cash Jul-Des 25'!$I:$I,Sheet1!E$1,'List Petty Cash Jul-Des 25'!$V:$V,Sheet1!$A27) -> 0 | F27: =+SUMIFS('List Petty Cash Jul-Des 25'!$AB:$AB,'List Petty Cash Jul-Des 25'!$I:$I,Sheet1!F$1,'List Petty Cash Jul-Des 25'!$V:$V,Sheet1!$A27) -> 0 | G27: =+SUMIFS('List Petty Cash Jul-Des 25'!$AB:$AB,'List Petty Cash Jul-Des 25'!$I:$I,Sheet1!G$1,'List Petty Cash Jul-Des 25'!$V:$V,Sheet1!$A27) -> 0 | H27: =+SUMIFS('List Petty Cash Jul-Des 25'!$AB:$AB,'List Petty Cash Jul-Des 25'!$I:$I,Sheet1!H$1,'List Petty Cash Jul-Des 25'!$V:$V,Sheet1!$A27) -> 0 | I27: =+SUM(C27:H27) -> 0 | K27: R124QMR | L27: =+SUMIFS('List Petty Cash Jul-Des 25'!$AB:$AB,'List Petty Cash Jul-Des 25'!$I:$I,Sheet1!L$1,'List Petty Cash Jul-Des 25'!$X:$X,Sheet1!$K27) -> 1292400 | M27: =+SUMIFS('List Petty Cash Jul-Des 25'!$AB:$AB,'List Petty Cash Jul-Des 25'!$I:$I,Sheet1!M$1,'List Petty Cash Jul-Des 25'!$X:$X,Sheet1!$K27) -> 71400 | N27: =+SUMIFS('List Petty Cash Jul-Des 25'!$AB:$AB,'List Petty Cash Jul-Des 25'!$I:$I,Sheet1!N$1,'List Petty Cash Jul-Des 25'!$X:$X,Sheet1!$K27) -> 0 | O27: =+SUMIFS('List Petty Cash Jul-Des 25'!$AB:$AB,'List Petty Cash Jul-Des 25'!$I:$I,Sheet1!O$1,'List Petty Cash Jul-Des 25'!$X:$X,Sheet1!$K27) -> 586500 | P27: =+SUMIFS('List Petty Cash Jul-Des 25'!$AB:$AB,'List Petty Cash Jul-Des 25'!$I:$I,Sheet1!P$1,'List Petty Cash Jul-Des 25'!$X:$X,Sheet1!$K27) -> 180000 | Q27: =+SUMIFS('List Petty Cash Jul-Des 25'!$AB:$AB,'List Petty Cash Jul-Des 25'!$I:$I,Sheet1!Q$1,'List Petty Cash Jul-Des 25'!$X:$X,Sheet1!$K27) -> 0 | R27: =+SUM(L27:Q27) -> 2130300 | S27: =+R27/$R$38*100% -> 0.0066631424 | AA27: R124WHP | AB27: 2235247
C28: =SUM(C2:C27) -> 58589163 | D28: =SUM(D2:D27) -> 34438078 | E28: =SUM(E2:E27) -> 30159697 | F28: =SUM(F2:F27) -> 63465821 | G28: =SUM(G2:G27) -> 66145918 | H28: =SUM(H2:H27) -> 66915336 | I28: =SUM(I2:I27) -> 319714013 | K28: R124REF | L28: =+SUMIFS('List Petty Cash Jul-Des 25'!$AB:$AB,'List Petty Cash Jul-Des 25'!$I:$I,Sheet1!L$1,'List Petty Cash Jul-Des 25'!$X:$X,Sheet1!$K28) -> 1834000 | M28: =+SUMIFS('List Petty Cash Jul-Des 25'!$AB:$AB,'List Petty Cash Jul-Des 25'!$I:$I,Sheet1!M$1,'List Petty Cash Jul-Des 25'!$X:$X,Sheet1!$K28) -> 604000 | N28: =+SUMIFS('List Petty Cash Jul-Des 25'!$AB:$AB,'List Petty Cash Jul-Des 25'!$I:$I,Sheet1!N$1,'List Petty Cash Jul-Des 25'!$X:$X,Sheet1!$K28) -> 800000 | O28: =+SUMIFS('List Petty Cash Jul-Des 25'!$AB:$AB,'List Petty Cash Jul-Des 25'!$I:$I,Sheet1!O$1,'List Petty Cash Jul-Des 25'!$X:$X,Sheet1!$K28) -> 379000 | P28: =+SUMIFS('List Petty Cash Jul-Des 25'!$AB:$AB,'List Petty Cash Jul-Des 25'!$I:$I,Sheet1!P$1,'List Petty Cash Jul-Des 25'!$X:$X,Sheet1!$K28) -> 919000 | Q28: =+SUMIFS('List Petty Cash Jul-Des 25'!$AB:$AB,'List Petty Cash Jul-Des 25'!$I:$I,Sheet1!Q$1,'List Petty Cash Jul-Des 25'!$X:$X,Sheet1!$K28) -> 2758000 | R28: =+SUM(L28:Q28) -> 7294000 | S28: =+R28/$R$38*100% -> 0.022814139 | AA28: R124QMR | AB28: 2130300
K29: R124REF2 | L29: =+SUMIFS('List Petty Cash Jul-Des 25'!$AB:$AB,'List Petty Cash Jul-Des 25'!$I:$I,Sheet1!L$1,'List Petty Cash Jul-Des 25'!$X:$X,Sheet1!$K29) -> 0 | M29: =+SUMIFS('List Petty Cash Jul-Des 25'!$AB:$AB,'List Petty Cash Jul-Des 25'!$I:$I,Sheet1!M$1,'List Petty Cash Jul-Des 25'!$X:$X,Sheet1!$K29) -> 310000 | N29: =+SUMIFS('List Petty Cash Jul-Des 25'!$AB:$AB,'List Petty Cash Jul-Des 25'!$I:$I,Sheet1!N$1,'List Petty Cash Jul-Des 25'!$X:$X,Sheet1!$K29) -> 0 | O29: =+SUMIFS('List Petty Cash Jul-Des 25'!$AB:$AB,'List Petty Cash Jul-Des 25'!$I:$I,Sheet1!O$1,'List Petty Cash Jul-Des 25'!$X:$X,Sheet1!$K29) -> 0 | P29: =+SUMIFS('List Petty Cash Jul-Des 25'!$AB:$AB,'List Petty Cash Jul-Des 25'!$I:$I,Sheet1!P$1,'List Petty Cash Jul-Des 25'!$X:$X,Sheet1!$K29) -> 768956 | Q29: =+SUMIFS('List Petty Cash Jul-Des 25'!$AB:$AB,'List Petty Cash Jul-Des 25'!$I:$I,Sheet1!Q$1,'List Petty Cash Jul-Des 25'!$X:$X,Sheet1!$K29) -> 0 | R29: =+SUM(L29:Q29) -> 1078956 | S29: =+R29/$R$38*100% -> 0.0033747535 | AA29: R124FAM | AB29: 2047748
K30: R124REF3 | L30: =+SUMIFS('List Petty Cash Jul-Des 25'!$AB:$AB,'List Petty Cash Jul-Des 25'!$I:$I,Sheet1!L$1,'List Petty Cash Jul-Des 25'!$X:$X,Sheet1!$K30) -> 648100 | M30: =+SUMIFS('List Petty Cash Jul-Des 25'!$AB:$AB,'List Petty Cash Jul-Des 25'!$I:$I,Sheet1!M$1,'List Petty Cash Jul-Des 25'!$X:$X,Sheet1!$K30) -> 0 | N30: =+SUMIFS('List Petty Cash Jul-Des 25'!$AB:$AB,'List Petty Cash Jul-Des 25'!$I:$I,Sheet1!N$1,'List Petty Cash Jul-Des 25'!$X:$X,Sheet1!$K30) -> 261036 | O30: =+SUMIFS('List Petty Cash Jul-Des 25'!$AB:$AB,'List Petty Cash Jul-Des 25'!$I:$I,Sheet1!O$1,'List Petty Cash Jul-Des 25'!$X:$X,Sheet1!$K30) -> 2744500 | P30: =+SUMIFS('List Petty Cash Jul-Des 25'!$AB:$AB,'List Petty Cash Jul-Des 25'!$I:$I,Sheet1!P$1,'List Petty Cash Jul-Des 25'!$X:$X,Sheet1!$K30) -> 819600 | Q30: =+SUMIFS('List Petty Cash Jul-Des 25'!$AB:$AB,'List Petty Cash Jul-Des 25'!$I:$I,Sheet1!Q$1,'List Petty Cash Jul-Des 25'!$X:$X,Sheet1!$K30) -> 1610800 | R30: =+SUM(L30:Q30) -> 6084036 | S30: =+R30/$R$38*100% -> 0.019029619 | AA30: R124MMP | AB30: 1861148
K31: R124REF4 | L31: =+SUMIFS('List Petty Cash Jul-Des 25'!$AB:$AB,'List Petty Cash Jul-Des 25'!$I:$I,Sheet1!L$1,'List Petty Cash Jul-Des 25'!$X:$X,Sheet1!$K31) -> 0 | M31: =+SUMIFS('List Petty Cash Jul-Des 25'!$AB:$AB,'List Petty Cash Jul-Des 25'!$I:$I,Sheet1!M$1,'List Petty Cash Jul-Des 25'!$X:$X,Sheet1!$K31) -> 0 | N31: =+SUMIFS('List Petty Cash Jul-Des 25'!$AB:$AB,'List Petty Cash Jul-Des 25'!$I:$I,Sheet1!N$1,'List Petty Cash Jul-Des 25'!$X:$X,Sheet1!$K31) -> 0 | O31: =+SUMIFS('List Petty Cash Jul-Des 25'!$AB:$AB,'List Petty Cash Jul-Des 25'!$I:$I,Sheet1!O$1,'List Petty Cash Jul-Des 25'!$X:$X,Sheet1!$K31) -> 1663000 | P31: =+SUMIFS('List Petty Cash Jul-Des 25'!$AB:$AB,'List Petty Cash Jul-Des 25'!$I:$I,Sheet1!P$1,'List Petty Cash Jul-Des 25'!$X:$X,Sheet1!$K31) -> 877100 | Q31: =+SUMIFS('List Petty Cash Jul-Des 25'!$AB:$AB,'List Petty Cash Jul-Des 25'!$I:$I,Sheet1!Q$1,'List Petty Cash Jul-Des 25'!$X:$X,Sheet1!$K31) -> 600000 | R31: =+SUM(L31:Q31) -> 3140100 | S31: =+R31/$R$38*100% -> 0.0098215901 | AA31: R124WHRS | AB31: 1590910
K32: R124STTRK | L32: =+SUMIFS('List Petty Cash Jul-Des 25'!$AB:$AB,'List Petty Cash Jul-Des 25'!$I:$I,Sheet1!L$1,'List Petty Cash Jul-Des 25'!$X:$X,Sheet1!$K32) -> 0 | M32: =+SUMIFS('List Petty Cash Jul-Des 25'!$AB:$AB,'List Petty Cash Jul-Des 25'!$I:$I,Sheet1!M$1,'List Petty Cash Jul-Des 25'!$X:$X,Sheet1!$K32) -> 0 | N32: =+SUMIFS('List Petty Cash Jul-Des 25'!$AB:$AB,'List Petty Cash Jul-Des 25'!$I:$I,Sheet1!N$1,'List Petty Cash Jul-Des 25'!$X:$X,Sheet1!$K32) -> 133500 | O32: =+SUMIFS('List Petty Cash Jul-Des 25'!$AB:$AB,'List Petty Cash Jul-Des 25'!$I:$I,Sheet1!O$1,'List Petty Cash Jul-Des 25'!$X:$X,Sheet1!$K32) -> 0 | P32: =+SUMIFS('List Petty Cash Jul-Des 25'!$AB:$AB,'List Petty Cash Jul-Des 25'!$I:$I,Sheet1!P$1,'List Petty Cash Jul-Des 25'!$X:$X,Sheet1!$K32) -> 208000 | Q32: =+SUMIFS('List Petty Cash Jul-Des 25'!$AB:$AB,'List Petty Cash Jul-Des 25'!$I:$I,Sheet1!Q$1,'List Petty Cash Jul-Des 25'!$X:$X,Sheet1!$K32) -> 1044900 | R32: =+SUM(L32:Q32) -> 1386400 | S32: =+R32/$R$38*100% -> 0.0043363755 | AA32: R124STTRK | AB32: 1386400
K33: R124TCP | L33: =+SUMIFS('List Petty Cash Jul-Des 25'!$AB:$AB,'List Petty Cash Jul-Des 25'!$I:$I,Sheet1!L$1,'List Petty Cash Jul-Des 25'!$X:$X,Sheet1!$K33) -> 2781500 | M33: =+SUMIFS('List Petty Cash Jul-Des 25'!$AB:$AB,'List Petty Cash Jul-Des 25'!$I:$I,Sheet1!M$1,'List Petty Cash Jul-Des 25'!$X:$X,Sheet1!$K33) -> 0 | N33: =+SUMIFS('List Petty Cash Jul-Des 25'!$AB:$AB,'List Petty Cash Jul-Des 25'!$I:$I,Sheet1!N$1,'List Petty Cash Jul-Des 25'!$X:$X,Sheet1!$K33) -> 0 | O33: =+SUMIFS('List Petty Cash Jul-Des 25'!$AB:$AB,'List Petty Cash Jul-Des 25'!$I:$I,Sheet1!O$1,'List Petty Cash Jul-Des 25'!$X:$X,Sheet1!$K33) -> 80000 | P33: =+SUMIFS('List Petty Cash Jul-Des 25'!$AB:$AB,'List Petty Cash Jul-Des 25'!$I:$I,Sheet1!P$1,'List Petty Cash Jul-Des 25'!$X:$X,Sheet1!$K33) -> 0 | Q33: =+SUMIFS('List Petty Cash Jul-Des 25'!$AB:$AB,'List Petty Cash Jul-Des 25'!$I:$I,Sheet1!Q$1,'List Petty Cash Jul-Des 25'!$X:$X,Sheet1!$K33) -> 1907540 | R33: =+SUM(L33:Q33) -> 4769040 | S33: =+R33/$R$38*100% -> 0.014916581 | AA33: R124M09 | AB33: 1295000
K34: R124WHFSB | L34: =+SUMIFS('List Petty Cash Jul-Des 25'!$AB:$AB,'List Petty Cash Jul-Des 25'!$I:$I,Sheet1!L$1,'List Petty Cash Jul-Des 25'!$X:$X,Sheet1!$K34) -> 2017000 | M34: =+SUMIFS('List Petty Cash Jul-Des 25'!$AB:$AB,'List Petty Cash Jul-Des 25'!$I:$I,Sheet1!M$1,'List Petty Cash Jul-Des 25'!$X:$X,Sheet1!$K34) -> 386300 | N34: =+SUMIFS('List Petty Cash Jul-Des 25'!$AB:$AB,'List Petty Cash Jul-Des 25'!$I:$I,Sheet1!N$1,'List Petty Cash Jul-Des 25'!$X:$X,Sheet1!$K34) -> 0 | O34: =+SUMIFS('List Petty Cash Jul-Des 25'!$AB:$AB,'List Petty Cash Jul-Des 25'!$I:$I,Sheet1!O$1,'List Petty Cash Jul-Des 25'!$X:$X,Sheet1!$K34) -> 822000 | P34: =+SUMIFS('List Petty Cash Jul-Des 25'!$AB:$AB,'List Petty Cash Jul-Des 25'!$I:$I,Sheet1!P$1,'List Petty Cash Jul-Des 25'!$X:$X,Sheet1!$K34) -> 0 | Q34: =+SUMIFS('List Petty Cash Jul-Des 25'!$AB:$AB,'List Petty Cash Jul-Des 25'!$I:$I,Sheet1!Q$1,'List Petty Cash Jul-Des 25'!$X:$X,Sheet1!$K34) -> 946000 | R34: =+SUM(L34:Q34) -> 4171300 | S34: =+R34/$R$38*100% -> 0.013046973 | AA34: R124MNT | AB34: 1291400
K35: R124WHP | L35: =+SUMIFS('List Petty Cash Jul-Des 25'!$AB:$AB,'List Petty Cash Jul-Des 25'!$I:$I,Sheet1!L$1,'List Petty Cash Jul-Des 25'!$X:$X,Sheet1!$K35) -> 835777 | M35: =+SUMIFS('List Petty Cash Jul-Des 25'!$AB:$AB,'List Petty Cash Jul-Des 25'!$I:$I,Sheet1!M$1,'List Petty Cash Jul-Des 25'!$X:$X,Sheet1!$K35) -> 0 | N35: =+SUMIFS('List Petty Cash Jul-Des 25'!$AB:$AB,'List Petty Cash Jul-Des 25'!$I:$I,Sheet1!N$1,'List Petty Cash Jul-Des 25'!$X:$X,Sheet1!$K35) -> 0 | O35: =+SUMIFS('List Petty Cash Jul-Des 25'!$AB:$AB,'List Petty Cash Jul-Des 25'!$I:$I,Sheet1!O$1,'List Petty Cash Jul-Des 25'!$X:$X,Sheet1!$K35) -> 890470 | P35: =+SUMIFS('List Petty Cash Jul-Des 25'!$AB:$AB,'List Petty Cash Jul-Des 25'!$I:$I,Sheet1!P$1,'List Petty Cash Jul-Des 25'!$X:$X,Sheet1!$K35) -> 0 | Q35: =+SUMIFS('List Petty Cash Jul-Des 25'!$AB:$AB,'List Petty Cash Jul-Des 25'!$I:$I,Sheet1!Q$1,'List Petty Cash Jul-Des 25'!$X:$X,Sheet1!$K35) -> 509000 | R35: =+SUM(L35:Q35) -> 2235247 | S35: =+R35/$R$38*100% -> 0.0069913952 | AA35: R124REF2 | AB35: 1078956
K36: R124WHRS | L36: =+SUMIFS('List Petty Cash Jul-Des 25'!$AB:$AB,'List Petty Cash Jul-Des 25'!$I:$I,Sheet1!L$1,'List Petty Cash Jul-Des 25'!$X:$X,Sheet1!$K36) -> 243910 | M36: =+SUMIFS('List Petty Cash Jul-Des 25'!$AB:$AB,'List Petty Cash Jul-Des 25'!$I:$I,Sheet1!M$1,'List Petty Cash Jul-Des 25'!$X:$X,Sheet1!$K36) -> 0 | N36: =+SUMIFS('List Petty Cash Jul-Des 25'!$AB:$AB,'List Petty Cash Jul-Des 25'!$I:$I,Sheet1!N$1,'List Petty Cash Jul-Des 25'!$X:$X,Sheet1!$K36) -> 581500 | O36: =+SUMIFS('List Petty Cash Jul-Des 25'!$AB:$AB,'List Petty Cash Jul-Des 25'!$I:$I,Sheet1!O$1,'List Petty Cash Jul-Des 25'!$X:$X,Sheet1!$K36) -> 665500 | P36: =+SUMIFS('List Petty Cash Jul-Des 25'!$AB:$AB,'List Petty Cash Jul-Des 25'!$I:$I,Sheet1!P$1,'List Petty Cash Jul-Des 25'!$X:$X,Sheet1!$K36) -> 100000 | Q36: =+SUMIFS('List Petty Cash Jul-Des 25'!$AB:$AB,'List Petty Cash Jul-Des 25'!$I:$I,Sheet1!Q$1,'List Petty Cash Jul-Des 25'!$X:$X,Sheet1!$K36) -> 0 | R36: =+SUM(L36:Q36) -> 1590910 | S36: =+R36/$R$38*100% -> 0.0049760409 | AA36: R124WTT | AB36: 991000
K37: R124WTT | L37: =+SUMIFS('List Petty Cash Jul-Des 25'!$AB:$AB,'List Petty Cash Jul-Des 25'!$I:$I,Sheet1!L$1,'List Petty Cash Jul-Des 25'!$X:$X,Sheet1!$K37) -> 991000 | M37: =+SUMIFS('List Petty Cash Jul-Des 25'!$AB:$AB,'List Petty Cash Jul-Des 25'!$I:$I,Sheet1!M$1,'List Petty Cash Jul-Des 25'!$X:$X,Sheet1!$K37) -> 0 | N37: =+SUMIFS('List Petty Cash Jul-Des 25'!$AB:$AB,'List Petty Cash Jul-Des 25'!$I:$I,Sheet1!N$1,'List Petty Cash Jul-Des 25'!$X:$X,Sheet1!$K37) -> 0 | O37: =+SUMIFS('List Petty Cash Jul-Des 25'!$AB:$AB,'List Petty Cash Jul-Des 25'!$I:$I,Sheet1!O$1,'List Petty Cash Jul-Des 25'!$X:$X,Sheet1!$K37) -> 0 | P37: =+SUMIFS('List Petty Cash Jul-Des 25'!$AB:$AB,'List Petty Cash Jul-Des 25'!$I:$I,Sheet1!P$1,'List Petty Cash Jul-Des 25'!$X:$X,Sheet1!$K37) -> 0 | Q37: =+SUMIFS('List Petty Cash Jul-Des 25'!$AB:$AB,'List Petty Cash Jul-Des 25'!$I:$I,Sheet1!Q$1,'List Petty Cash Jul-Des 25'!$X:$X,Sheet1!$K37) -> 0 | R37: =+SUM(L37:Q37) -> 991000 | S37: =+R37/$R$38*100% -> 0.0030996452 | AA37: R124D1TPDU | AB37: 385000
L38: =SUM(L2:L37) -> 58589163 | M38: =SUM(M2:M37) -> 34438078 | N38: =SUM(N2:N37) -> 30159697 | O38: =SUM(O2:O37) -> 63465821 | P38: =SUM(P2:P37) -> 66145918 | Q38: =SUM(Q2:Q37) -> 66915336 | R38: =SUM(R2:R37) -> 319714013
C39: 07 | D39: 08 | E39: 09 | F39: 10 | G39: 11 | H39: 12 | I39: Total
A40: - | C40: =+SUMIFS('List Petty Cash Jul-Des 25'!$AB:$AB,'List Petty Cash Jul-Des 25'!$I:$I,Sheet1!C$1,'List Petty Cash Jul-Des 25'!$V:$V,Sheet1!$A40) -> 0
A41: 15000900 | C41: =+SUMIFS('List Petty Cash Jul-Des 25'!$AB:$AB,'List Petty Cash Jul-Des 25'!$I:$I,Sheet1!C$1,'List Petty Cash Jul-Des 25'!$V:$V,Sheet1!$A41,'List Petty Cash Jul-Des 25'!$X:$X,Sheet1!$A40) -> 131000 | D41: =+SUMIFS('List Petty Cash Jul-Des 25'!$AB:$AB,'List Petty Cash Jul-Des 25'!$I:$I,Sheet1!D$1,'List Petty Cash Jul-Des 25'!$V:$V,Sheet1!$A41,'List Petty Cash Jul-Des 25'!$X:$X,Sheet1!$A40) -> 930000 | E41: =+SUMIFS('List Petty Cash Jul-Des 25'!$AB:$AB,'List Petty Cash Jul-Des 25'!$I:$I,Sheet1!E$1,'List Petty Cash Jul-Des 25'!$V:$V,Sheet1!$A41,'List Petty Cash Jul-Des 25'!$X:$X,Sheet1!$A40) -> 1203853 | F41: =+SUMIFS('List Petty Cash Jul-Des 25'!$AB:$AB,'List Petty Cash Jul-Des 25'!$I:$I,Sheet1!F$1,'List Petty Cash Jul-Des 25'!$V:$V,Sheet1!$A41,'List Petty Cash Jul-Des 25'!$X:$X,Sheet1!$A40) -> 1469656 | G41: =+SUMIFS('List Petty Cash Jul-Des 25'!$AB:$AB,'List Petty Cash Jul-Des 25'!$I:$I,Sheet1!G$1,'List Petty Cash Jul-Des 25'!$V:$V,Sheet1!$A41,'List Petty Cash Jul-Des 25'!$X:$X,Sheet1!$A40) -> 4791052 | H41: =+SUMIFS('List Petty Cash Jul-Des 25'!$AB:$AB,'List Petty Cash Jul-Des 25'!$I:$I,Sheet1!H$1,'List Petty Cash Jul-Des 25'!$V:$V,Sheet1!$A41,'List Petty Cash Jul-Des 25'!$X:$X,Sheet1!$A40) -> 3214369 | I41: =+SUM(C41:H41) -> 11739930
A42: C206D1SLSS | S42: Bulan | T42: Total
A43: 70001110 | B43: =+VLOOKUP(A43,$A$2:$B$27,2,0) -> Biaya Ekspor lainnya | C43: =+SUMIFS('List Petty Cash Jul-Des 25'!$AB:$AB,'List Petty Cash Jul-Des 25'!$I:$I,Sheet1!C$1,'List Petty Cash Jul-Des 25'!$V:$V,Sheet1!$A43,'List Petty Cash Jul-Des 25'!$X:$X,Sheet1!$A42) -> 0 | D43: =+SUMIFS('List Petty Cash Jul-Des 25'!$AB:$AB,'List Petty Cash Jul-Des 25'!$I:$I,Sheet1!D$1,'List Petty Cash Jul-Des 25'!$V:$V,Sheet1!$A43,'List Petty Cash Jul-Des 25'!$X:$X,Sheet1!$A42) -> 0 | E43: =+SUMIFS('List Petty Cash Jul-Des 25'!$AB:$AB,'List Petty Cash Jul-Des 25'!$I:$I,Sheet1!E$1,'List Petty Cash Jul-Des 25'!$V:$V,Sheet1!$A43,'List Petty Cash Jul-Des 25'!$X:$X,Sheet1!$A42) -> 0 | F43: =+SUMIFS('List Petty Cash Jul-Des 25'!$AB:$AB,'List Petty Cash Jul-Des 25'!$I:$I,Sheet1!F$1,'List Petty Cash Jul-Des 25'!$V:$V,Sheet1!$A43,'List Petty Cash Jul-Des 25'!$X:$X,Sheet1!$A42) -> 0 | G43: =+SUMIFS('List Petty Cash Jul-Des 25'!$AB:$AB,'List Petty Cash Jul-Des 25'!$I:$I,Sheet1!G$1,'List Petty Cash Jul-Des 25'!$V:$V,Sheet1!$A43,'List Petty Cash Jul-Des 25'!$X:$X,Sheet1!$A42) -> 1420000 | H43: =+SUMIFS('List Petty Cash Jul-Des 25'!$AB:$AB,'List Petty Cash Jul-Des 25'!$I:$I,Sheet1!H$1,'List Petty Cash Jul-Des 25'!$V:$V,Sheet1!$A43,'List Petty Cash Jul-Des 25'!$X:$X,Sheet1!$A42) -> 1300000 | I43: =+SUM(C43:H43) -> 2720000 | S43: Juli 2025 | T43: =+C28 -> 58589163
A44: 70009110 | B44: =+VLOOKUP(A44,$A$2:$B$27,2,0) -> Biaya Survey dan Analisa | C44: =+SUMIFS('List Petty Cash Jul-Des 25'!$AB:$AB,'List Petty Cash Jul-Des 25'!$I:$I,Sheet1!C$1,'List Petty Cash Jul-Des 25'!$V:$V,Sheet1!$A44,'List Petty Cash Jul-Des 25'!$X:$X,Sheet1!$A42) -> 400000 | D44: =+SUMIFS('List Petty Cash Jul-Des 25'!$AB:$AB,'List Petty Cash Jul-Des 25'!$I:$I,Sheet1!D$1,'List Petty Cash Jul-Des 25'!$V:$V,Sheet1!$A44,'List Petty Cash Jul-Des 25'!$X:$X,Sheet1!$A42) -> 1350000 | E44: =+SUMIFS('List Petty Cash Jul-Des 25'!$AB:$AB,'List Petty Cash Jul-Des 25'!$I:$I,Sheet1!E$1,'List Petty Cash Jul-Des 25'!$V:$V,Sheet1!$A44,'List Petty Cash Jul-Des 25'!$X:$X,Sheet1!$A42) -> 850000 | F44: =+SUMIFS('List Petty Cash Jul-Des 25'!$AB:$AB,'List Petty Cash Jul-Des 25'!$I:$I,Sheet1!F$1,'List Petty Cash Jul-Des 25'!$V:$V,Sheet1!$A44,'List Petty Cash Jul-Des 25'!$X:$X,Sheet1!$A42) -> 2400000 | G44: =+SUMIFS('List Petty Cash Jul-Des 25'!$AB:$AB,'List Petty Cash Jul-Des 25'!$I:$I,Sheet1!G$1,'List Petty Cash Jul-Des 25'!$V:$V,Sheet1!$A44,'List Petty Cash Jul-Des 25'!$X:$X,Sheet1!$A42) -> 0 | H44: =+SUMIFS('List Petty Cash Jul-Des 25'!$AB:$AB,'List Petty Cash Jul-Des 25'!$I:$I,Sheet1!H$1,'List Petty Cash Jul-Des 25'!$V:$V,Sheet1!$A44,'List Petty Cash Jul-Des 25'!$X:$X,Sheet1!$A42) -> 0 | I44: =+SUM(C44:H44) -> 5000000 | S44: Agust 2025 | T44: =+D28 -> 34438078
A45: 70101202 | B45: =+VLOOKUP(A45,$A$2:$B$27,2,0) -> By Pemeliharaan Kend,ABerat,Mesin-Material Pihak3 | C45: =+SUMIFS('List Petty Cash Jul-Des 25'!$AB:$AB,'List Petty Cash Jul-Des 25'!$I:$I,Sheet1!C$1,'List Petty Cash Jul-Des 25'!$V:$V,Sheet1!$A45,'List Petty Cash Jul-Des 25'!$X:$X,Sheet1!$A42) -> 420000 | D45: =+SUMIFS('List Petty Cash Jul-Des 25'!$AB:$AB,'List Petty Cash Jul-Des 25'!$I:$I,Sheet1!D$1,'List Petty Cash Jul-Des 25'!$V:$V,Sheet1!$A45,'List Petty Cash Jul-Des 25'!$X:$X,Sheet1!$A42) -> 520000 | E45: =+SUMIFS('List Petty Cash Jul-Des 25'!$AB:$AB,'List Petty Cash Jul-Des 25'!$I:$I,Sheet1!E$1,'List Petty Cash Jul-Des 25'!$V:$V,Sheet1!$A45,'List Petty Cash Jul-Des 25'!$X:$X,Sheet1!$A42) -> 430000 | F45: =+SUMIFS('List Petty Cash Jul-Des 25'!$AB:$AB,'List Petty Cash Jul-Des 25'!$I:$I,Sheet1!F$1,'List Petty Cash Jul-Des 25'!$V:$V,Sheet1!$A45,'List Petty Cash Jul-Des 25'!$X:$X,Sheet1!$A42) -> 375000 | G45: =+SUMIFS('List Petty Cash Jul-Des 25'!$AB:$AB,'List Petty Cash Jul-Des 25'!$I:$I,Sheet1!G$1,'List Petty Cash Jul-Des 25'!$V:$V,Sheet1!$A45,'List Petty Cash Jul-Des 25'!$X:$X,Sheet1!$A42) -> 358000 | H45: =+SUMIFS('List Petty Cash Jul-Des 25'!$AB:$AB,'List Petty Cash Jul-Des 25'!$I:$I,Sheet1!H$1,'List Petty Cash Jul-Des 25'!$V:$V,Sheet1!$A45,'List Petty Cash Jul-Des 25'!$X:$X,Sheet1!$A42) -> 330000 | I45: =+SUM(C45:H45) -> 2433000 | S45: Sept 2025 | T45: =+E28 -> 30159697
A46: H200D1MMDP | S46: Okt 2025 | T46: =+F28 -> 63465821
A47: 70110210 | B47: =+VLOOKUP(A47,$A$2:$B$27,2,0) -> 0 | C47: =+SUMIFS('List Petty Cash Jul-Des 25'!$AB:$AB,'List Petty Cash Jul-Des 25'!$I:$I,Sheet1!C$1,'List Petty Cash Jul-Des 25'!$V:$V,Sheet1!$A47,'List Petty Cash Jul-Des 25'!$X:$X,Sheet1!$A46) -> 0 | D47: =+SUMIFS('List Petty Cash Jul-Des 25'!$AB:$AB,'List Petty Cash Jul-Des 25'!$I:$I,Sheet1!D$1,'List Petty Cash Jul-Des 25'!$V:$V,Sheet1!$A47,'List Petty Cash Jul-Des 25'!$X:$X,Sheet1!$A46) -> 0 | E47: =+SUMIFS('List Petty Cash Jul-Des 25'!$AB:$AB,'List Petty Cash Jul-Des 25'!$I:$I,Sheet1!E$1,'List Petty Cash Jul-Des 25'!$V:$V,Sheet1!$A47,'List Petty Cash Jul-Des 25'!$X:$X,Sheet1!$A46) -> 0 | F47: =+SUMIFS('List Petty Cash Jul-Des 25'!$AB:$AB,'List Petty Cash Jul-Des 25'!$I:$I,Sheet1!F$1,'List Petty Cash Jul-Des 25'!$V:$V,Sheet1!$A47,'List Petty Cash Jul-Des 25'!$X:$X,Sheet1!$A46) -> 135000 | G47: =+SUMIFS('List Petty Cash Jul-Des 25'!$AB:$AB,'List Petty Cash Jul-Des 25'!$I:$I,Sheet1!G$1,'List Petty Cash Jul-Des 25'!$V:$V,Sheet1!$A47,'List Petty Cash Jul-Des 25'!$X:$X,Sheet1!$A46) -> 7478800 | H47: =+SUMIFS('List Petty Cash Jul-Des 25'!$AB:$AB,'List Petty Cash Jul-Des 25'!$I:$I,Sheet1!H$1,'List Petty Cash Jul-Des 25'!$V:$V,Sheet1!$A47,'List Petty Cash Jul-Des 25'!$X:$X,Sheet1!$A46) -> 1335000 | I47: =+SUM(C47:H47) -> 8948800 | S47: Nov 2025 | T47: =+G28 -> 66145918
A48: M204D1COMM | S48: Des 2025 | T48: =+H28 -> 66915336
A49: 70001110 | B49: =+VLOOKUP(A49,$A$2:$B$27,2,0) -> Biaya Ekspor lainnya | C49: =+SUMIFS('List Petty Cash Jul-Des 25'!$AB:$AB,'List Petty Cash Jul-Des 25'!$I:$I,Sheet1!C$1,'List Petty Cash Jul-Des 25'!$V:$V,Sheet1!$A49,'List Petty Cash Jul-Des 25'!$X:$X,Sheet1!$A48) -> 29000 | D49: =+SUMIFS('List Petty Cash Jul-Des 25'!$AB:$AB,'List Petty Cash Jul-Des 25'!$I:$I,Sheet1!D$1,'List Petty Cash Jul-Des 25'!$V:$V,Sheet1!$A49,'List Petty Cash Jul-Des 25'!$X:$X,Sheet1!$A48) -> 18000 | E49: =+SUMIFS('List Petty Cash Jul-Des 25'!$AB:$AB,'List Petty Cash Jul-Des 25'!$I:$I,Sheet1!E$1,'List Petty Cash Jul-Des 25'!$V:$V,Sheet1!$A49,'List Petty Cash Jul-Des 25'!$X:$X,Sheet1!$A48) -> 13000 | F49: =+SUMIFS('List Petty Cash Jul-Des 25'!$AB:$AB,'List Petty Cash Jul-Des 25'!$I:$I,Sheet1!F$1,'List Petty Cash Jul-Des 25'!$V:$V,Sheet1!$A49,'List Petty Cash Jul-Des 25'!$X:$X,Sheet1!$A48) -> 24000 | G49: =+SUMIFS('List Petty Cash Jul-Des 25'!$AB:$AB,'List Petty Cash Jul-Des 25'!$I:$I,Sheet1!G$1,'List Petty Cash Jul-Des 25'!$V:$V,Sheet1!$A49,'List Petty Cash Jul-Des 25'!$X:$X,Sheet1!$A48) -> 1120000 | H49: =+SUMIFS('List Petty Cash Jul-Des 25'!$AB:$AB,'List Petty Cash Jul-Des 25'!$I:$I,Sheet1!H$1,'List Petty Cash Jul-Des 25'!$V:$V,Sheet1!$A49,'List Petty Cash Jul-Des 25'!$X:$X,Sheet1!$A48) -> 1218000 | I49: =+SUM(C49:H49) -> 2422000 | T49: =SUM(T43:T48) -> 319714013
A50: 70009110 | B50: =+VLOOKUP(A50,$A$2:$B$27,2,0) -> Biaya Survey dan Analisa | C50: =+SUMIFS('List Petty Cash Jul-Des 25'!$AB:$AB,'List Petty Cash Jul-Des 25'!$I:$I,Sheet1!C$1,'List Petty Cash Jul-Des 25'!$V:$V,Sheet1!$A50,'List Petty Cash Jul-Des 25'!$X:$X,Sheet1!$A48) -> 1150000 | D50: =+SUMIFS('List Petty Cash Jul-Des 25'!$AB:$AB,'List Petty Cash Jul-Des 25'!$I:$I,Sheet1!D$1,'List Petty Cash Jul-Des 25'!$V:$V,Sheet1!$A50,'List Petty Cash Jul-Des 25'!$X:$X,Sheet1!$A48) -> 700000 | E50: =+SUMIFS('List Petty Cash Jul-Des 25'!$AB:$AB,'List Petty Cash Jul-Des 25'!$I:$I,Sheet1!E$1,'List Petty Cash Jul-Des 25'!$V:$V,Sheet1!$A50,'List Petty Cash Jul-Des 25'!$X:$X,Sheet1!$A48) -> 750000 | F50: =+SUMIFS('List Petty Cash Jul-Des 25'!$AB:$AB,'List Petty Cash Jul-Des 25'!$I:$I,Sheet1!F$1,'List Petty Cash Jul-Des 25'!$V:$V,Sheet1!$A50,'List Petty Cash Jul-Des 25'!$X:$X,Sheet1!$A48) -> 2600000 | G50: =+SUMIFS('List Petty Cash Jul-Des 25'!$AB:$AB,'List Petty Cash Jul-Des 25'!$I:$I,Sheet1!G$1,'List Petty Cash Jul-Des 25'!$V:$V,Sheet1!$A50,'List Petty Cash Jul-Des 25'!$X:$X,Sheet1!$A48) -> 0 | H50: =+SUMIFS('List Petty Cash Jul-Des 25'!$AB:$AB,'List Petty Cash Jul-Des 25'!$I:$I,Sheet1!H$1,'List Petty Cash Jul-Des 25'!$V:$V,Sheet1!$A50,'List Petty Cash Jul-Des 25'!$X:$X,Sheet1!$A48) -> 0 | I50: =+SUM(C50:H50) -> 5200000
A51: 70105321 | B51: =+VLOOKUP(A51,$A$2:$B$27,2,0) -> By Sertifikasi Non Quality Food Safety (Non QFS) | C51: =+SUMIFS('List Petty Cash Jul-Des 25'!$AB:$AB,'List Petty Cash Jul-Des 25'!$I:$I,Sheet1!C$1,'List Petty Cash Jul-Des 25'!$V:$V,Sheet1!$A51,'List Petty Cash Jul-Des 25'!$X:$X,Sheet1!$A48) -> 0 | D51: =+SUMIFS('List Petty Cash Jul-Des 25'!$AB:$AB,'List Petty Cash Jul-Des 25'!$I:$I,Sheet1!D$1,'List Petty Cash Jul-Des 25'!$V:$V,Sheet1!$A51,'List Petty Cash Jul-Des 25'!$X:$X,Sheet1!$A48) -> 0 | E51: =+SUMIFS('List Petty Cash Jul-Des 25'!$AB:$AB,'List Petty Cash Jul-Des 25'!$I:$I,Sheet1!E$1,'List Petty Cash Jul-Des 25'!$V:$V,Sheet1!$A51,'List Petty Cash Jul-Des 25'!$X:$X,Sheet1!$A48) -> 0 | F51: =+SUMIFS('List Petty Cash Jul-Des 25'!$AB:$AB,'List Petty Cash Jul-Des 25'!$I:$I,Sheet1!F$1,'List Petty Cash Jul-Des 25'!$V:$V,Sheet1!$A51,'List Petty Cash Jul-Des 25'!$X:$X,Sheet1!$A48) -> 916000 | G51: =+SUMIFS('List Petty Cash Jul-Des 25'!$AB:$AB,'List Petty Cash Jul-Des 25'!$I:$I,Sheet1!G$1,'List Petty Cash Jul-Des 25'!$V:$V,Sheet1!$A51,'List Petty Cash Jul-Des 25'!$X:$X,Sheet1!$A48) -> 0 | H51: =+SUMIFS('List Petty Cash Jul-Des 25'!$AB:$AB,'List Petty Cash Jul-Des 25'!$I:$I,Sheet1!H$1,'List Petty Cash Jul-Des 25'!$V:$V,Sheet1!$A51,'List Petty Cash Jul-Des 25'!$X:$X,Sheet1!$A48) -> 0 | I51: =+SUM(C51:H51) -> 916000
A52: 70107600 | B52: =+VLOOKUP(A52,$A$2:$B$27,2,0) -> Biaya Konsumsi Kantor | C52: =+SUMIFS('List Petty Cash Jul-Des 25'!$AB:$AB,'List Petty Cash Jul-Des 25'!$I:$I,Sheet1!C$1,'List Petty Cash Jul-Des 25'!$V:$V,Sheet1!$A52,'List Petty Cash Jul-Des 25'!$X:$X,Sheet1!$A48) -> 945000 | D52: =+SUMIFS('List Petty Cash Jul-Des 25'!$AB:$AB,'List Petty Cash Jul-Des 25'!$I:$I,Sheet1!D$1,'List Petty Cash Jul-Des 25'!$V:$V,Sheet1!$A52,'List Petty Cash Jul-Des 25'!$X:$X,Sheet1!$A48) -> 0 | E52: =+SUMIFS('List Petty Cash Jul-Des 25'!$AB:$AB,'List Petty Cash Jul-Des 25'!$I:$I,Sheet1!E$1,'List Petty Cash Jul-Des 25'!$V:$V,Sheet1!$A52,'List Petty Cash Jul-Des 25'!$X:$X,Sheet1!$A48) -> 0 | F52: =+SUMIFS('List Petty Cash Jul-Des 25'!$AB:$AB,'List Petty Cash Jul-Des 25'!$I:$I,Sheet1!F$1,'List Petty Cash Jul-Des 25'!$V:$V,Sheet1!$A52,'List Petty Cash Jul-Des 25'!$X:$X,Sheet1!$A48) -> 0 | G52: =+SUMIFS('List Petty Cash Jul-Des 25'!$AB:$AB,'List Petty Cash Jul-Des 25'!$I:$I,Sheet1!G$1,'List Petty Cash Jul-Des 25'!$V:$V,Sheet1!$A52,'List Petty Cash Jul-Des 25'!$X:$X,Sheet1!$A48) -> 0 | H52: =+SUMIFS('List Petty Cash Jul-Des 25'!$AB:$AB,'List Petty Cash Jul-Des 25'!$I:$I,Sheet1!H$1,'List Petty Cash Jul-Des 25'!$V:$V,Sheet1!$A52,'List Petty Cash Jul-Des 25'!$X:$X,Sheet1!$A48) -> 0 | I52: =+SUM(C52:H52) -> 945000
A53: 70115100 | B53: =+VLOOKUP(A53,$A$2:$B$27,2,0) -> Biaya Riset, Pengembangan, dan Laboratorium | C53: =+SUMIFS('List Petty Cash Jul-Des 25'!$AB:$AB,'List Petty Cash Jul-Des 25'!$I:$I,Sheet1!C$1,'List Petty Cash Jul-Des 25'!$V:$V,Sheet1!$A53,'List Petty Cash Jul-Des 25'!$X:$X,Sheet1!$A48) -> 1578000 | D53: =+SUMIFS('List Petty Cash Jul-Des 25'!$AB:$AB,'List Petty Cash Jul-Des 25'!$I:$I,Sheet1!D$1,'List Petty Cash Jul-Des 25'!$V:$V,Sheet1!$A53,'List Petty Cash Jul-Des 25'!$X:$X,Sheet1!$A48) -> 4209000 | E53: =+SUMIFS('List Petty Cash Jul-Des 25'!$AB:$AB,'List Petty Cash Jul-Des 25'!$I:$I,Sheet1!E$1,'List Petty Cash Jul-Des 25'!$V:$V,Sheet1!$A53,'List Petty Cash Jul-Des 25'!$X:$X,Sheet1!$A48) -> 0 | F53: =+SUMIFS('List Petty Cash Jul-Des 25'!$AB:$AB,'List Petty Cash Jul-Des 25'!$I:$I,Sheet1!F$1,'List Petty Cash Jul-Des 25'!$V:$V,Sheet1!$A53,'List Petty Cash Jul-Des 25'!$X:$X,Sheet1!$A48) -> 0 | G53: =+SUMIFS('List Petty Cash Jul-Des 25'!$AB:$AB,'List Petty Cash Jul-Des 25'!$I:$I,Sheet1!G$1,'List Petty Cash Jul-Des 25'!$V:$V,Sheet1!$A53,'List Petty Cash Jul-Des 25'!$X:$X,Sheet1!$A48) -> 0 | H53: =+SUMIFS('List Petty Cash Jul-Des 25'!$AB:$AB,'List Petty Cash Jul-Des 25'!$I:$I,Sheet1!H$1,'List Petty Cash Jul-Des 25'!$V:$V,Sheet1!$A53,'List Petty Cash Jul-Des 25'!$X:$X,Sheet1!$A48) -> 512300 | I53: =+SUM(C53:H53) -> 6299300
A54: P206D1SLSC
A55: 70001110 | B55: =+VLOOKUP(A55,$A$2:$B$27,2,0) -> Biaya Ekspor lainnya | C55: =+SUMIFS('List Petty Cash Jul-Des 25'!$AB:$AB,'List Petty Cash Jul-Des 25'!$I:$I,Sheet1!C$1,'List Petty Cash Jul-Des 25'!$V:$V,Sheet1!$A55,'List Petty Cash Jul-Des 25'!$X:$X,Sheet1!$A54) -> 0 | D55: =+SUMIFS('List Petty Cash Jul-Des 25'!$AB:$AB,'List Petty Cash Jul-Des 25'!$I:$I,Sheet1!D$1,'List Petty Cash Jul-Des 25'!$V:$V,Sheet1!$A55,'List Petty Cash Jul-Des 25'!$X:$X,Sheet1!$A54) -> 0 | E55: =+SUMIFS('List Petty Cash Jul-Des 25'!$AB:$AB,'List Petty Cash Jul-Des 25'!$I:$I,Sheet1!E$1,'List Petty Cash Jul-Des 25'!$V:$V,Sheet1!$A55,'List Petty Cash Jul-Des 25'!$X:$X,Sheet1!$A54) -> 0 | F55: =+SUMIFS('List Petty Cash Jul-Des 25'!$AB:$AB,'List Petty Cash Jul-Des 25'!$I:$I,Sheet1!F$1,'List Petty Cash Jul-Des 25'!$V:$V,Sheet1!$A55,'List Petty Cash Jul-Des 25'!$X:$X,Sheet1!$A54) -> 0 | G55: =+SUMIFS('List Petty Cash Jul-Des 25'!$AB:$AB,'List Petty Cash Jul-Des 25'!$I:$I,Sheet1!G$1,'List Petty Cash Jul-Des 25'!$V:$V,Sheet1!$A55,'List Petty Cash Jul-Des 25'!$X:$X,Sheet1!$A54) -> 400000 | H55: =+SUMIFS('List Petty Cash Jul-Des 25'!$AB:$AB,'List Petty Cash Jul-Des 25'!$I:$I,Sheet1!H$1,'List Petty Cash Jul-Des 25'!$V:$V,Sheet1!$A55,'List Petty Cash Jul-Des 25'!$X:$X,Sheet1!$A54) -> 500000 | I55: =+SUM(C55:H55) -> 900000
A56: 70009110 | B56: =+VLOOKUP(A56,$A$2:$B$27,2,0) -> Biaya Survey dan Analisa | C56: =+SUMIFS('List Petty Cash Jul-Des 25'!$AB:$AB,'List Petty Cash Jul-Des 25'!$I:$I,Sheet1!C$1,'List Petty Cash Jul-Des 25'!$V:$V,Sheet1!$A56,'List Petty Cash Jul-Des 25'!$X:$X,Sheet1!$A54) -> 350000 | D56: =+SUMIFS('List Petty Cash Jul-Des 25'!$AB:$AB,'List Petty Cash Jul-Des 25'!$I:$I,Sheet1!D$1,'List Petty Cash Jul-Des 25'!$V:$V,Sheet1!$A56,'List Petty Cash Jul-Des 25'!$X:$X,Sheet1!$A54) -> 350000 | E56: =+SUMIFS('List Petty Cash Jul-Des 25'!$AB:$AB,'List Petty Cash Jul-Des 25'!$I:$I,Sheet1!E$1,'List Petty Cash Jul-Des 25'!$V:$V,Sheet1!$A56,'List Petty Cash Jul-Des 25'!$X:$X,Sheet1!$A54) -> 700000 | F56: =+SUMIFS('List Petty Cash Jul-Des 25'!$AB:$AB,'List Petty Cash Jul-Des 25'!$I:$I,Sheet1!F$1,'List Petty Cash Jul-Des 25'!$V:$V,Sheet1!$A56,'List Petty Cash Jul-Des 25'!$X:$X,Sheet1!$A54) -> 400000 | G56: =+SUMIFS('List Petty Cash Jul-Des 25'!$AB:$AB,'List Petty Cash Jul-Des 25'!$I:$I,Sheet1!G$1,'List Petty Cash Jul-Des 25'!$V:$V,Sheet1!$A56,'List Petty Cash Jul-Des 25'!$X:$X,Sheet1!$A54) -> 0 | H56: =+SUMIFS('List Petty Cash Jul-Des 25'!$AB:$AB,'List Petty Cash Jul-Des 25'!$I:$I,Sheet1!H$1,'List Petty Cash Jul-Des 25'!$V:$V,Sheet1!$A56,'List Petty Cash Jul-Des 25'!$X:$X,Sheet1!$A54) -> 0 | I56: =+SUM(C56:H56) -> 1800000
A57: P206D1SLSS
A58: 70001110 | B58: =+VLOOKUP(A58,$A$2:$B$27,2,0) -> Biaya Ekspor lainnya | C58: =+SUMIFS('List Petty Cash Jul-Des 25'!$AB:$AB,'List Petty Cash Jul-Des 25'!$I:$I,Sheet1!C$1,'List Petty Cash Jul-Des 25'!$V:$V,Sheet1!$A58,'List Petty Cash Jul-Des 25'!$X:$X,Sheet1!$A57) -> 0 | D58: =+SUMIFS('List Petty Cash Jul-Des 25'!$AB:$AB,'List Petty Cash Jul-Des 25'!$I:$I,Sheet1!D$1,'List Petty Cash Jul-Des 25'!$V:$V,Sheet1!$A58,'List Petty Cash Jul-Des 25'!$X:$X,Sheet1!$A57) -> 868100 | E58: =+SUMIFS('List Petty Cash Jul-Des 25'!$AB:$AB,'List Petty Cash Jul-Des 25'!$I:$I,Sheet1!E$1,'List Petty Cash Jul-Des 25'!$V:$V,Sheet1!$A58,'List Petty Cash Jul-Des 25'!$X:$X,Sheet1!$A57) -> 0 | F58: =+SUMIFS('List Petty Cash Jul-Des 25'!$AB:$AB,'List Petty Cash Jul-Des 25'!$I:$I,Sheet1!F$1,'List Petty Cash Jul-Des 25'!$V:$V,Sheet1!$A58,'List Petty Cash Jul-Des 25'!$X:$X,Sheet1!$A57) -> 0 | G58: =+SUMIFS('List Petty Cash Jul-Des 25'!$AB:$AB,'List Petty Cash Jul-Des 25'!$I:$I,Sheet1!G$1,'List Petty Cash Jul-Des 25'!$V:$V,Sheet1!$A58,'List Petty Cash Jul-Des 25'!$X:$X,Sheet1!$A57) -> 4250000 | H58: =+SUMIFS('List Petty Cash Jul-Des 25'!$AB:$AB,'List Petty Cash Jul-Des 25'!$I:$I,Sheet1!H$1,'List Petty Cash Jul-Des 25'!$V:$V,Sheet1!$A58,'List Petty Cash Jul-Des 25'!$X:$X,Sheet1!$A57) -> 3900000 | I58: =+SUM(C58:H58) -> 9018100
A59: 70009110 | B59: =+VLOOKUP(A59,$A$2:$B$27,2,0) -> Biaya Survey dan Analisa | C59: =+SUMIFS('List Petty Cash Jul-Des 25'!$AB:$AB,'List Petty Cash Jul-Des 25'!$I:$I,Sheet1!C$1,'List Petty Cash Jul-Des 25'!$V:$V,Sheet1!$A59,'List Petty Cash Jul-Des 25'!$X:$X,Sheet1!$A57) -> 5100000 | D59: =+SUMIFS('List Petty Cash Jul-Des 25'!$AB:$AB,'List Petty Cash Jul-Des 25'!$I:$I,Sheet1!D$1,'List Petty Cash Jul-Des 25'!$V:$V,Sheet1!$A59,'List Petty Cash Jul-Des 25'!$X:$X,Sheet1!$A57) -> 3200000 | E59: =+SUMIFS('List Petty Cash Jul-Des 25'!$AB:$AB,'List Petty Cash Jul-Des 25'!$I:$I,Sheet1!E$1,'List Petty Cash Jul-Des 25'!$V:$V,Sheet1!$A59,'List Petty Cash Jul-Des 25'!$X:$X,Sheet1!$A57) -> 2900000 | F59: =+SUMIFS('List Petty Cash Jul-Des 25'!$AB:$AB,'List Petty Cash Jul-Des 25'!$I:$I,Sheet1!F$1,'List Petty Cash Jul-Des 25'!$V:$V,Sheet1!$A59,'List Petty Cash Jul-Des 25'!$X:$X,Sheet1!$A57) -> 3950000 | G59: =+SUMIFS('List Petty Cash Jul-Des 25'!$AB:$AB,'List Petty Cash Jul-Des 25'!$I:$I,Sheet1!G$1,'List Petty Cash Jul-Des 25'!$V:$V,Sheet1!$A59,'List Petty Cash Jul-Des 25'!$X:$X,Sheet1!$A57) -> 0 | H59: =+SUMIFS('List Petty Cash Jul-Des 25'!$AB:$AB,'List Petty Cash Jul-Des 25'!$I:$I,Sheet1!H$1,'List Petty Cash Jul-Des 25'!$V:$V,Sheet1!$A59,'List Petty Cash Jul-Des 25'!$X:$X,Sheet1!$A57) -> 0 | I59: =+SUM(C59:H59) -> 15150000
A60: 70101202 | B60: =+VLOOKUP(A60,$A$2:$B$27,2,0) -> By Pemeliharaan Kend,ABerat,Mesin-Material Pihak3 | C60: =+SUMIFS('List Petty Cash Jul-Des 25'!$AB:$AB,'List Petty Cash Jul-Des 25'!$I:$I,Sheet1!C$1,'List Petty Cash Jul-Des 25'!$V:$V,Sheet1!$A60,'List Petty Cash Jul-Des 25'!$X:$X,Sheet1!$A57) -> 328000 | D60: =+SUMIFS('List Petty Cash Jul-Des 25'!$AB:$AB,'List Petty Cash Jul-Des 25'!$I:$I,Sheet1!D$1,'List Petty Cash Jul-Des 25'!$V:$V,Sheet1!$A60,'List Petty Cash Jul-Des 25'!$X:$X,Sheet1!$A57) -> 321000 | E60: =+SUMIFS('List Petty Cash Jul-Des 25'!$AB:$AB,'List Petty Cash Jul-Des 25'!$I:$I,Sheet1!E$1,'List Petty Cash Jul-Des 25'!$V:$V,Sheet1!$A60,'List Petty Cash Jul-Des 25'!$X:$X,Sheet1!$A57) -> 298000 | F60: =+SUMIFS('List Petty Cash Jul-Des 25'!$AB:$AB,'List Petty Cash Jul-Des 25'!$I:$I,Sheet1!F$1,'List Petty Cash Jul-Des 25'!$V:$V,Sheet1!$A60,'List Petty Cash Jul-Des 25'!$X:$X,Sheet1!$A57) -> 300000 | G60: =+SUMIFS('List Petty Cash Jul-Des 25'!$AB:$AB,'List Petty Cash Jul-Des 25'!$I:$I,Sheet1!G$1,'List Petty Cash Jul-Des 25'!$V:$V,Sheet1!$A60,'List Petty Cash Jul-Des 25'!$X:$X,Sheet1!$A57) -> 452000 | H60: =+SUMIFS('List Petty Cash Jul-Des 25'!$AB:$AB,'List Petty Cash Jul-Des 25'!$I:$I,Sheet1!H$1,'List Petty Cash Jul-Des 25'!$V:$V,Sheet1!$A60,'List Petty Cash Jul-Des 25'!$X:$X,Sheet1!$A57) -> 310000 | I60: =+SUM(C60:H60) -> 2009000
A61: 70106100 | B61: =+VLOOKUP(A61,$A$2:$B$27,2,0) -> Biaya Transportasi Lokal | C61: =+SUMIFS('List Petty Cash Jul-Des 25'!$AB:$AB,'List Petty Cash Jul-Des 25'!$I:$I,Sheet1!C$1,'List Petty Cash Jul-Des 25'!$V:$V,Sheet1!$A61,'List Petty Cash Jul-Des 25'!$X:$X,Sheet1!$A57) -> 394000 | D61: =+SUMIFS('List Petty Cash Jul-Des 25'!$AB:$AB,'List Petty Cash Jul-Des 25'!$I:$I,Sheet1!D$1,'List Petty Cash Jul-Des 25'!$V:$V,Sheet1!$A61,'List Petty Cash Jul-Des 25'!$X:$X,Sheet1!$A57) -> 382000 | E61: =+SUMIFS('List Petty Cash Jul-Des 25'!$AB:$AB,'List Petty Cash Jul-Des 25'!$I:$I,Sheet1!E$1,'List Petty Cash Jul-Des 25'!$V:$V,Sheet1!$A61,'List Petty Cash Jul-Des 25'!$X:$X,Sheet1!$A57) -> 445000 | F61: =+SUMIFS('List Petty Cash Jul-Des 25'!$AB:$AB,'List Petty Cash Jul-Des 25'!$I:$I,Sheet1!F$1,'List Petty Cash Jul-Des 25'!$V:$V,Sheet1!$A61,'List Petty Cash Jul-Des 25'!$X:$X,Sheet1!$A57) -> 422000 | G61: =+SUMIFS('List Petty Cash Jul-Des 25'!$AB:$AB,'List Petty Cash Jul-Des 25'!$I:$I,Sheet1!G$1,'List Petty Cash Jul-Des 25'!$V:$V,Sheet1!$A61,'List Petty Cash Jul-Des 25'!$X:$X,Sheet1!$A57) -> 432000 | H61: =+SUMIFS('List Petty Cash Jul-Des 25'!$AB:$AB,'List Petty Cash Jul-Des 25'!$I:$I,Sheet1!H$1,'List Petty Cash Jul-Des 25'!$V:$V,Sheet1!$A61,'List Petty Cash Jul-Des 25'!$X:$X,Sheet1!$A57) -> 437000 | I61: =+SUM(C61:H61) -> 2512000
A62: 70108110 | B62: =+VLOOKUP(A62,$A$2:$B$27,2,0) -> Biaya Fotocopy | C62: =+SUMIFS('List Petty Cash Jul-Des 25'!$AB:$AB,'List Petty Cash Jul-Des 25'!$I:$I,Sheet1!C$1,'List Petty Cash Jul-Des 25'!$V:$V,Sheet1!$A62,'List Petty Cash Jul-Des 25'!$X:$X,Sheet1!$A57) -> 22000 | D62: =+SUMIFS('List Petty Cash Jul-Des 25'!$AB:$AB,'List Petty Cash Jul-Des 25'!$I:$I,Sheet1!D$1,'List Petty Cash Jul-Des 25'!$V:$V,Sheet1!$A62,'List Petty Cash Jul-Des 25'!$X:$X,Sheet1!$A57) -> 23000 | E62: =+SUMIFS('List Petty Cash Jul-Des 25'!$AB:$AB,'List Petty Cash Jul-Des 25'!$I:$I,Sheet1!E$1,'List Petty Cash Jul-Des 25'!$V:$V,Sheet1!$A62,'List Petty Cash Jul-Des 25'!$X:$X,Sheet1!$A57) -> 0 | F62: =+SUMIFS('List Petty Cash Jul-Des 25'!$AB:$AB,'List Petty Cash Jul-Des 25'!$I:$I,Sheet1!F$1,'List Petty Cash Jul-Des 25'!$V:$V,Sheet1!$A62,'List Petty Cash Jul-Des 25'!$X:$X,Sheet1!$A57) -> 15000 | G62: =+SUMIFS('List Petty Cash Jul-Des 25'!$AB:$AB,'List Petty Cash Jul-Des 25'!$I:$I,Sheet1!G$1,'List Petty Cash Jul-Des 25'!$V:$V,Sheet1!$A62,'List Petty Cash Jul-Des 25'!$X:$X,Sheet1!$A57) -> 16000 | H62: =+SUMIFS('List Petty Cash Jul-Des 25'!$AB:$AB,'List Petty Cash Jul-Des 25'!$I:$I,Sheet1!H$1,'List Petty Cash Jul-Des 25'!$V:$V,Sheet1!$A62,'List Petty Cash Jul-Des 25'!$X:$X,Sheet1!$A57) -> 28000 | I62: =+SUM(C62:H62) -> 104000
A63: 70119300 | B63: =+VLOOKUP(A63,$A$2:$B$27,2,0) -> Biaya Umum dan Administrasi | C63: =+SUMIFS('List Petty Cash Jul-Des 25'!$AB:$AB,'List Petty Cash Jul-Des 25'!$I:$I,Sheet1!C$1,'List Petty Cash Jul-Des 25'!$V:$V,Sheet1!$A63,'List Petty Cash Jul-Des 25'!$X:$X,Sheet1!$A57) -> 1000000 | D63: =+SUMIFS('List Petty Cash Jul-Des 25'!$AB:$AB,'List Petty Cash Jul-Des 25'!$I:$I,Sheet1!D$1,'List Petty Cash Jul-Des 25'!$V:$V,Sheet1!$A63,'List Petty Cash Jul-Des 25'!$X:$X,Sheet1!$A57) -> 50000 | E63: =+SUMIFS('List Petty Cash Jul-Des 25'!$AB:$AB,'List Petty Cash Jul-Des 25'!$I:$I,Sheet1!E$1,'List Petty Cash Jul-Des 25'!$V:$V,Sheet1!$A63,'List Petty Cash Jul-Des 25'!$X:$X,Sheet1!$A57) -> 0 | F63: =+SUMIFS('List Petty Cash Jul-Des 25'!$AB:$AB,'List Petty Cash Jul-Des 25'!$I:$I,Sheet1!F$1,'List Petty Cash Jul-Des 25'!$V:$V,Sheet1!$A63,'List Petty Cash Jul-Des 25'!$X:$X,Sheet1!$A57) -> 1150000 | G63: =+SUMIFS('List Petty Cash Jul-Des 25'!$AB:$AB,'List Petty Cash Jul-Des 25'!$I:$I,Sheet1!G$1,'List Petty Cash Jul-Des 25'!$V:$V,Sheet1!$A63,'List Petty Cash Jul-Des 25'!$X:$X,Sheet1!$A57) -> 1050000 | H63: =+SUMIFS('List Petty Cash Jul-Des 25'!$AB:$AB,'List Petty Cash Jul-Des 25'!$I:$I,Sheet1!H$1,'List Petty Cash Jul-Des 25'!$V:$V,Sheet1!$A63,'List Petty Cash Jul-Des 25'!$X:$X,Sheet1!$A57) -> 1026000 | I63: =+SUM(C63:H63) -> 4276000
A64: R124BLR
